Workbook

Sheet Planning
A1: Dept | B1: KPI count | C1: KPI's Selected? | D1: All cataloged? | E1: Data been asked for? | F1: All data entered? | G1: Benchmark/ target entered? | H1: Narrative added? | I1: Visual confirmation from dep?
A2: PD | B2: =COUNTIF('KPI Catalog'!A:A, A2)
A3: HR | B3: =COUNTIF('KPI Catalog'!A:A, A3)
A4: TRAN | B4: =COUNTIF('KPI Catalog'!A:A, A4) | E4: 46310
A5: CLERK | B5: =COUNTIF('KPI Catalog'!A:A, A5)
A6: LIB | B6: =COUNTIF('KPI Catalog'!A:A, A6)
A7: 911 | B7: =COUNTIF('KPI Catalog'!A:A, A7)
A8: PIO | B8: =COUNTIF('KPI Catalog'!A:A, A8) | C8: Need KS metrics id's | D8: Need KS metrics id's | E8: 46308
A9: IT | B9: =COUNTIF('KPI Catalog'!A:A, A9)
A10: AIR | B10: =COUNTIF('KPI Catalog'!A:A, A10)
A11: CAO | B11: =COUNTIF('KPI Catalog'!A:A, A11)
A12: CMO | B12: =COUNTIF('KPI Catalog'!A:A, A12)
A13: OE | B13: =COUNTIF('KPI Catalog'!A:A, A13)
A14: COMDEV | B14: =COUNTIF('KPI Catalog'!A:A, A14)
A15: FIN | B15: =COUNTIF('KPI Catalog'!A:A, A15)
A16: PROSP | B16: =COUNTIF('KPI Catalog'!A:A, A16) | E16: 46308
A17: PW | B17: =COUNTIF('KPI Catalog'!A:A, A17)
A18: COURT | B18: =COUNTIF('KPI Catalog'!A:A, A18)
A19: PR | B19: =COUNTIF('KPI Catalog'!A:A, A19)
A20: REC | B20: =COUNTIF('KPI Catalog'!A:A, A20)

Sheet Metric Wireframe (work system)
A1: Key Work System | B1: Key Service | C1: Program | D1: Dashboard ID | E1: Metrics | F1: Data? | G1: Target? | H1: Benchmark? | I1: Narrative? | J1: Dash Status | K1: Note
A2: Leadership & Governance (ws1) | B2: Administrative Leadership & Governance (ks1) | C2: Strategic Planning | D2: p2
C3: Organizational Performance Management | D3: p3
C4: Compliance Oversight | D4: p4
C5: Customer Service | D5: p5
B6: City Clerk & Records Management (ks2) Records Request Response Rate Agenda Posting time Liquor and marijuana license turnaround Business License Turnaround Voter turnout (%) | C6: Records Management | D6: p7 | E6: Records request response rate
C7: Elections Administration | D7: p8 | E7: Voter turnout (%)
E8: Response rate for public election related questions
E9: Logic and accuracy test
E10: Click through rate on City's election landing page
C11: Council/Board Support | D11: p6 | E11: Agenda posting time
C12: Licensing | D12: p29 | E12: Liquor and marijuana license turnaround
E13: Business license turnaround time
B14: Public Information & Community Engagement (ks3) | C14: Public Outreach | D14: p11 | E14: SeeClickFix requests
E15: Website views + social media post link clicks + news letter open rate
C16: Social Media | D16: p12 | E16: Social media engagement rate (FB, IG, TT) | J16: Online
E17: Social media audience growth (FB, IG, TT) | J17: Online
E18: Engage Durango: First time visitors vs returning
E19: Visitors + Contributors
E20: Engage Durango: Contributions
A21: Financial & Internal Services (ws2) | B21: Financial Management & Accountability (ks4) | C21: Budgeting & Forecasting | D21: p15 | E21: Expenditure Budget to Actuals by Goal and Fund (TBD on actuals report by Goal)
E22: Revenue Budget to Actuals by Fund and Source (i.e. Sales Tax as a whole)
C23: Grants Management | D23: p16 | E23: Percent of revenue from Grants - Utilization/execution of grant revenue (%)
C24: Procurement | D24: p17 | E24: All POs: classified blanket POs, open, dollar amounts, etc. Tracking of purchase orders (open POs, POs that are negative, etc.);
E25: Zip code of POS- Percent or count of local vendors
E26: Number of p-card transactions and dollars; (Phase 2: by type of transaction..travel, operational, etc.)
E27: Procurement piece of projects (open, stage of the project, etc.);
E28: Purchasing Exemptions by Type (16)
C29: Vendor Management | D29: p98 | E29: Total cost to a vendor ($)
C30: Accounting & Reporting | D30: p18 | E30: success rate in deterring fraudulent transactions on bank account
E31: cash reconciliations in timely manner
E32: savings from using 3rd party providers ie Hauler Logic for water dock
E33: outstanding checks for payroll stay within 1 year
E34: outstanding checks for a/p vendors 1 year
E35: Tax Based Revenue
E36: closing the month on a regular schedule, ie 10th of month unless a holiday week - Including total pending/unreconcilled transaction
E37: A/R billing monthly
E38: MAR Aging -outstanding payments less than 60 days out
C39: Financial Compliance | D39: p99 | E39: Meeting deadlines to State Auditor for annual reports for Airport, COD & ETSA
B40: Human Resources & Workforce Development (ks5) Employee Engagement Rate (EE survey) Hiring: time to hire from NeoGov Retain & Develop: Internal promotion rate Retain & develop: turnover rate by voluntary vs not | C40: Learning & Development | D40: p22 | E40: CFT participation
E41: Utilization of tuition reimbursement program
E42: Utilization of professional development budget
C43: Recruitment & Retention | D43: p24 | E43: Retain: Employee Engagement Rate (EE survey)
E44: Attracting: job posting view
E45: Attracting: applications per recruitment
E46: Attracting: traffic source data
E47: Hiring: time to hire from NeoGov
E48: Hiring: offer acceptance rate
E49: Retain & develop: vacancy rate
E50: Retain & develop: 1st year retention
E51: Retain & Develop: Internal promotion rate
E52: Retain & develop: turnover rate
C53: Compensation & Benefits | D53: p25 | E53: Exit survey: satisfaction with compensation and benefits
E54: Employee Engagement Survey: satisfaction with compensation and benefits
B55: Legal Services (ks6) | C55: Legal Counsel | D55: p26
C56: Risk Management | D56: p27 | E56: DOT Compliance Score (employees with CDLs)
E57: EMOD (experience modification) for Work Comp - annually from Pinnacol, score dictates premium
E58: Work Comp (loss run report?)
E59: Property casualty claims (by department, dollar amount)
E60: Accident Review Board - Average or cumulative severity?
E61: Safety Training
C62: Code Compliance | D62: p28
B63: Information Technology Services (ks7) Phish Prone Rate Network Uptime PIT Scores Help Desk Resolution within SLA IT Liaison Survey | C63: Network & Infrastructure Management | D63: p30 | E63: Network Uptime (Planned vs. Unplanned) | J63: Online
C64: Cybersecurity | D64: p31 | E64: Organization phish prone rate | J64: Online
C65: Business Applications Support | D65: p32 | E65: Tickets per Application
C66: GIS | D66: p33 | E66: Address Requirest within SLA
E67: New Address NENA Compliance
E68: NENA Compliance (overall)
C69: Help Desk | D69: p34 | E69: PIT survey
E70: Ticket closure within SLA
E71: Critical Ticket Count
A72: Community Growth & Economic Vitality (ws3) | B72: Community Development & Planning (ks8) Total Regulated Affordable Housing Units Acres of land annexed and sorted by zone Building permits issued within 48 hours Land use permits: Median number of days for application submittal to approval/completion (extreme outliers) - pre app, sign permits, limited use permits, | C72: Long Range Comprehensive Planning | D72: p35 | E72: Acres of land annexed and sorted by zone
E73: Could plug in metrics from prosperity
E74: Dwelling units created each year/existing units = percent increase
C75: Development Review & Permitting (inspections) | D75: p36 | E75: Median number of days for application submittal to approval/completion (extreme outliers) - pre app, sign permits, limited use permits,
E76: Median number of days for application submittal to approval/completion (extreme outliers) - pre app in two weeks/or other SLA
E77: % of applications with a complete review within 21 days
E78: % of solar, roofing, windows, siding permits issued in 48 hours
C79: Housing Initiatives | D79: p37 | E79: total regulated affordable housing units | J79: Online
E80: building permits issued under prop 123
E81: total residential building permits
E82: ADU Owner Occupancy Compliance - 50% rn
E83: Dwelling units created each year/existing units = percent increase
E84: Percent of alteration certificates completed within the 3rd avenue district
C85: Historical Preservation | D85: p38 | E85: Percent of alteration certificates completed within the 3rd avenue district
B86: Economic Prosperity & Business Support (ks9) Annual URA Income as a rate of growth - broken out individually by URA and total Occupancy Rate (Year over Year Quarterly) + Visitor Spend (annual YOY) | C86: Community Investments, Partnerships, and Grant Making | D86: p100 | E86: Number of grants awarded Annually
E87: Local Spend from grants awarded Annually
C88: Business Support Services | D88: p40 | E88: Annual URA Income as a rate of growth - broken out individually by URA and total
C89: Destination Marketing and Management (Tourism) | D89: p43 | E89: Occupancy Rate (Year over Year Quarterly)
E90: Visitor Spend (Annual Year over Year)
E91: Total Nights on Tour Sales (annual) | J91: Online
E92: Welcome Center Door Count
B93: Sustainability & Environmental Stewardship (ks10) | C93: Energy, Climate and Sustainability Programs | D93: p44
C94: Waste Reduction (recycling) | D94: p45
C95: Water Conservation | D95: p46
C96: Urban Forestry | D96: p47
C97: Resilience Planning | D97: p48
A98: Public Safety (ws4) | B98: Public Safety Services (ks11) Violent/property crime trend Traffic injury trend Fatal crash trend Response time - segmented into 911 and non emergent response Call volume - officer initiated vs citizen initiated Crime clearance rate - solvability by type. ticket, arrest, transfer out, etc. | C98: Police Patrol | D98: p49 | E98: Response Time
E99: Total incidents - officer initiatied/proactivity vs dispatch call for service by incident type? - outcome would be more proactivity.
E100: Proactive vs reactive time
...

Sheet Metric Wireframe (goal area)
A1: Goal Area | B1: Objective | C1: Key Service | D1: Key Service | E1: Metric [highlighted = most relevant kpi from the key service] | F1: Data? | G1: Target? | H1: Benchmark? | I1: Narrative? | J1: Dash Status | K1: Review note
A2: Organizational Stewardship | B2: 1.1 Ensure a financially sustainable and innovation-led framework that thrives on building effective partnerships to alleviate city costs, and harnesses the power of technology for efficiency. | C2: Information Technology Services | D2: show how well technology is making the city more efficient | E2: Phish Prone Rate
E3: Network Uptime
E4: PIT Scores
E5: Help Desk Resolution within SLA
E6: IT Liaison Survey
C7: Economic Prosperity and Business Support | D7: adds revenue that can strengthen the city's longterm financial position | E7: Annual URA Income as a rate of growth - broken out individually by URA and total
E8: Occupancy Rate (Year over Year Quarterly) + Visitor Spend (annual YOY)
C9: Financial Management & Accountability | D9: budget, revenue collection, and financial compliance are the core long term financial health
C10: Administrative Leadership and Governance | D10: leadership sets the strategic and budget priorities
C11: Legal Services | D11: risk management and legal counsel protect the city from claims and losses that would cost taxpayers
B12: 1.2 Foster strong community group partnerships through effective communication and a commitment to diversity, equity, and inclusivity efforts while focusing on increased accessibility of services for underserved communities. | C12: Administrative Leadership and Governance | D12: leadership builds city partnerships and sets DEI commitment
C13: Public Information & Community Engagement | D13: outreach and engagement initiatives are how the city reaches community groups and underserved residents
B14: 1.3 Advance a systematic approach toward environmental sustainability through focused efforts to conserve resources and mitigate environmental stressors by meeting or exceeding local, state, and national standards. | C14: Sustainability & Environmental Stewardship | D14: the city's main tools for conserving resources
C15: Public Works & Municipal Services | D15: decide whether the city meets environmental standards
A16: Innovative Housing and Economic Development | B16: 2.1 Cultivate innovative housing solutions and partnerships to advance the development of a variety of housing options to support a multigenerational and mixed-income community by narrowing the gap between income levels and housing affordability. | C16: Community Development & Planning | D16: shows progress on housing options for all income levels | E16: Total Regulated Affordable Housing Units
E17: Acres of land annexed and sorted by zone
E18: Building permits issued within 48 hours
E19: Land use permits: Median number of days for application submittal to approval/completion (extreme outliers) - pre app, sign permits, limited use permits,
B20: 2.2 Stimulate economic progress and resiliency through strategic collaboration, nurturing entrepreneurship and supporting business growth through well-designed City services and programs. | C20: City Clerk and Records Management | D20: fast business and liquor licensing turnaround is a "well designed city service" that helps business grow and open | E20: Records Request Response Rate
E21: Agenda Posting time
E22: Liquor and marijuana license turnaround
E23: Business License Turnaround
E24: Voter turnout (%)
C25: Community Development & Planning | D25: shows how well city services support businesses and developers | E25: Total Regulated Affordable Housing Units
E26: Acres of land annexed and sorted by zone
E27: Building permits issued within 48 hours
E28: Land use permits: Median number of days for application submittal to approval/completion (extreme outliers) - pre app, sign permits, limited use permits,
C29: Economic Prosperity & Business Support | D29: measures the health of the local tourism and business economy | E29: Annual URA Income as a rate of growth - broken out individually by URA and total
E30: Occupancy Rate (Year over Year Quarterly) + Visitor Spend (annual YOY)
B31: 2.3 Preserve and enhance Durango’s distinctive appeal and competitive edge as an attractive community by engaging in community-driven planning, strategic infrastructure investments, and partnerships between the public and private sectors. | C31: Community Development & Planning | D31: shape how durango grows while protecting its character | E31: Total Regulated Affordable Housing Units
E32: Acres of land annexed and sorted by zone
E33: Building permits issued within 48 hours
E34: Land use permits: Median number of days for application submittal to approval/completion (extreme outliers) - pre app, sign permits, limited use permits,
C35: Economic Prosperity & Business Support | D35: shows return of public-private investments in key districts | E35: Annual URA Income as a rate of growth - broken out individually by URA and total
E36: Occupancy Rate (Year over Year Quarterly) + Visitor Spend (annual YOY)
A37: Safety and Quality of Life | B37: 3.1 Ensure the seamless operation and continual enhancement of police, code enforcement, 911 communications, and contracted emergency services to advance public safety measures, and cooperative emergency preparedness to reinforce community trust to reduce targeted crime rates and enhance the overall sense of safety. | C37: Legal Services | D37: code compliance and prosecution support the enforcemet work that keeps the community safe
C38: Public Safety Services | D38: show how safe the community is and how well the police and 911 perform | E38: Violent/property crime trend
E39: Traffic injury trend
E40: Fatal crash trend
E41: Response time - segmented into 911 and non emergent response
E42: Call volume - officer initiated vs citizen initiated
E43: Crime clearance rate - solvability by type. ticket, arrest, transfer out, etc.
C44: Municipal Court | D44: show the court reducing repeat offenses and supporting long term community safety | E44: Number of specialty court cases resolved through graduating
B45: 3.2 Provide sustainable and inclusive arts, literacy, culture, and recreation opportunities by listening to the community’s diverse needs. | C45: Library & Learning Services | D45: shows how much residents use the librarys literacy and cultural offerings | E45: visitation
E46: circulation
C47: Recreation & Community Programs | D47: shows whether recreation meets residents' diverse needs | E47: Total pass retention
E48: Total program capacity
E49: Community survey results (with service population or another metric??)
E50: Social media engagement rate - P&R channels only
B51: 3.3 Continue the ongoing maintenance, preservation, and acquisition of quality parks, trails, and natural lands. | C51: Parks and Open Space Management | D51: shows whether parks and open space are being maintained and preservefd | E51: ops/capital budget per acre of park space - overlay CoD population
E52: ops/capital budget per 1000 acres of open space - overlay CoD population
E53: COMMUNITY SURVEY: Quality of experience results
A54: Reliable Infrastructure and Community Connectivity | B54: 4.1 Provide consistently safe, reliable, and accessible mobility and transportation services throughout the community. | C54: Transit Services | D54: shows how many residents rely on transit for safe, accessible travel | E54: Total Transit Ridership
E55: Total Rider Dependency / Choice Rider
E56: Vacancy Rate and Occupancy Rate
B57: 4.2 Invest in transportation and infrastructure systems that maximize safety, mobility, innovation, accessibility, and user satisfaction. | C57: Public Works & Municipal Services | D57: where transportation investments are delivered
B58: 4.3 Uphold a continuous, high-efficiency system for managing water, wastewater, and stormwater systems that adhere to strict compliance with environmental regulations. | C58: Asset Management | D58: proper asset management keeps the utility systems reliable and compliant
C59: Public Works & Municipal Services | D59: systems directly tied to this objective
B60: 4.4 Maintain and enhance DRO’s status as the key regional hub for aviation services by delivering safe, efficient, and sustainable airport operations and promoting a competitive airline environment. | C60: Airport Operations | D60: what keeps DRO a competitive regional hub
B61: 4.5 Provide resources supporting maintenance, expansion, and ensuring reliable and secure IT infrastructure management. | C61: Asset Management | D61: proper asset management keeps the IT systems reliable and compliant
C62: Information Technology Services | D62: shows how reliable and secure city it systems are | E62: Phish Prone Rate
E63: Network Uptime
E64: PIT Scores
E65: Help Desk Resolution within SLA
E66: IT Liaison Survey
B67: 4.6 Continue planned expansion of City surface transportation system and maintain existing assets within Right of Way | C67: Public Works & Municipal Services | D67: streets and assets within the right of way
C68: Transit Services (ks14) | D68: shows how well the transportation system and right of way are being used | E68: Total Transit Ridership
E69: Total Rider Dependency / Choice Rider
E70: Vacancy Rate and Occupancy Rate
A71: Engaged and Informed Community | B71: 5.1 Champion a systematic approach where community engagement, education, outreach and communication thrive as cornerstones of civic involvement. | C71: Public Information & Community Engagement | D71: engagement on city channels shows whether outreach is drawing residents
C72: City Clerk and Records Management | D72: voter turnout and timely agenda posting show how well residents can take part in local government | E72: Records Request Response Rate
E73: Agenda Posting time
E74: Liquor and marijuana license turnaround
E75: Business License Turnaround
E76: Voter turnout (%)
B77: 5.2 Cultivate and leverage communication systems through convenient, open, and accessible information. | C77: City Clerk and Records Management | D77: records request response times and agenda posting show how quickly residents can get pubhlic info | E77: Records Request Response Rate
E78: Agenda Posting time
E79: Liquor and marijuana license turnaround
E80: Business License Turnaround
E81: Voter turnout (%)
C82: Public Information & Community Engagement | D82: website, socials, and newsletter reach show how easily residents can find city info
C83: Library & Learning Services | D83: shows residents have free, convenient access to info and learning resources | E83: visitation
E84: circulation
C85: Financial Management & Accountability | D85: financial transparency
A86: Strategic Workforce Development | B86: 6.1 Foster a workplace culture designed to attract and retain diverse, skilled and engaged staff members, which enhances employee satisfaction, engagement and performance by offering an environment reflective of the City’s commitment to excellence and strategic alignment. | C86: Human Resources & Workforce Development | D86: show if the city's workplace culture attracts and keeps skilled staff | E86: Employee Engagement Rate (EE survey)
E87: Hiring: time to hire from NeoGov
E88: Retain & Develop: Internal promotion rate
E89: Retain & develop: turnover rate by voluntary vs not
C90: Community Development & Planning | D90: affordability is a major factor is whether the city can attract and keep employees in durango | E90: Total Regulated Affordable Housing Units
E91: Acres of land annexed and sorted by zone
E92: Building permits issued within 48 hours
E93: Land use permits: Median number of days for application submittal to approval/completion (extreme outliers) - pre app, sign permits, limited use permits,
B94: 6.2 Ensure a comprehensive career progression strategy that readies employees for key roles and leadership positions in alignment with the City’s long-term goals. | C94: Administrative Leadership and Governance | D94: Leadership programs prepare employees to step into key roles (CFT involvement and Strat Planning)
C95: Human Resources & Workforce Development | D95: shows whether employees are being developed for key leaderhip roles | E95: Employee Engagement Rate (EE survey)
E96: Hiring: time to hire from NeoGov
E97: Retain & Develop: Internal promotion rate
E98: Retain & develop: turnover rate by voluntary vs not
B99: 6.3 Facilitate workforce preparedness through management of City processes, capacity and capability, ensuring optimization of staff skill levels designed to meet operational needs and evolving municipal demands. | C99: Information Technology Services | D99: security awareness and effective IT support show staff have the skills and tools to do their jobs | E99: Phish Prone Rate
E100: Network Uptime
...

Sheet KPI Catalog
A1: Dept | B1: KPI ID | C1: KPI Name | D1: Level | E1: Dashboard Item ID | F1: Item Name (auto) | G1: Also Show Under | H1: Also Under (auto) | I1: Unit | J1: Decimals | K1: Higher Is Better | L1: Status Based On | M1: On Track Within % | N1: Off Track Beyond % | O1: Drives Status | P1: Update Frequency | Q1: Owner | R1: Source | S1: Description | T1: Footnote | U1: Gauge Role (auto)
A2: =LEFT(B2, FIND("-", B2) - 1) | B2: 911-COMPLAINTRES | C2: Complaint Resolution | D2: Program | E2: p101 | F2: =IF(E2="","",IFERROR(IF(INDEX('Dashboard Items'!$B$2:$B$495,MATCH(E2,'Dashboard Items'!$A$2:$A$495,0))="Objective","Objectives go in the next column",IF(OR(D2="",INDEX('Dashboard Items'!$B$2:$B$495,MATCH(E2,'Dashboard Items'!$A$2:$A$495,0))=D2),INDEX('Dashboard Items'!$C$2:$C$495,MATCH(E2,'Dashboard Items'!$A$2:$A$495,0)),"Level does not match ID")),"ID not found")) | H2: =IF(G2="","",IF(ISNUMBER(SEARCH(",",G2)),"Several items (the script lists them)",IFERROR(INDEX('Dashboard Items'!$B$2:$B$495,MATCH(G2,'Dashboard Items'!$A$2:$A$495,0))&": "&INDEX('Dashboard Items'!$C$2:$C$495,MATCH(G2,'Dashboard Items'!$A$2:$A$495,0)),"ID not found"))) | I2: number | J2: 2 | K2: Yes | L2: Target | M2: 0 | N2: 0 | O2: Yes | P2: Every year | Q2: Chief of Police | U2: =IF(B2="","",IF(IF(D2<>"",D2,IFERROR(INDEX('Dashboard Items'!$B$2:$B$495,MATCH(E2,'Dashboard Items'!$A$2:$A$495,0)),""))="Key Service",IF(O2="No","Key Service: shown, not counted","Counts in Key Service gauge"),IF(IF(D2<>"",D2,IFERROR(INDEX('Dashboard Items'!$B$2:$B$495,MATCH(E2,'Dashboard Items'!$A$2:$A$495,0)),""))="Program",IF(ISNUMBER(SEARCH("ks",G2)),IF(O2="No","Program, also at Key Service: not counted","Counts in Key Service gauge + sets Program chip"),IF(O2="No","Program: shown, no status chip","Sets Program status chip")),IF(IF(D2<>"",D2,IFERROR(INDEX('Dashboard Items'!$B$2:$B$495,MATCH(E2,'Dashboard Items'!$A$2:$A$495,0)),""))="Work System","Work System: shown, not counted","Check Level"))))
A3: =LEFT(B3, FIND("-", B3) - 1) | B3: 911-COMSATISFACTION | C3: Community Satisfaction | D3: Program | E3: p102 | F3: =IF(E3="","",IFERROR(IF(INDEX('Dashboard Items'!$B$2:$B$495,MATCH(E3,'Dashboard Items'!$A$2:$A$495,0))="Objective","Objectives go in the next column",IF(OR(D3="",INDEX('Dashboard Items'!$B$2:$B$495,MATCH(E3,'Dashboard Items'!$A$2:$A$495,0))=D3),INDEX('Dashboard Items'!$C$2:$C$495,MATCH(E3,'Dashboard Items'!$A$2:$A$495,0)),"Level does not match ID")),"ID not found")) | G3: p102 | H3: =IF(G3="","",IF(ISNUMBER(SEARCH(",",G3)),"Several items (the script lists them)",IFERROR(INDEX('Dashboard Items'!$B$2:$B$495,MATCH(G3,'Dashboard Items'!$A$2:$A$495,0))&": "&INDEX('Dashboard Items'!$C$2:$C$495,MATCH(G3,'Dashboard Items'!$A$2:$A$495,0)),"ID not found"))) | I3: number | J3: 2 | K3: Yes | L3: Target | M3: 0 | N3: 0 | O3: Yes | P3: Every year | Q3: Chief of Police | U3: =IF(B3="","",IF(IF(D3<>"",D3,IFERROR(INDEX('Dashboard Items'!$B$2:$B$495,MATCH(E3,'Dashboard Items'!$A$2:$A$495,0)),""))="Key Service",IF(O3="No","Key Service: shown, not counted","Counts in Key Service gauge"),IF(IF(D3<>"",D3,IFERROR(INDEX('Dashboard Items'!$B$2:$B$495,MATCH(E3,'Dashboard Items'!$A$2:$A$495,0)),""))="Program",IF(ISNUMBER(SEARCH("ks",G3)),IF(O3="No","Program, also at Key Service: not counted","Counts in Key Service gauge + sets Program chip"),IF(O3="No","Program: shown, no status chip","Sets Program status chip")),IF(IF(D3<>"",D3,IFERROR(INDEX('Dashboard Items'!$B$2:$B$495,MATCH(E3,'Dashboard Items'!$A$2:$A$495,0)),""))="Work System","Work System: shown, not counted","Check Level"))))
A4: =LEFT(B4, FIND("-", B4) - 1) | B4: 911-DISPATCHTIME | C4: 911 Answer Times | D4: Key Service | E4: ks11 | F4: =IF(E4="","",IFERROR(IF(INDEX('Dashboard Items'!$B$2:$B$495,MATCH(E4,'Dashboard Items'!$A$2:$A$495,0))="Objective","Objectives go in the next column",IF(OR(D4="",INDEX('Dashboard Items'!$B$2:$B$495,MATCH(E4,'Dashboard Items'!$A$2:$A$495,0))=D4),INDEX('Dashboard Items'!$C$2:$C$495,MATCH(E4,'Dashboard Items'!$A$2:$A$495,0)),"Level does not match ID")),"ID not found")) | G4: p101 | H4: =IF(G4="","",IF(ISNUMBER(SEARCH(",",G4)),"Several items (the script lists them)",IFERROR(INDEX('Dashboard Items'!$B$2:$B$495,MATCH(G4,'Dashboard Items'!$A$2:$A$495,0))&": "&INDEX('Dashboard Items'!$C$2:$C$495,MATCH(G4,'Dashboard Items'!$A$2:$A$495,0)),"ID not found"))) | I4: percent | J4: 0 | K4: Yes | L4: Target | M4: 0 | N4: 0 | O4: Yes | P4: Every Quarter | Q4: 911 Director | R4: Intrado 911 call data, via the Powermetrics reporting module (automated) | S4: Share of 911 calls answered within 15 seconds and within 20 seconds each fiscal year, each compared with its national standard. | T4: Target and benchmark (NENA standard, as set by the 911 center): 95% of calls answered within 15 seconds and 90% within 20 seconds. The center has been at critical staffing since Q2 2021, which has lengthened answer times; results remain above the standard. | U4: =IF(B4="","",IF(IF(D4<>"",D4,IFERROR(INDEX('Dashboard Items'!$B$2:$B$495,MATCH(E4,'Dashboard Items'!$A$2:$A$495,0)),""))="Key Service",IF(O4="No","Key Service: shown, not counted","Counts in Key Service gauge"),IF(IF(D4<>"",D4,IFERROR(INDEX('Dashboard Items'!$B$2:$B$495,MATCH(E4,'Dashboard Items'!$A$2:$A$495,0)),""))="Program",IF(ISNUMBER(SEARCH("ks",G4)),IF(O4="No","Program, also at Key Service: not counted","Counts in Key Service gauge + sets Program chip"),IF(O4="No","Program: shown, no status chip","Sets Program status chip")),IF(IF(D4<>"",D4,IFERROR(INDEX('Dashboard Items'!$B$2:$B$495,MATCH(E4,'Dashboard Items'!$A$2:$A$495,0)),""))="Work System","Work System: shown, not counted","Check Level"))))
A5: =LEFT(B5, FIND("-", B5) - 1) | B5: 911-NFPADROPTIME | C5: NFPA Drop Times; | D5: Program | E5: p101 | F5: =IF(E5="","",IFERROR(IF(INDEX('Dashboard Items'!$B$2:$B$495,MATCH(E5,'Dashboard Items'!$A$2:$A$495,0))="Objective","Objectives go in the next column",IF(OR(D5="",INDEX('Dashboard Items'!$B$2:$B$495,MATCH(E5,'Dashboard Items'!$A$2:$A$495,0))=D5),INDEX('Dashboard Items'!$C$2:$C$495,MATCH(E5,'Dashboard Items'!$A$2:$A$495,0)),"Level does not match ID")),"ID not found")) | H5: =IF(G5="","",IF(ISNUMBER(SEARCH(",",G5)),"Several items (the script lists them)",IFERROR(INDEX('Dashboard Items'!$B$2:$B$495,MATCH(G5,'Dashboard Items'!$A$2:$A$495,0))&": "&INDEX('Dashboard Items'!$C$2:$C$495,MATCH(G5,'Dashboard Items'!$A$2:$A$495,0)),"ID not found"))) | I5: number | J5: 2 | K5: Yes | L5: Target | M5: 0 | N5: 0 | O5: Yes | P5: Every year | Q5: Chief of Police | U5: =IF(B5="","",IF(IF(D5<>"",D5,IFERROR(INDEX('Dashboard Items'!$B$2:$B$495,MATCH(E5,'Dashboard Items'!$A$2:$A$495,0)),""))="Key Service",IF(O5="No","Key Service: shown, not counted","Counts in Key Service gauge"),IF(IF(D5<>"",D5,IFERROR(INDEX('Dashboard Items'!$B$2:$B$495,MATCH(E5,'Dashboard Items'!$A$2:$A$495,0)),""))="Program",IF(ISNUMBER(SEARCH("ks",G5)),IF(O5="No","Program, also at Key Service: not counted","Counts in Key Service gauge + sets Program chip"),IF(O5="No","Program: shown, no status chip","Sets Program status chip")),IF(IF(D5<>"",D5,IFERROR(INDEX('Dashboard Items'!$B$2:$B$495,MATCH(E5,'Dashboard Items'!$A$2:$A$495,0)),""))="Work System","Work System: shown, not counted","Check Level"))))
A6: =LEFT(B6, FIND("-", B6) - 1) | B6: 911-QAQC | C6: Quality Assurance; | D6: Program | E6: p101 | F6: =IF(E6="","",IFERROR(IF(INDEX('Dashboard Items'!$B$2:$B$495,MATCH(E6,'Dashboard Items'!$A$2:$A$495,0))="Objective","Objectives go in the next column",IF(OR(D6="",INDEX('Dashboard Items'!$B$2:$B$495,MATCH(E6,'Dashboard Items'!$A$2:$A$495,0))=D6),INDEX('Dashboard Items'!$C$2:$C$495,MATCH(E6,'Dashboard Items'!$A$2:$A$495,0)),"Level does not match ID")),"ID not found")) | G6: p102 | H6: =IF(G6="","",IF(ISNUMBER(SEARCH(",",G6)),"Several items (the script lists them)",IFERROR(INDEX('Dashboard Items'!$B$2:$B$495,MATCH(G6,'Dashboard Items'!$A$2:$A$495,0))&": "&INDEX('Dashboard Items'!$C$2:$C$495,MATCH(G6,'Dashboard Items'!$A$2:$A$495,0)),"ID not found"))) | I6: number | J6: 2 | K6: Yes | L6: Target | M6: 0 | N6: 0 | O6: Yes | P6: Every year | Q6: Chief of Police | U6: =IF(B6="","",IF(IF(D6<>"",D6,IFERROR(INDEX('Dashboard Items'!$B$2:$B$495,MATCH(E6,'Dashboard Items'!$A$2:$A$495,0)),""))="Key Service",IF(O6="No","Key Service: shown, not counted","Counts in Key Service gauge"),IF(IF(D6<>"",D6,IFERROR(INDEX('Dashboard Items'!$B$2:$B$495,MATCH(E6,'Dashboard Items'!$A$2:$A$495,0)),""))="Program",IF(ISNUMBER(SEARCH("ks",G6)),IF(O6="No","Program, also at Key Service: not counted","Counts in Key Service gauge + sets Program chip"),IF(O6="No","Program: shown, no status chip","Sets Program status chip")),IF(IF(D6<>"",D6,IFERROR(INDEX('Dashboard Items'!$B$2:$B$495,MATCH(E6,'Dashboard Items'!$A$2:$A$495,0)),""))="Work System","Work System: shown, not counted","Check Level"))))
A7: =LEFT(B7, FIND("-", B7) - 1) | B7: 911-SERVICEUPTIME | C7: 911 Services uptime (could roll up to system wide uptime under IT services); | D7: Program | E7: p104 | F7: =IF(E7="","",IFERROR(IF(INDEX('Dashboard Items'!$B$2:$B$495,MATCH(E7,'Dashboard Items'!$A$2:$A$495,0))="Objective","Objectives go in the next column",IF(OR(D7="",INDEX('Dashboard Items'!$B$2:$B$495,MATCH(E7,'Dashboard Items'!$A$2:$A$495,0))=D7),INDEX('Dashboard Items'!$C$2:$C$495,MATCH(E7,'Dashboard Items'!$A$2:$A$495,0)),"Level does not match ID")),"ID not found")) | H7: =IF(G7="","",IF(ISNUMBER(SEARCH(",",G7)),"Several items (the script lists them)",IFERROR(INDEX('Dashboard Items'!$B$2:$B$495,MATCH(G7,'Dashboard Items'!$A$2:$A$495,0))&": "&INDEX('Dashboard Items'!$C$2:$C$495,MATCH(G7,'Dashboard Items'!$A$2:$A$495,0)),"ID not found"))) | I7: number | J7: 2 | K7: Yes | L7: Target | M7: 0 | N7: 0 | O7: Yes | P7: Every year | Q7: Chief of Police | U7: =IF(B7="","",IF(IF(D7<>"",D7,IFERROR(INDEX('Dashboard Items'!$B$2:$B$495,MATCH(E7,'Dashboard Items'!$A$2:$A$495,0)),""))="Key Service",IF(O7="No","Key Service: shown, not counted","Counts in Key Service gauge"),IF(IF(D7<>"",D7,IFERROR(INDEX('Dashboard Items'!$B$2:$B$495,MATCH(E7,'Dashboard Items'!$A$2:$A$495,0)),""))="Program",IF(ISNUMBER(SEARCH("ks",G7)),IF(O7="No","Program, also at Key Service: not counted","Counts in Key Service gauge + sets Program chip"),IF(O7="No","Program: shown, no status chip","Sets Program status chip")),IF(IF(D7<>"",D7,IFERROR(INDEX('Dashboard Items'!$B$2:$B$495,MATCH(E7,'Dashboard Items'!$A$2:$A$495,0)),""))="Work System","Work System: shown, not counted","Check Level"))))
A8: =LEFT(B8, FIND("-", B8) - 1) | B8: 911-STAFFING | C8: Staffing metrics: Vacancy, turnover, internal promotion? | D8: Key Service | E8: ks11 | F8: =IF(E8="","",IFERROR(IF(INDEX('Dashboard Items'!$B$2:$B$495,MATCH(E8,'Dashboard Items'!$A$2:$A$495,0))="Objective","Objectives go in the next column",IF(OR(D8="",INDEX('Dashboard Items'!$B$2:$B$495,MATCH(E8,'Dashboard Items'!$A$2:$A$495,0))=D8),INDEX('Dashboard Items'!$C$2:$C$495,MATCH(E8,'Dashboard Items'!$A$2:$A$495,0)),"Level does not match ID")),"ID not found")) | H8: =IF(G8="","",IF(ISNUMBER(SEARCH(",",G8)),"Several items (the script lists them)",IFERROR(INDEX('Dashboard Items'!$B$2:$B$495,MATCH(G8,'Dashboard Items'!$A$2:$A$495,0))&": "&INDEX('Dashboard Items'!$C$2:$C$495,MATCH(G8,'Dashboard Items'!$A$2:$A$495,0)),"ID not found"))) | I8: number | J8: 2 | K8: Yes | L8: Target | M8: 0 | N8: 0 | O8: Yes | P8: Every year | Q8: Chief of Police | U8: =IF(B8="","",IF(IF(D8<>"",D8,IFERROR(INDEX('Dashboard Items'!$B$2:$B$495,MATCH(E8,'Dashboard Items'!$A$2:$A$495,0)),""))="Key Service",IF(O8="No","Key Service: shown, not counted","Counts in Key Service gauge"),IF(IF(D8<>"",D8,IFERROR(INDEX('Dashboard Items'!$B$2:$B$495,MATCH(E8,'Dashboard Items'!$A$2:$A$495,0)),""))="Program",IF(ISNUMBER(SEARCH("ks",G8)),IF(O8="No","Program, also at Key Service: not counted","Counts in Key Service gauge + sets Program chip"),IF(O8="No","Program: shown, no status chip","Sets Program status chip")),IF(IF(D8<>"",D8,IFERROR(INDEX('Dashboard Items'!$B$2:$B$495,MATCH(E8,'Dashboard Items'!$A$2:$A$495,0)),""))="Work System","Work System: shown, not counted","Check Level"))))
A9: =LEFT(B9, FIND("-", B9) - 1) | B9: CLERK-AGENDAPOST | C9: Agenda posting time | D9: Program | E9: p6 | F9: =IF(E9="","",IFERROR(IF(INDEX('Dashboard Items'!$B$2:$B$495,MATCH(E9,'Dashboard Items'!$A$2:$A$495,0))="Objective","Objectives go in the next column",IF(OR(D9="",INDEX('Dashboard Items'!$B$2:$B$495,MATCH(E9,'Dashboard Items'!$A$2:$A$495,0))=D9),INDEX('Dashboard Items'!$C$2:$C$495,MATCH(E9,'Dashboard Items'!$A$2:$A$495,0)),"Level does not match ID")),"ID not found")) | G9: ks2 | H9: =IF(G9="","",IF(ISNUMBER(SEARCH(",",G9)),"Several items (the script lists them)",IFERROR(INDEX('Dashboard Items'!$B$2:$B$495,MATCH(G9,'Dashboard Items'!$A$2:$A$495,0))&": "&INDEX('Dashboard Items'!$C$2:$C$495,MATCH(G9,'Dashboard Items'!$A$2:$A$495,0)),"ID not found"))) | I9: percent | J9: 0 | K9: Yes | L9: Target | P9: Every Quarter | S9: Share of regular City Council meeting agendas posted at least 48 hours before the meeting, each quarter. | T9: Target: more than 90% posted within 48 hours. Results swing from quarter to quarter because the number of meetings varies. | U9: =IF(B9="","",IF(IF(D9<>"",D9,IFERROR(INDEX('Dashboard Items'!$B$2:$B$495,MATCH(E9,'Dashboard Items'!$A$2:$A$495,0)),""))="Key Service",IF(O9="No","Key Service: shown, not counted","Counts in Key Service gauge"),IF(IF(D9<>"",D9,IFERROR(INDEX('Dashboard Items'!$B$2:$B$495,MATCH(E9,'Dashboard Items'!$A$2:$A$495,0)),""))="Program",IF(ISNUMBER(SEARCH("ks",G9)),IF(O9="No","Program, also at Key Service: not counted","Counts in Key Service gauge + sets Program chip"),IF(O9="No","Program: shown, no status chip","Sets Program status chip")),IF(IF(D9<>"",D9,IFERROR(INDEX('Dashboard Items'!$B$2:$B$495,MATCH(E9,'Dashboard Items'!$A$2:$A$495,0)),""))="Work System","Work System: shown, not counted","Check Level"))))
A10: =LEFT(B10, FIND("-", B10) - 1) | B10: CLERK-BIZLIC | C10: Business license turnaround time | D10: Program | E10: p29 | F10: =IF(E10="","",IFERROR(IF(INDEX('Dashboard Items'!$B$2:$B$495,MATCH(E10,'Dashboard Items'!$A$2:$A$495,0))="Objective","Objectives go in the next column",IF(OR(D10="",INDEX('Dashboard Items'!$B$2:$B$495,MATCH(E10,'Dashboard Items'!$A$2:$A$495,0))=D10),INDEX('Dashboard Items'!$C$2:$C$495,MATCH(E10,'Dashboard Items'!$A$2:$A$495,0)),"Level does not match ID")),"ID not found")) | G10: ks2 | H10: =IF(G10="","",IF(ISNUMBER(SEARCH(",",G10)),"Several items (the script lists them)",IFERROR(INDEX('Dashboard Items'!$B$2:$B$495,MATCH(G10,'Dashboard Items'!$A$2:$A$495,0))&": "&INDEX('Dashboard Items'!$C$2:$C$495,MATCH(G10,'Dashboard Items'!$A$2:$A$495,0)),"ID not found"))) | U10: =IF(B10="","",IF(IF(D10<>"",D10,IFERROR(INDEX('Dashboard Items'!$B$2:$B$495,MATCH(E10,'Dashboard Items'!$A$2:$A$495,0)),""))="Key Service",IF(O10="No","Key Service: shown, not counted","Counts in Key Service gauge"),IF(IF(D10<>"",D10,IFERROR(INDEX('Dashboard Items'!$B$2:$B$495,MATCH(E10,'Dashboard Items'!$A$2:$A$495,0)),""))="Program",IF(ISNUMBER(SEARCH("ks",G10)),IF(O10="No","Program, also at Key Service: not counted","Counts in Key Service gauge + sets Program chip"),IF(O10="No","Program: shown, no status chip","Sets Program status chip")),IF(IF(D10<>"",D10,IFERROR(INDEX('Dashboard Items'!$B$2:$B$495,MATCH(E10,'Dashboard Items'!$A$2:$A$495,0)),""))="Work System","Work System: shown, not counted","Check Level"))))
A11: =LEFT(B11, FIND("-", B11) - 1) | B11: CLERK-CLICKTHRURATE | C11: Click through rate on City's election landing page | D11: Program | E11: p8 | F11: =IF(E11="","",IFERROR(IF(INDEX('Dashboard Items'!$B$2:$B$495,MATCH(E11,'Dashboard Items'!$A$2:$A$495,0))="Objective","Objectives go in the next column",IF(OR(D11="",INDEX('Dashboard Items'!$B$2:$B$495,MATCH(E11,'Dashboard Items'!$A$2:$A$495,0))=D11),INDEX('Dashboard Items'!$C$2:$C$495,MATCH(E11,'Dashboard Items'!$A$2:$A$495,0)),"Level does not match ID")),"ID not found")) | H11: =IF(G11="","",IF(ISNUMBER(SEARCH(",",G11)),"Several items (the script lists them)",IFERROR(INDEX('Dashboard Items'!$B$2:$B$495,MATCH(G11,'Dashboard Items'!$A$2:$A$495,0))&": "&INDEX('Dashboard Items'!$C$2:$C$495,MATCH(G11,'Dashboard Items'!$A$2:$A$495,0)),"ID not found"))) | U11: =IF(B11="","",IF(IF(D11<>"",D11,IFERROR(INDEX('Dashboard Items'!$B$2:$B$495,MATCH(E11,'Dashboard Items'!$A$2:$A$495,0)),""))="Key Service",IF(O11="No","Key Service: shown, not counted","Counts in Key Service gauge"),IF(IF(D11<>"",D11,IFERROR(INDEX('Dashboard Items'!$B$2:$B$495,MATCH(E11,'Dashboard Items'!$A$2:$A$495,0)),""))="Program",IF(ISNUMBER(SEARCH("ks",G11)),IF(O11="No","Program, also at Key Service: not counted","Counts in Key Service gauge + sets Program chip"),IF(O11="No","Program: shown, no status chip","Sets Program status chip")),IF(IF(D11<>"",D11,IFERROR(INDEX('Dashboard Items'!$B$2:$B$495,MATCH(E11,'Dashboard Items'!$A$2:$A$495,0)),""))="Work System","Work System: shown, not counted","Check Level"))))
A12: =LEFT(B12, FIND("-", B12) - 1) | B12: CLERK-CORARESPRATE | C12: Records request response rate | D12: Program | E12: p7 | F12: =IF(E12="","",IFERROR(IF(INDEX('Dashboard Items'!$B$2:$B$495,MATCH(E12,'Dashboard Items'!$A$2:$A$495,0))="Objective","Objectives go in the next column",IF(OR(D12="",INDEX('Dashboard Items'!$B$2:$B$495,MATCH(E12,'Dashboard Items'!$A$2:$A$495,0))=D12),INDEX('Dashboard Items'!$C$2:$C$495,MATCH(E12,'Dashboard Items'!$A$2:$A$495,0)),"Level does not match ID")),"ID not found")) | G12: ks2 | H12: =IF(G12="","",IF(ISNUMBER(SEARCH(",",G12)),"Several items (the script lists them)",IFERROR(INDEX('Dashboard Items'!$B$2:$B$495,MATCH(G12,'Dashboard Items'!$A$2:$A$495,0))&": "&INDEX('Dashboard Items'!$C$2:$C$495,MATCH(G12,'Dashboard Items'!$A$2:$A$495,0)),"ID not found"))) | I12: percent | J12: 0 | K12: Yes | L12: Target | P12: Every Quarter | S12: Share of public records requests closed within 24 hours, each quarter. | T12: Target: 90% closed within 24 hours. The legal deadline is 3 days. Some requests are delayed while waiting on the requester, especially for payment. | U12: =IF(B12="","",IF(IF(D12<>"",D12,IFERROR(INDEX('Dashboard Items'!$B$2:$B$495,MATCH(E12,'Dashboard Items'!$A$2:$A$495,0)),""))="Key Service",IF(O12="No","Key Service: shown, not counted","Counts in Key Service gauge"),IF(IF(D12<>"",D12,IFERROR(INDEX('Dashboard Items'!$B$2:$B$495,MATCH(E12,'Dashboard Items'!$A$2:$A$495,0)),""))="Program",IF(ISNUMBER(SEARCH("ks",G12)),IF(O12="No","Program, also at Key Service: not counted","Counts in Key Service gauge + sets Program chip"),IF(O12="No","Program: shown, no status chip","Sets Program status chip")),IF(IF(D12<>"",D12,IFERROR(INDEX('Dashboard Items'!$B$2:$B$495,MATCH(E12,'Dashboard Items'!$A$2:$A$495,0)),""))="Work System","Work System: shown, not counted","Check Level"))))
A13: =LEFT(B13, FIND("-", B13) - 1) | B13: CLERK-LIQMARJLIC | C13: Liquor and marijuana license turnaround | D13: Program | E13: p29 | F13: =IF(E13="","",IFERROR(IF(INDEX('Dashboard Items'!$B$2:$B$495,MATCH(E13,'Dashboard Items'!$A$2:$A$495,0))="Objective","Objectives go in the next column",IF(OR(D13="",INDEX('Dashboard Items'!$B$2:$B$495,MATCH(E13,'Dashboard Items'!$A$2:$A$495,0))=D13),INDEX('Dashboard Items'!$C$2:$C$495,MATCH(E13,'Dashboard Items'!$A$2:$A$495,0)),"Level does not match ID")),"ID not found")) | G13: ks2 | H13: =IF(G13="","",IF(ISNUMBER(SEARCH(",",G13)),"Several items (the script lists them)",IFERROR(INDEX('Dashboard Items'!$B$2:$B$495,MATCH(G13,'Dashboard Items'!$A$2:$A$495,0))&": "&INDEX('Dashboard Items'!$C$2:$C$495,MATCH(G13,'Dashboard Items'!$A$2:$A$495,0)),"ID not found"))) | U13: =IF(B13="","",IF(IF(D13<>"",D13,IFERROR(INDEX('Dashboard Items'!$B$2:$B$495,MATCH(E13,'Dashboard Items'!$A$2:$A$495,0)),""))="Key Service",IF(O13="No","Key Service: shown, not counted","Counts in Key Service gauge"),IF(IF(D13<>"",D13,IFERROR(INDEX('Dashboard Items'!$B$2:$B$495,MATCH(E13,'Dashboard Items'!$A$2:$A$495,0)),""))="Program",IF(ISNUMBER(SEARCH("ks",G13)),IF(O13="No","Program, also at Key Service: not counted","Counts in Key Service gauge + sets Program chip"),IF(O13="No","Program: shown, no status chip","Sets Program status chip")),IF(IF(D13<>"",D13,IFERROR(INDEX('Dashboard Items'!$B$2:$B$495,MATCH(E13,'Dashboard Items'!$A$2:$A$495,0)),""))="Work System","Work System: shown, not counted","Check Level"))))
A14: =LEFT(B14, FIND("-", B14) - 1) | B14: CLERK-LOGICTEST | C14: Logic and accuracy test | D14: Program | E14: p8 | F14: =IF(E14="","",IFERROR(IF(INDEX('Dashboard Items'!$B$2:$B$495,MATCH(E14,'Dashboard Items'!$A$2:$A$495,0))="Objective","Objectives go in the next column",IF(OR(D14="",INDEX('Dashboard Items'!$B$2:$B$495,MATCH(E14,'Dashboard Items'!$A$2:$A$495,0))=D14),INDEX('Dashboard Items'!$C$2:$C$495,MATCH(E14,'Dashboard Items'!$A$2:$A$495,0)),"Level does not match ID")),"ID not found")) | H14: =IF(G14="","",IF(ISNUMBER(SEARCH(",",G14)),"Several items (the script lists them)",IFERROR(INDEX('Dashboard Items'!$B$2:$B$495,MATCH(G14,'Dashboard Items'!$A$2:$A$495,0))&": "&INDEX('Dashboard Items'!$C$2:$C$495,MATCH(G14,'Dashboard Items'!$A$2:$A$495,0)),"ID not found"))) | U14: =IF(B14="","",IF(IF(D14<>"",D14,IFERROR(INDEX('Dashboard Items'!$B$2:$B$495,MATCH(E14,'Dashboard Items'!$A$2:$A$495,0)),""))="Key Service",IF(O14="No","Key Service: shown, not counted","Counts in Key Service gauge"),IF(IF(D14<>"",D14,IFERROR(INDEX('Dashboard Items'!$B$2:$B$495,MATCH(E14,'Dashboard Items'!$A$2:$A$495,0)),""))="Program",IF(ISNUMBER(SEARCH("ks",G14)),IF(O14="No","Program, also at Key Service: not counted","Counts in Key Service gauge + sets Program chip"),IF(O14="No","Program: shown, no status chip","Sets Program status chip")),IF(IF(D14<>"",D14,IFERROR(INDEX('Dashboard Items'!$B$2:$B$495,MATCH(E14,'Dashboard Items'!$A$2:$A$495,0)),""))="Work System","Work System: shown, not counted","Check Level"))))
A15: =LEFT(B15, FIND("-", B15) - 1) | B15: CLERK-QRESPRATE | C15: Response rate for public election related questions | D15: Program | E15: p8 | F15: =IF(E15="","",IFERROR(IF(INDEX('Dashboard Items'!$B$2:$B$495,MATCH(E15,'Dashboard Items'!$A$2:$A$495,0))="Objective","Objectives go in the next column",IF(OR(D15="",INDEX('Dashboard Items'!$B$2:$B$495,MATCH(E15,'Dashboard Items'!$A$2:$A$495,0))=D15),INDEX('Dashboard Items'!$C$2:$C$495,MATCH(E15,'Dashboard Items'!$A$2:$A$495,0)),"Level does not match ID")),"ID not found")) | H15: =IF(G15="","",IF(ISNUMBER(SEARCH(",",G15)),"Several items (the script lists them)",IFERROR(INDEX('Dashboard Items'!$B$2:$B$495,MATCH(G15,'Dashboard Items'!$A$2:$A$495,0))&": "&INDEX('Dashboard Items'!$C$2:$C$495,MATCH(G15,'Dashboard Items'!$A$2:$A$495,0)),"ID not found"))) | U15: =IF(B15="","",IF(IF(D15<>"",D15,IFERROR(INDEX('Dashboard Items'!$B$2:$B$495,MATCH(E15,'Dashboard Items'!$A$2:$A$495,0)),""))="Key Service",IF(O15="No","Key Service: shown, not counted","Counts in Key Service gauge"),IF(IF(D15<>"",D15,IFERROR(INDEX('Dashboard Items'!$B$2:$B$495,MATCH(E15,'Dashboard Items'!$A$2:$A$495,0)),""))="Program",IF(ISNUMBER(SEARCH("ks",G15)),IF(O15="No","Program, also at Key Service: not counted","Counts in Key Service gauge + sets Program chip"),IF(O15="No","Program: shown, no status chip","Sets Program status chip")),IF(IF(D15<>"",D15,IFERROR(INDEX('Dashboard Items'!$B$2:$B$495,MATCH(E15,'Dashboard Items'!$A$2:$A$495,0)),""))="Work System","Work System: shown, not counted","Check Level"))))
A16: =LEFT(B16, FIND("-", B16) - 1) | B16: CLERK-SPECCOURT | C16: # cases resolved through graduating from specialty court | D16: Program | E16: p58 | F16: =IF(E16="","",IFERROR(IF(INDEX('Dashboard Items'!$B$2:$B$495,MATCH(E16,'Dashboard Items'!$A$2:$A$495,0))="Objective","Objectives go in the next column",IF(OR(D16="",INDEX('Dashboard Items'!$B$2:$B$495,MATCH(E16,'Dashboard Items'!$A$2:$A$495,0))=D16),INDEX('Dashboard Items'!$C$2:$C$495,MATCH(E16,'Dashboard Items'!$A$2:$A$495,0)),"Level does not match ID")),"ID not found")) | G16: ks12 | H16: =IF(G16="","",IF(ISNUMBER(SEARCH(",",G16)),"Several items (the script lists them)",IFERROR(INDEX('Dashboard Items'!$B$2:$B$495,MATCH(G16,'Dashboard Items'!$A$2:$A$495,0))&": "&INDEX('Dashboard Items'!$C$2:$C$495,MATCH(G16,'Dashboard Items'!$A$2:$A$495,0)),"ID not found"))) | U16: =IF(B16="","",IF(IF(D16<>"",D16,IFERROR(INDEX('Dashboard Items'!$B$2:$B$495,MATCH(E16,'Dashboard Items'!$A$2:$A$495,0)),""))="Key Service",IF(O16="No","Key Service: shown, not counted","Counts in Key Service gauge"),IF(IF(D16<>"",D16,IFERROR(INDEX('Dashboard Items'!$B$2:$B$495,MATCH(E16,'Dashboard Items'!$A$2:$A$495,0)),""))="Program",IF(ISNUMBER(SEARCH("ks",G16)),IF(O16="No","Program, also at Key Service: not counted","Counts in Key Service gauge + sets Program chip"),IF(O16="No","Program: shown, no status chip","Sets Program status chip")),IF(IF(D16<>"",D16,IFERROR(INDEX('Dashboard Items'!$B$2:$B$495,MATCH(E16,'Dashboard Items'!$A$2:$A$495,0)),""))="Work System","Work System: shown, not counted","Check Level"))))
A17: =LEFT(B17, FIND("-", B17) - 1) | B17: CLERK-VOTERTURNOUT | C17: Voter turnout (%) | D17: Program | E17: p8 | F17: =IF(E17="","",IFERROR(IF(INDEX('Dashboard Items'!$B$2:$B$495,MATCH(E17,'Dashboard Items'!$A$2:$A$495,0))="Objective","Objectives go in the next column",IF(OR(D17="",INDEX('Dashboard Items'!$B$2:$B$495,MATCH(E17,'Dashboard Items'!$A$2:$A$495,0))=D17),INDEX('Dashboard Items'!$C$2:$C$495,MATCH(E17,'Dashboard Items'!$A$2:$A$495,0)),"Level does not match ID")),"ID not found")) | G17: ks2 | H17: =IF(G17="","",IF(ISNUMBER(SEARCH(",",G17)),"Several items (the script lists them)",IFERROR(INDEX('Dashboard Items'!$B$2:$B$495,MATCH(G17,'Dashboard Items'!$A$2:$A$495,0))&": "&INDEX('Dashboard Items'!$C$2:$C$495,MATCH(G17,'Dashboard Items'!$A$2:$A$495,0)),"ID not found"))) | U17: =IF(B17="","",IF(IF(D17<>"",D17,IFERROR(INDEX('Dashboard Items'!$B$2:$B$495,MATCH(E17,'Dashboard Items'!$A$2:$A$495,0)),""))="Key Service",IF(O17="No","Key Service: shown, not counted","Counts in Key Service gauge"),IF(IF(D17<>"",D17,IFERROR(INDEX('Dashboard Items'!$B$2:$B$495,MATCH(E17,'Dashboard Items'!$A$2:$A$495,0)),""))="Program",IF(ISNUMBER(SEARCH("ks",G17)),IF(O17="No","Program, also at Key Service: not counted","Counts in Key Service gauge + sets Program chip"),IF(O17="No","Program: shown, no status chip","Sets Program status chip")),IF(IF(D17<>"",D17,IFERROR(INDEX('Dashboard Items'!$B$2:$B$495,MATCH(E17,'Dashboard Items'!$A$2:$A$495,0)),""))="Work System","Work System: shown, not counted","Check Level"))))
A18: =LEFT(B18, FIND("-", B18) - 1) | B18: HR-ACCREVBOARD | C18: Accident Review Board - Average or cumulative severity? | D18: Program | E18: p27 | F18: =IF(E18="","",IFERROR(IF(INDEX('Dashboard Items'!$B$2:$B$495,MATCH(E18,'Dashboard Items'!$A$2:$A$495,0))="Objective","Objectives go in the next column",IF(OR(D18="",INDEX('Dashboard Items'!$B$2:$B$495,MATCH(E18,'Dashboard Items'!$A$2:$A$495,0))=D18),INDEX('Dashboard Items'!$C$2:$C$495,MATCH(E18,'Dashboard Items'!$A$2:$A$495,0)),"Level does not match ID")),"ID not found")) | H18: =IF(G18="","",IF(ISNUMBER(SEARCH(",",G18)),"Several items (the script lists them)",IFERROR(INDEX('Dashboard Items'!$B$2:$B$495,MATCH(G18,'Dashboard Items'!$A$2:$A$495,0))&": "&INDEX('Dashboard Items'!$C$2:$C$495,MATCH(G18,'Dashboard Items'!$A$2:$A$495,0)),"ID not found"))) | U18: =IF(B18="","",IF(IF(D18<>"",D18,IFERROR(INDEX('Dashboard Items'!$B$2:$B$495,MATCH(E18,'Dashboard Items'!$A$2:$A$495,0)),""))="Key Service",IF(O18="No","Key Service: shown, not counted","Counts in Key Service gauge"),IF(IF(D18<>"",D18,IFERROR(INDEX('Dashboard Items'!$B$2:$B$495,MATCH(E18,'Dashboard Items'!$A$2:$A$495,0)),""))="Program",IF(ISNUMBER(SEARCH("ks",G18)),IF(O18="No","Program, also at Key Service: not counted","Counts in Key Service gauge + sets Program chip"),IF(O18="No","Program: shown, no status chip","Sets Program status chip")),IF(IF(D18<>"",D18,IFERROR(INDEX('Dashboard Items'!$B$2:$B$495,MATCH(E18,'Dashboard Items'!$A$2:$A$495,0)),""))="Work System","Work System: shown, not counted","Check Level"))))
A19: =LEFT(B19, FIND("-", B19) - 1) | B19: HR-APPPERREC | C19: Attracting: applications per recruitment | D19: Program | E19: p24 | F19: =IF(E19="","",IFERROR(IF(INDEX('Dashboard Items'!$B$2:$B$495,MATCH(E19,'Dashboard Items'!$A$2:$A$495,0))="Objective","Objectives go in the next column",IF(OR(D19="",INDEX('Dashboard Items'!$B$2:$B$495,MATCH(E19,'Dashboard Items'!$A$2:$A$495,0))=D19),INDEX('Dashboard Items'!$C$2:$C$495,MATCH(E19,'Dashboard Items'!$A$2:$A$495,0)),"Level does not match ID")),"ID not found")) | H19: =IF(G19="","",IF(ISNUMBER(SEARCH(",",G19)),"Several items (the script lists them)",IFERROR(INDEX('Dashboard Items'!$B$2:$B$495,MATCH(G19,'Dashboard Items'!$A$2:$A$495,0))&": "&INDEX('Dashboard Items'!$C$2:$C$495,MATCH(G19,'Dashboard Items'!$A$2:$A$495,0)),"ID not found"))) | Q19: Safety / Risk Administrator | U19: =IF(B19="","",IF(IF(D19<>"",D19,IFERROR(INDEX('Dashboard Items'!$B$2:$B$495,MATCH(E19,'Dashboard Items'!$A$2:$A$495,0)),""))="Key Service",IF(O19="No","Key Service: shown, not counted","Counts in Key Service gauge"),IF(IF(D19<>"",D19,IFERROR(INDEX('Dashboard Items'!$B$2:$B$495,MATCH(E19,'Dashboard Items'!$A$2:$A$495,0)),""))="Program",IF(ISNUMBER(SEARCH("ks",G19)),IF(O19="No","Program, also at Key Service: not counted","Counts in Key Service gauge + sets Program chip"),IF(O19="No","Program: shown, no status chip","Sets Program status chip")),IF(IF(D19<>"",D19,IFERROR(INDEX('Dashboard Items'!$B$2:$B$495,MATCH(E19,'Dashboard Items'!$A$2:$A$495,0)),""))="Work System","Work System: shown, not counted","Check Level"))))
A20: =LEFT(B20, FIND("-", B20) - 1) | B20: HR-CFT | C20: CFT participation | D20: Program | E20: p22 | F20: =IF(E20="","",IFERROR(IF(INDEX('Dashboard Items'!$B$2:$B$495,MATCH(E20,'Dashboard Items'!$A$2:$A$495,0))="Objective","Objectives go in the next column",IF(OR(D20="",INDEX('Dashboard Items'!$B$2:$B$495,MATCH(E20,'Dashboard Items'!$A$2:$A$495,0))=D20),INDEX('Dashboard Items'!$C$2:$C$495,MATCH(E20,'Dashboard Items'!$A$2:$A$495,0)),"Level does not match ID")),"ID not found")) | H20: =IF(G20="","",IF(ISNUMBER(SEARCH(",",G20)),"Several items (the script lists them)",IFERROR(INDEX('Dashboard Items'!$B$2:$B$495,MATCH(G20,'Dashboard Items'!$A$2:$A$495,0))&": "&INDEX('Dashboard Items'!$C$2:$C$495,MATCH(G20,'Dashboard Items'!$A$2:$A$495,0)),"ID not found"))) | U20: =IF(B20="","",IF(IF(D20<>"",D20,IFERROR(INDEX('Dashboard Items'!$B$2:$B$495,MATCH(E20,'Dashboard Items'!$A$2:$A$495,0)),""))="Key Service",IF(O20="No","Key Service: shown, not counted","Counts in Key Service gauge"),IF(IF(D20<>"",D20,IFERROR(INDEX('Dashboard Items'!$B$2:$B$495,MATCH(E20,'Dashboard Items'!$A$2:$A$495,0)),""))="Program",IF(ISNUMBER(SEARCH("ks",G20)),IF(O20="No","Program, also at Key Service: not counted","Counts in Key Service gauge + sets Program chip"),IF(O20="No","Program: shown, no status chip","Sets Program status chip")),IF(IF(D20<>"",D20,IFERROR(INDEX('Dashboard Items'!$B$2:$B$495,MATCH(E20,'Dashboard Items'!$A$2:$A$495,0)),""))="Work System","Work System: shown, not counted","Check Level"))))
A21: =LEFT(B21, FIND("-", B21) - 1) | B21: HR-COMPANDBEN | C21: Employee Engagement Survey: satisfaction with compensation and benefits | D21: Program | E21: p25 | F21: =IF(E21="","",IFERROR(IF(INDEX('Dashboard Items'!$B$2:$B$495,MATCH(E21,'Dashboard Items'!$A$2:$A$495,0))="Objective","Objectives go in the next column",IF(OR(D21="",INDEX('Dashboard Items'!$B$2:$B$495,MATCH(E21,'Dashboard Items'!$A$2:$A$495,0))=D21),INDEX('Dashboard Items'!$C$2:$C$495,MATCH(E21,'Dashboard Items'!$A$2:$A$495,0)),"Level does not match ID")),"ID not found")) | H21: =IF(G21="","",IF(ISNUMBER(SEARCH(",",G21)),"Several items (the script lists them)",IFERROR(INDEX('Dashboard Items'!$B$2:$B$495,MATCH(G21,'Dashboard Items'!$A$2:$A$495,0))&": "&INDEX('Dashboard Items'!$C$2:$C$495,MATCH(G21,'Dashboard Items'!$A$2:$A$495,0)),"ID not found"))) | U21: =IF(B21="","",IF(IF(D21<>"",D21,IFERROR(INDEX('Dashboard Items'!$B$2:$B$495,MATCH(E21,'Dashboard Items'!$A$2:$A$495,0)),""))="Key Service",IF(O21="No","Key Service: shown, not counted","Counts in Key Service gauge"),IF(IF(D21<>"",D21,IFERROR(INDEX('Dashboard Items'!$B$2:$B$495,MATCH(E21,'Dashboard Items'!$A$2:$A$495,0)),""))="Program",IF(ISNUMBER(SEARCH("ks",G21)),IF(O21="No","Program, also at Key Service: not counted","Counts in Key Service gauge + sets Program chip"),IF(O21="No","Program: shown, no status chip","Sets Program status chip")),IF(IF(D21<>"",D21,IFERROR(INDEX('Dashboard Items'!$B$2:$B$495,MATCH(E21,'Dashboard Items'!$A$2:$A$495,0)),""))="Work System","Work System: shown, not counted","Check Level"))))
A22: =LEFT(B22, FIND("-", B22) - 1) | B22: HR-DOTCOMPSCORE | C22: DOT Compliance Score (employees with CDLs) | D22: Program | E22: p27 | F22: =IF(E22="","",IFERROR(IF(INDEX('Dashboard Items'!$B$2:$B$495,MATCH(E22,'Dashboard Items'!$A$2:$A$495,0))="Objective","Objectives go in the next column",IF(OR(D22="",INDEX('Dashboard Items'!$B$2:$B$495,MATCH(E22,'Dashboard Items'!$A$2:$A$495,0))=D22),INDEX('Dashboard Items'!$C$2:$C$495,MATCH(E22,'Dashboard Items'!$A$2:$A$495,0)),"Level does not match ID")),"ID not found")) | H22: =IF(G22="","",IF(ISNUMBER(SEARCH(",",G22)),"Several items (the script lists them)",IFERROR(INDEX('Dashboard Items'!$B$2:$B$495,MATCH(G22,'Dashboard Items'!$A$2:$A$495,0))&": "&INDEX('Dashboard Items'!$C$2:$C$495,MATCH(G22,'Dashboard Items'!$A$2:$A$495,0)),"ID not found"))) | U22: =IF(B22="","",IF(IF(D22<>"",D22,IFERROR(INDEX('Dashboard Items'!$B$2:$B$495,MATCH(E22,'Dashboard Items'!$A$2:$A$495,0)),""))="Key Service",IF(O22="No","Key Service: shown, not counted","Counts in Key Service gauge"),IF(IF(D22<>"",D22,IFERROR(INDEX('Dashboard Items'!$B$2:$B$495,MATCH(E22,'Dashboard Items'!$A$2:$A$495,0)),""))="Program",IF(ISNUMBER(SEARCH("ks",G22)),IF(O22="No","Program, also at Key Service: not counted","Counts in Key Service gauge + sets Program chip"),IF(O22="No","Program: shown, no status chip","Sets Program status chip")),IF(IF(D22<>"",D22,IFERROR(INDEX('Dashboard Items'!$B$2:$B$495,MATCH(E22,'Dashboard Items'!$A$2:$A$495,0)),""))="Work System","Work System: shown, not counted","Check Level"))))
A23: =LEFT(B23, FIND("-", B23) - 1) | B23: HR-EMOD | C23: EMOD (experience modification) for Work Comp - annually from Pinnacol, score dictates premium | D23: Program | E23: p27 | F23: =IF(E23="","",IFERROR(IF(INDEX('Dashboard Items'!$B$2:$B$495,MATCH(E23,'Dashboard Items'!$A$2:$A$495,0))="Objective","Objectives go in the next column",IF(OR(D23="",INDEX('Dashboard Items'!$B$2:$B$495,MATCH(E23,'Dashboard Items'!$A$2:$A$495,0))=D23),INDEX('Dashboard Items'!$C$2:$C$495,MATCH(E23,'Dashboard Items'!$A$2:$A$495,0)),"Level does not match ID")),"ID not found")) | H23: =IF(G23="","",IF(ISNUMBER(SEARCH(",",G23)),"Several items (the script lists them)",IFERROR(INDEX('Dashboard Items'!$B$2:$B$495,MATCH(G23,'Dashboard Items'!$A$2:$A$495,0))&": "&INDEX('Dashboard Items'!$C$2:$C$495,MATCH(G23,'Dashboard Items'!$A$2:$A$495,0)),"ID not found"))) | U23: =IF(B23="","",IF(IF(D23<>"",D23,IFERROR(INDEX('Dashboard Items'!$B$2:$B$495,MATCH(E23,'Dashboard Items'!$A$2:$A$495,0)),""))="Key Service",IF(O23="No","Key Service: shown, not counted","Counts in Key Service gauge"),IF(IF(D23<>"",D23,IFERROR(INDEX('Dashboard Items'!$B$2:$B$495,MATCH(E23,'Dashboard Items'!$A$2:$A$495,0)),""))="Program",IF(ISNUMBER(SEARCH("ks",G23)),IF(O23="No","Program, also at Key Service: not counted","Counts in Key Service gauge + sets Program chip"),IF(O23="No","Program: shown, no status chip","Sets Program status chip")),IF(IF(D23<>"",D23,IFERROR(INDEX('Dashboard Items'!$B$2:$B$495,MATCH(E23,'Dashboard Items'!$A$2:$A$495,0)),""))="Work System","Work System: shown, not counted","Check Level"))))
A24: =LEFT(B24, FIND("-", B24) - 1) | B24: HR-EMPENG | C24: Employee engagement score | D24: Key Service | E24: ks5 | F24: =IF(E24="","",IFERROR(IF(INDEX('Dashboard Items'!$B$2:$B$495,MATCH(E24,'Dashboard Items'!$A$2:$A$495,0))="Objective","Objectives go in the next column",IF(OR(D24="",INDEX('Dashboard Items'!$B$2:$B$495,MATCH(E24,'Dashboard Items'!$A$2:$A$495,0))=D24),INDEX('Dashboard Items'!$C$2:$C$495,MATCH(E24,'Dashboard Items'!$A$2:$A$495,0)),"Level does not match ID")),"ID not found")) | G24: ob18, p24 | H24: =IF(G24="","",IF(ISNUMBER(SEARCH(",",G24)),"Several items (the script lists them)",IFERROR(INDEX('Dashboard Items'!$B$2:$B$495,MATCH(G24,'Dashboard Items'!$A$2:$A$495,0))&": "&INDEX('Dashboard Items'!$C$2:$C$495,MATCH(G24,'Dashboard Items'!$A$2:$A$495,0)),"ID not found"))) | I24: percent | J24: 1 | K24: Yes | L24: Target | M24: 5 | N24: 15 | O24: Yes | P24: Every 2 years | Q24: HR Director | R24: Employee Survey | S24: Overall engagement score from the City employee survey, compared with the survey benchmark. | U24: =IF(B24="","",IF(IF(D24<>"",D24,IFERROR(INDEX('Dashboard Items'!$B$2:$B$495,MATCH(E24,'Dashboard Items'!$A$2:$A$495,0)),""))="Key Service",IF(O24="No","Key Service: shown, not counted","Counts in Key Service gauge"),IF(IF(D24<>"",D24,IFERROR(INDEX('Dashboard Items'!$B$2:$B$495,MATCH(E24,'Dashboard Items'!$A$2:$A$495,0)),""))="Program",IF(ISNUMBER(SEARCH("ks",G24)),IF(O24="No","Program, also at Key Service: not counted","Counts in Key Service gauge + sets Program chip"),IF(O24="No","Program: shown, no status chip","Sets Program status chip")),IF(IF(D24<>"",D24,IFERROR(INDEX('Dashboard Items'!$B$2:$B$495,MATCH(E24,'Dashboard Items'!$A$2:$A$495,0)),""))="Work System","Work System: shown, not counted","Check Level"))))
A25: =LEFT(B25, FIND("-", B25) - 1) | B25: HR-INTPROMO | C25: Retain & Develop: Internal promotion rate | D25: Key Service | E25: ks5 | F25: =IF(E25="","",IFERROR(IF(INDEX('Dashboard Items'!$B$2:$B$495,MATCH(E25,'Dashboard Items'!$A$2:$A$495,0))="Objective","Objectives go in the next column",IF(OR(D25="",INDEX('Dashboard Items'!$B$2:$B$495,MATCH(E25,'Dashboard Items'!$A$2:$A$495,0))=D25),INDEX('Dashboard Items'!$C$2:$C$495,MATCH(E25,'Dashboard Items'!$A$2:$A$495,0)),"Level does not match ID")),"ID not found")) | G25: p24 | H25: =IF(G25="","",IF(ISNUMBER(SEARCH(",",G25)),"Several items (the script lists them)",IFERROR(INDEX('Dashboard Items'!$B$2:$B$495,MATCH(G25,'Dashboard Items'!$A$2:$A$495,0))&": "&INDEX('Dashboard Items'!$C$2:$C$495,MATCH(G25,'Dashboard Items'!$A$2:$A$495,0)),"ID not found"))) | I25: percent | J25: 2 | K25: Yes | L25: Target | P25: Every year | S25: Internal promotion rate for full-time City positions each fiscal year. | T25: Target: 10%. Benchmark: 6%, SHRM's average internal promotion rate. | U25: =IF(B25="","",IF(IF(D25<>"",D25,IFERROR(INDEX('Dashboard Items'!$B$2:$B$495,MATCH(E25,'Dashboard Items'!$A$2:$A$495,0)),""))="Key Service",IF(O25="No","Key Service: shown, not counted","Counts in Key Service gauge"),IF(IF(D25<>"",D25,IFERROR(INDEX('Dashboard Items'!$B$2:$B$495,MATCH(E25,'Dashboard Items'!$A$2:$A$495,0)),""))="Program",IF(ISNUMBER(SEARCH("ks",G25)),IF(O25="No","Program, also at Key Service: not counted","Counts in Key Service gauge + sets Program chip"),IF(O25="No","Program: shown, no status chip","Sets Program status chip")),IF(IF(D25<>"",D25,IFERROR(INDEX('Dashboard Items'!$B$2:$B$495,MATCH(E25,'Dashboard Items'!$A$2:$A$495,0)),""))="Work System","Work System: shown, not counted","Check Level"))))
A26: =LEFT(B26, FIND("-", B26) - 1) | B26: HR-JOBPOSTVIEW | C26: Attracting: job posting view | D26: Program | E26: p24 | F26: =IF(E26="","",IFERROR(IF(INDEX('Dashboard Items'!$B$2:$B$495,MATCH(E26,'Dashboard Items'!$A$2:$A$495,0))="Objective","Objectives go in the next column",IF(OR(D26="",INDEX('Dashboard Items'!$B$2:$B$495,MATCH(E26,'Dashboard Items'!$A$2:$A$495,0))=D26),INDEX('Dashboard Items'!$C$2:$C$495,MATCH(E26,'Dashboard Items'!$A$2:$A$495,0)),"Level does not match ID")),"ID not found")) | H26: =IF(G26="","",IF(ISNUMBER(SEARCH(",",G26)),"Several items (the script lists them)",IFERROR(INDEX('Dashboard Items'!$B$2:$B$495,MATCH(G26,'Dashboard Items'!$A$2:$A$495,0))&": "&INDEX('Dashboard Items'!$C$2:$C$495,MATCH(G26,'Dashboard Items'!$A$2:$A$495,0)),"ID not found"))) | K26: No | Q26: Safety / Risk Administrator | U26: =IF(B26="","",IF(IF(D26<>"",D26,IFERROR(INDEX('Dashboard Items'!$B$2:$B$495,MATCH(E26,'Dashboard Items'!$A$2:$A$495,0)),""))="Key Service",IF(O26="No","Key Service: shown, not counted","Counts in Key Service gauge"),IF(IF(D26<>"",D26,IFERROR(INDEX('Dashboard Items'!$B$2:$B$495,MATCH(E26,'Dashboard Items'!$A$2:$A$495,0)),""))="Program",IF(ISNUMBER(SEARCH("ks",G26)),IF(O26="No","Program, also at Key Service: not counted","Counts in Key Service gauge + sets Program chip"),IF(O26="No","Program: shown, no status chip","Sets Program status chip")),IF(IF(D26<>"",D26,IFERROR(INDEX('Dashboard Items'!$B$2:$B$495,MATCH(E26,'Dashboard Items'!$A$2:$A$495,0)),""))="Work System","Work System: shown, not counted","Check Level"))))
A27: =LEFT(B27, FIND("-", B27) - 1) | B27: HR-LOSSRUNREPORT | C27: Work Comp (loss run report?) | D27: Program | E27: p27 | F27: =IF(E27="","",IFERROR(IF(INDEX('Dashboard Items'!$B$2:$B$495,MATCH(E27,'Dashboard Items'!$A$2:$A$495,0))="Objective","Objectives go in the next column",IF(OR(D27="",INDEX('Dashboard Items'!$B$2:$B$495,MATCH(E27,'Dashboard Items'!$A$2:$A$495,0))=D27),INDEX('Dashboard Items'!$C$2:$C$495,MATCH(E27,'Dashboard Items'!$A$2:$A$495,0)),"Level does not match ID")),"ID not found")) | H27: =IF(G27="","",IF(ISNUMBER(SEARCH(",",G27)),"Several items (the script lists them)",IFERROR(INDEX('Dashboard Items'!$B$2:$B$495,MATCH(G27,'Dashboard Items'!$A$2:$A$495,0))&": "&INDEX('Dashboard Items'!$C$2:$C$495,MATCH(G27,'Dashboard Items'!$A$2:$A$495,0)),"ID not found"))) | U27: =IF(B27="","",IF(IF(D27<>"",D27,IFERROR(INDEX('Dashboard Items'!$B$2:$B$495,MATCH(E27,'Dashboard Items'!$A$2:$A$495,0)),""))="Key Service",IF(O27="No","Key Service: shown, not counted","Counts in Key Service gauge"),IF(IF(D27<>"",D27,IFERROR(INDEX('Dashboard Items'!$B$2:$B$495,MATCH(E27,'Dashboard Items'!$A$2:$A$495,0)),""))="Program",IF(ISNUMBER(SEARCH("ks",G27)),IF(O27="No","Program, also at Key Service: not counted","Counts in Key Service gauge + sets Program chip"),IF(O27="No","Program: shown, no status chip","Sets Program status chip")),IF(IF(D27<>"",D27,IFERROR(INDEX('Dashboard Items'!$B$2:$B$495,MATCH(E27,'Dashboard Items'!$A$2:$A$495,0)),""))="Work System","Work System: shown, not counted","Check Level"))))
A28: =LEFT(B28, FIND("-", B28) - 1) | B28: HR-OFFICERACC | C28: Hiring: offer acceptance rate | D28: Program | E28: p24 | F28: =IF(E28="","",IFERROR(IF(INDEX('Dashboard Items'!$B$2:$B$495,MATCH(E28,'Dashboard Items'!$A$2:$A$495,0))="Objective","Objectives go in the next column",IF(OR(D28="",INDEX('Dashboard Items'!$B$2:$B$495,MATCH(E28,'Dashboard Items'!$A$2:$A$495,0))=D28),INDEX('Dashboard Items'!$C$2:$C$495,MATCH(E28,'Dashboard Items'!$A$2:$A$495,0)),"Level does not match ID")),"ID not found")) | H28: =IF(G28="","",IF(ISNUMBER(SEARCH(",",G28)),"Several items (the script lists them)",IFERROR(INDEX('Dashboard Items'!$B$2:$B$495,MATCH(G28,'Dashboard Items'!$A$2:$A$495,0))&": "&INDEX('Dashboard Items'!$C$2:$C$495,MATCH(G28,'Dashboard Items'!$A$2:$A$495,0)),"ID not found"))) | K28: No | Q28: Safety / Risk Administrator | U28: =IF(B28="","",IF(IF(D28<>"",D28,IFERROR(INDEX('Dashboard Items'!$B$2:$B$495,MATCH(E28,'Dashboard Items'!$A$2:$A$495,0)),""))="Key Service",IF(O28="No","Key Service: shown, not counted","Counts in Key Service gauge"),IF(IF(D28<>"",D28,IFERROR(INDEX('Dashboard Items'!$B$2:$B$495,MATCH(E28,'Dashboard Items'!$A$2:$A$495,0)),""))="Program",IF(ISNUMBER(SEARCH("ks",G28)),IF(O28="No","Program, also at Key Service: not counted","Counts in Key Service gauge + sets Program chip"),IF(O28="No","Program: shown, no status chip","Sets Program status chip")),IF(IF(D28<>"",D28,IFERROR(INDEX('Dashboard Items'!$B$2:$B$495,MATCH(E28,'Dashboard Items'!$A$2:$A$495,0)),""))="Work System","Work System: shown, not counted","Check Level"))))
A29: =LEFT(B29, FIND("-", B29) - 1) | B29: HR-PROFDEV | C29: Utilization of professional development budget | D29: Program | E29: p22 | F29: =IF(E29="","",IFERROR(IF(INDEX('Dashboard Items'!$B$2:$B$495,MATCH(E29,'Dashboard Items'!$A$2:$A$495,0))="Objective","Objectives go in the next column",IF(OR(D29="",INDEX('Dashboard Items'!$B$2:$B$495,MATCH(E29,'Dashboard Items'!$A$2:$A$495,0))=D29),INDEX('Dashboard Items'!$C$2:$C$495,MATCH(E29,'Dashboard Items'!$A$2:$A$495,0)),"Level does not match ID")),"ID not found")) | H29: =IF(G29="","",IF(ISNUMBER(SEARCH(",",G29)),"Several items (the script lists them)",IFERROR(INDEX('Dashboard Items'!$B$2:$B$495,MATCH(G29,'Dashboard Items'!$A$2:$A$495,0))&": "&INDEX('Dashboard Items'!$C$2:$C$495,MATCH(G29,'Dashboard Items'!$A$2:$A$495,0)),"ID not found"))) | U29: =IF(B29="","",IF(IF(D29<>"",D29,IFERROR(INDEX('Dashboard Items'!$B$2:$B$495,MATCH(E29,'Dashboard Items'!$A$2:$A$495,0)),""))="Key Service",IF(O29="No","Key Service: shown, not counted","Counts in Key Service gauge"),IF(IF(D29<>"",D29,IFERROR(INDEX('Dashboard Items'!$B$2:$B$495,MATCH(E29,'Dashboard Items'!$A$2:$A$495,0)),""))="Program",IF(ISNUMBER(SEARCH("ks",G29)),IF(O29="No","Program, also at Key Service: not counted","Counts in Key Service gauge + sets Program chip"),IF(O29="No","Program: shown, no status chip","Sets Program status chip")),IF(IF(D29<>"",D29,IFERROR(INDEX('Dashboard Items'!$B$2:$B$495,MATCH(E29,'Dashboard Items'!$A$2:$A$495,0)),""))="Work System","Work System: shown, not counted","Check Level"))))
A30: =LEFT(B30, FIND("-", B30) - 1) | B30: HR-PROPCASCLAIM | C30: Property casualty claims (by department, dollar amount) | D30: Program | E30: p27 | F30: =IF(E30="","",IFERROR(IF(INDEX('Dashboard Items'!$B$2:$B$495,MATCH(E30,'Dashboard Items'!$A$2:$A$495,0))="Objective","Objectives go in the next column",IF(OR(D30="",INDEX('Dashboard Items'!$B$2:$B$495,MATCH(E30,'Dashboard Items'!$A$2:$A$495,0))=D30),INDEX('Dashboard Items'!$C$2:$C$495,MATCH(E30,'Dashboard Items'!$A$2:$A$495,0)),"Level does not match ID")),"ID not found")) | H30: =IF(G30="","",IF(ISNUMBER(SEARCH(",",G30)),"Several items (the script lists them)",IFERROR(INDEX('Dashboard Items'!$B$2:$B$495,MATCH(G30,'Dashboard Items'!$A$2:$A$495,0))&": "&INDEX('Dashboard Items'!$C$2:$C$495,MATCH(G30,'Dashboard Items'!$A$2:$A$495,0)),"ID not found"))) | U30: =IF(B30="","",IF(IF(D30<>"",D30,IFERROR(INDEX('Dashboard Items'!$B$2:$B$495,MATCH(E30,'Dashboard Items'!$A$2:$A$495,0)),""))="Key Service",IF(O30="No","Key Service: shown, not counted","Counts in Key Service gauge"),IF(IF(D30<>"",D30,IFERROR(INDEX('Dashboard Items'!$B$2:$B$495,MATCH(E30,'Dashboard Items'!$A$2:$A$495,0)),""))="Program",IF(ISNUMBER(SEARCH("ks",G30)),IF(O30="No","Program, also at Key Service: not counted","Counts in Key Service gauge + sets Program chip"),IF(O30="No","Program: shown, no status chip","Sets Program status chip")),IF(IF(D30<>"",D30,IFERROR(INDEX('Dashboard Items'!$B$2:$B$495,MATCH(E30,'Dashboard Items'!$A$2:$A$495,0)),""))="Work System","Work System: shown, not counted","Check Level"))))
A31: =LEFT(B31, FIND("-", B31) - 1) | B31: HR-RETENTION | C31: Retain & develop: 1st year retention | D31: Program | E31: p24 | F31: =IF(E31="","",IFERROR(IF(INDEX('Dashboard Items'!$B$2:$B$495,MATCH(E31,'Dashboard Items'!$A$2:$A$495,0))="Objective","Objectives go in the next column",IF(OR(D31="",INDEX('Dashboard Items'!$B$2:$B$495,MATCH(E31,'Dashboard Items'!$A$2:$A$495,0))=D31),INDEX('Dashboard Items'!$C$2:$C$495,MATCH(E31,'Dashboard Items'!$A$2:$A$495,0)),"Level does not match ID")),"ID not found")) | H31: =IF(G31="","",IF(ISNUMBER(SEARCH(",",G31)),"Several items (the script lists them)",IFERROR(INDEX('Dashboard Items'!$B$2:$B$495,MATCH(G31,'Dashboard Items'!$A$2:$A$495,0))&": "&INDEX('Dashboard Items'!$C$2:$C$495,MATCH(G31,'Dashboard Items'!$A$2:$A$495,0)),"ID not found"))) | U31: =IF(B31="","",IF(IF(D31<>"",D31,IFERROR(INDEX('Dashboard Items'!$B$2:$B$495,MATCH(E31,'Dashboard Items'!$A$2:$A$495,0)),""))="Key Service",IF(O31="No","Key Service: shown, not counted","Counts in Key Service gauge"),IF(IF(D31<>"",D31,IFERROR(INDEX('Dashboard Items'!$B$2:$B$495,MATCH(E31,'Dashboard Items'!$A$2:$A$495,0)),""))="Program",IF(ISNUMBER(SEARCH("ks",G31)),IF(O31="No","Program, also at Key Service: not counted","Counts in Key Service gauge + sets Program chip"),IF(O31="No","Program: shown, no status chip","Sets Program status chip")),IF(IF(D31<>"",D31,IFERROR(INDEX('Dashboard Items'!$B$2:$B$495,MATCH(E31,'Dashboard Items'!$A$2:$A$495,0)),""))="Work System","Work System: shown, not counted","Check Level"))))
A32: =LEFT(B32, FIND("-", B32) - 1) | B32: HR-SAFETYTRAINING | C32: Safety Training | D32: Program | E32: p27 | F32: =IF(E32="","",IFERROR(IF(INDEX('Dashboard Items'!$B$2:$B$495,MATCH(E32,'Dashboard Items'!$A$2:$A$495,0))="Objective","Objectives go in the next column",IF(OR(D32="",INDEX('Dashboard Items'!$B$2:$B$495,MATCH(E32,'Dashboard Items'!$A$2:$A$495,0))=D32),INDEX('Dashboard Items'!$C$2:$C$495,MATCH(E32,'Dashboard Items'!$A$2:$A$495,0)),"Level does not match ID")),"ID not found")) | H32: =IF(G32="","",IF(ISNUMBER(SEARCH(",",G32)),"Several items (the script lists them)",IFERROR(INDEX('Dashboard Items'!$B$2:$B$495,MATCH(G32,'Dashboard Items'!$A$2:$A$495,0))&": "&INDEX('Dashboard Items'!$C$2:$C$495,MATCH(G32,'Dashboard Items'!$A$2:$A$495,0)),"ID not found"))) | U32: =IF(B32="","",IF(IF(D32<>"",D32,IFERROR(INDEX('Dashboard Items'!$B$2:$B$495,MATCH(E32,'Dashboard Items'!$A$2:$A$495,0)),""))="Key Service",IF(O32="No","Key Service: shown, not counted","Counts in Key Service gauge"),IF(IF(D32<>"",D32,IFERROR(INDEX('Dashboard Items'!$B$2:$B$495,MATCH(E32,'Dashboard Items'!$A$2:$A$495,0)),""))="Program",IF(ISNUMBER(SEARCH("ks",G32)),IF(O32="No","Program, also at Key Service: not counted","Counts in Key Service gauge + sets Program chip"),IF(O32="No","Program: shown, no status chip","Sets Program status chip")),IF(IF(D32<>"",D32,IFERROR(INDEX('Dashboard Items'!$B$2:$B$495,MATCH(E32,'Dashboard Items'!$A$2:$A$495,0)),""))="Work System","Work System: shown, not counted","Check Level"))))
A33: =LEFT(B33, FIND("-", B33) - 1) | B33: HR-TIMETOHIRE | C33: Hiring: time to hire from NeoGov | D33: Key Service | E33: ks5 | F33: =IF(E33="","",IFERROR(IF(INDEX('Dashboard Items'!$B$2:$B$495,MATCH(E33,'Dashboard Items'!$A$2:$A$495,0))="Objective","Objectives go in the next column",IF(OR(D33="",INDEX('Dashboard Items'!$B$2:$B$495,MATCH(E33,'Dashboard Items'!$A$2:$A$495,0))=D33),INDEX('Dashboard Items'!$C$2:$C$495,MATCH(E33,'Dashboard Items'!$A$2:$A$495,0)),"Level does not match ID")),"ID not found")) | G33: p24 | H33: =IF(G33="","",IF(ISNUMBER(SEARCH(",",G33)),"Several items (the script lists them)",IFERROR(INDEX('Dashboard Items'!$B$2:$B$495,MATCH(G33,'Dashboard Items'!$A$2:$A$495,0))&": "&INDEX('Dashboard Items'!$C$2:$C$495,MATCH(G33,'Dashboard Items'!$A$2:$A$495,0)),"ID not found"))) | Q33: Safety / Risk Administrator | U33: =IF(B33="","",IF(IF(D33<>"",D33,IFERROR(INDEX('Dashboard Items'!$B$2:$B$495,MATCH(E33,'Dashboard Items'!$A$2:$A$495,0)),""))="Key Service",IF(O33="No","Key Service: shown, not counted","Counts in Key Service gauge"),IF(IF(D33<>"",D33,IFERROR(INDEX('Dashboard Items'!$B$2:$B$495,MATCH(E33,'Dashboard Items'!$A$2:$A$495,0)),""))="Program",IF(ISNUMBER(SEARCH("ks",G33)),IF(O33="No","Program, also at Key Service: not counted","Counts in Key Service gauge + sets Program chip"),IF(O33="No","Program: shown, no status chip","Sets Program status chip")),IF(IF(D33<>"",D33,IFERROR(INDEX('Dashboard Items'!$B$2:$B$495,MATCH(E33,'Dashboard Items'!$A$2:$A$495,0)),""))="Work System","Work System: shown, not counted","Check Level"))))
A34: =LEFT(B34, FIND("-", B34) - 1) | B34: HR-TRAFFICSOURCE | C34: Attracting: traffic source data | D34: Program | E34: p24 | F34: =IF(E34="","",IFERROR(IF(INDEX('Dashboard Items'!$B$2:$B$495,MATCH(E34,'Dashboard Items'!$A$2:$A$495,0))="Objective","Objectives go in the next column",IF(OR(D34="",INDEX('Dashboard Items'!$B$2:$B$495,MATCH(E34,'Dashboard Items'!$A$2:$A$495,0))=D34),INDEX('Dashboard Items'!$C$2:$C$495,MATCH(E34,'Dashboard Items'!$A$2:$A$495,0)),"Level does not match ID")),"ID not found")) | H34: =IF(G34="","",IF(ISNUMBER(SEARCH(",",G34)),"Several items (the script lists them)",IFERROR(INDEX('Dashboard Items'!$B$2:$B$495,MATCH(G34,'Dashboard Items'!$A$2:$A$495,0))&": "&INDEX('Dashboard Items'!$C$2:$C$495,MATCH(G34,'Dashboard Items'!$A$2:$A$495,0)),"ID not found"))) | Q34: Safety / Risk Administrator | U34: =IF(B34="","",IF(IF(D34<>"",D34,IFERROR(INDEX('Dashboard Items'!$B$2:$B$495,MATCH(E34,'Dashboard Items'!$A$2:$A$495,0)),""))="Key Service",IF(O34="No","Key Service: shown, not counted","Counts in Key Service gauge"),IF(IF(D34<>"",D34,IFERROR(INDEX('Dashboard Items'!$B$2:$B$495,MATCH(E34,'Dashboard Items'!$A$2:$A$495,0)),""))="Program",IF(ISNUMBER(SEARCH("ks",G34)),IF(O34="No","Program, also at Key Service: not counted","Counts in Key Service gauge + sets Program chip"),IF(O34="No","Program: shown, no status chip","Sets Program status chip")),IF(IF(D34<>"",D34,IFERROR(INDEX('Dashboard Items'!$B$2:$B$495,MATCH(E34,'Dashboard Items'!$A$2:$A$495,0)),""))="Work System","Work System: shown, not counted","Check Level"))))
A35: =LEFT(B35, FIND("-", B35) - 1) | B35: HR-TUITIONREIMB | C35: Utilization of tuition reimbursement program | D35: Program | E35: p22 | F35: =IF(E35="","",IFERROR(IF(INDEX('Dashboard Items'!$B$2:$B$495,MATCH(E35,'Dashboard Items'!$A$2:$A$495,0))="Objective","Objectives go in the next column",IF(OR(D35="",INDEX('Dashboard Items'!$B$2:$B$495,MATCH(E35,'Dashboard Items'!$A$2:$A$495,0))=D35),INDEX('Dashboard Items'!$C$2:$C$495,MATCH(E35,'Dashboard Items'!$A$2:$A$495,0)),"Level does not match ID")),"ID not found")) | H35: =IF(G35="","",IF(ISNUMBER(SEARCH(",",G35)),"Several items (the script lists them)",IFERROR(INDEX('Dashboard Items'!$B$2:$B$495,MATCH(G35,'Dashboard Items'!$A$2:$A$495,0))&": "&INDEX('Dashboard Items'!$C$2:$C$495,MATCH(G35,'Dashboard Items'!$A$2:$A$495,0)),"ID not found"))) | U35: =IF(B35="","",IF(IF(D35<>"",D35,IFERROR(INDEX('Dashboard Items'!$B$2:$B$495,MATCH(E35,'Dashboard Items'!$A$2:$A$495,0)),""))="Key Service",IF(O35="No","Key Service: shown, not counted","Counts in Key Service gauge"),IF(IF(D35<>"",D35,IFERROR(INDEX('Dashboard Items'!$B$2:$B$495,MATCH(E35,'Dashboard Items'!$A$2:$A$495,0)),""))="Program",IF(ISNUMBER(SEARCH("ks",G35)),IF(O35="No","Program, also at Key Service: not counted","Counts in Key Service gauge + sets Program chip"),IF(O35="No","Program: shown, no status chip","Sets Program status chip")),IF(IF(D35<>"",D35,IFERROR(INDEX('Dashboard Items'!$B$2:$B$495,MATCH(E35,'Dashboard Items'!$A$2:$A$495,0)),""))="Work System","Work System: shown, not counted","Check Level"))))
A36: =LEFT(B36, FIND("-", B36) - 1) | B36: HR-TURNRATE | C36: Retain & develop: turnover rate by voluntary and involuntary | D36: Key Service | E36: ks5 | F36: =IF(E36="","",IFERROR(IF(INDEX('Dashboard Items'!$B$2:$B$495,MATCH(E36,'Dashboard Items'!$A$2:$A$495,0))="Objective","Objectives go in the next column",IF(OR(D36="",INDEX('Dashboard Items'!$B$2:$B$495,MATCH(E36,'Dashboard Items'!$A$2:$A$495,0))=D36),INDEX('Dashboard Items'!$C$2:$C$495,MATCH(E36,'Dashboard Items'!$A$2:$A$495,0)),"Level does not match ID")),"ID not found")) | G36: p24 | H36: =IF(G36="","",IF(ISNUMBER(SEARCH(",",G36)),"Several items (the script lists them)",IFERROR(INDEX('Dashboard Items'!$B$2:$B$495,MATCH(G36,'Dashboard Items'!$A$2:$A$495,0))&": "&INDEX('Dashboard Items'!$C$2:$C$495,MATCH(G36,'Dashboard Items'!$A$2:$A$495,0)),"ID not found"))) | I36: percent | J36: 2 | K36: No | L36: Target | P36: Every year | S36: Cumulative turnover rate for City employees each fiscal year. Lower is better. | T36: Target: 20%. Benchmark: the Colorado average (18% in 2021, 20% in 2022, 18% in 2023); from 2024, SHRM's 20% average for government, as the Colorado figure is not available. Shown as one total; a voluntary/involuntary split is not available yet. | U36: =IF(B36="","",IF(IF(D36<>"",D36,IFERROR(INDEX('Dashboard Items'!$B$2:$B$495,MATCH(E36,'Dashboard Items'!$A$2:$A$495,0)),""))="Key Service",IF(O36="No","Key Service: shown, not counted","Counts in Key Service gauge"),IF(IF(D36<>"",D36,IFERROR(INDEX('Dashboard Items'!$B$2:$B$495,MATCH(E36,'Dashboard Items'!$A$2:$A$495,0)),""))="Program",IF(ISNUMBER(SEARCH("ks",G36)),IF(O36="No","Program, also at Key Service: not counted","Counts in Key Service gauge + sets Program chip"),IF(O36="No","Program: shown, no status chip","Sets Program status chip")),IF(IF(D36<>"",D36,IFERROR(INDEX('Dashboard Items'!$B$2:$B$495,MATCH(E36,'Dashboard Items'!$A$2:$A$495,0)),""))="Work System","Work System: shown, not counted","Check Level"))))
A37: =LEFT(B37, FIND("-", B37) - 1) | B37: HR-VACRATE | C37: Retain & develop: vacancy rate | D37: Program | E37: p24 | F37: =IF(E37="","",IFERROR(IF(INDEX('Dashboard Items'!$B$2:$B$495,MATCH(E37,'Dashboard Items'!$A$2:$A$495,0))="Objective","Objectives go in the next column",IF(OR(D37="",INDEX('Dashboard Items'!$B$2:$B$495,MATCH(E37,'Dashboard Items'!$A$2:$A$495,0))=D37),INDEX('Dashboard Items'!$C$2:$C$495,MATCH(E37,'Dashboard Items'!$A$2:$A$495,0)),"Level does not match ID")),"ID not found")) | H37: =IF(G37="","",IF(ISNUMBER(SEARCH(",",G37)),"Several items (the script lists them)",IFERROR(INDEX('Dashboard Items'!$B$2:$B$495,MATCH(G37,'Dashboard Items'!$A$2:$A$495,0))&": "&INDEX('Dashboard Items'!$C$2:$C$495,MATCH(G37,'Dashboard Items'!$A$2:$A$495,0)),"ID not found"))) | K37: Yes | Q37: Safety / Risk Administrator | U37: =IF(B37="","",IF(IF(D37<>"",D37,IFERROR(INDEX('Dashboard Items'!$B$2:$B$495,MATCH(E37,'Dashboard Items'!$A$2:$A$495,0)),""))="Key Service",IF(O37="No","Key Service: shown, not counted","Counts in Key Service gauge"),IF(IF(D37<>"",D37,IFERROR(INDEX('Dashboard Items'!$B$2:$B$495,MATCH(E37,'Dashboard Items'!$A$2:$A$495,0)),""))="Program",IF(ISNUMBER(SEARCH("ks",G37)),IF(O37="No","Program, also at Key Service: not counted","Counts in Key Service gauge + sets Program chip"),IF(O37="No","Program: shown, no status chip","Sets Program status chip")),IF(IF(D37<>"",D37,IFERROR(INDEX('Dashboard Items'!$B$2:$B$495,MATCH(E37,'Dashboard Items'!$A$2:$A$495,0)),""))="Work System","Work System: shown, not counted","Check Level"))))
A38: =LEFT(B38, FIND("-", B38) - 1) | B38: IT-PHISHRATE | C38: Organization phish prone rate | D38: Program | E38: p31 | F38: =IF(E38="","",IFERROR(IF(INDEX('Dashboard Items'!$B$2:$B$495,MATCH(E38,'Dashboard Items'!$A$2:$A$495,0))="Objective","Objectives go in the next column",IF(OR(D38="",INDEX('Dashboard Items'!$B$2:$B$495,MATCH(E38,'Dashboard Items'!$A$2:$A$495,0))=D38),INDEX('Dashboard Items'!$C$2:$C$495,MATCH(E38,'Dashboard Items'!$A$2:$A$495,0)),"Level does not match ID")),"ID not found")) | G38: ks7 | H38: =IF(G38="","",IF(ISNUMBER(SEARCH(",",G38)),"Several items (the script lists them)",IFERROR(INDEX('Dashboard Items'!$B$2:$B$495,MATCH(G38,'Dashboard Items'!$A$2:$A$495,0))&": "&INDEX('Dashboard Items'!$C$2:$C$495,MATCH(G38,'Dashboard Items'!$A$2:$A$495,0)),"ID not found"))) | I38: percent | J38: 2 | K38: No | L38: Target | M38: 5 | N38: 15 | O38: Yes | P38: Every Quarter | Q38: IT Director | R38: KnowBe4 | U38: =IF(B38="","",IF(IF(D38<>"",D38,IFERROR(INDEX('Dashboard Items'!$B$2:$B$495,MATCH(E38,'Dashboard Items'!$A$2:$A$495,0)),""))="Key Service",IF(O38="No","Key Service: shown, not counted","Counts in Key Service gauge"),IF(IF(D38<>"",D38,IFERROR(INDEX('Dashboard Items'!$B$2:$B$495,MATCH(E38,'Dashboard Items'!$A$2:$A$495,0)),""))="Program",IF(ISNUMBER(SEARCH("ks",G38)),IF(O38="No","Program, also at Key Service: not counted","Counts in Key Service gauge + sets Program chip"),IF(O38="No","Program: shown, no status chip","Sets Program status chip")),IF(IF(D38<>"",D38,IFERROR(INDEX('Dashboard Items'!$B$2:$B$495,MATCH(E38,'Dashboard Items'!$A$2:$A$495,0)),""))="Work System","Work System: shown, not counted","Check Level"))))
A39: =LEFT(B39, FIND("-", B39) - 1) | B39: IT-PITSURV | C39: Point in time help desk survey | D39: Program | E39: p34 | F39: =IF(E39="","",IFERROR(IF(INDEX('Dashboard Items'!$B$2:$B$495,MATCH(E39,'Dashboard Items'!$A$2:$A$495,0))="Objective","Objectives go in the next column",IF(OR(D39="",INDEX('Dashboard Items'!$B$2:$B$495,MATCH(E39,'Dashboard Items'!$A$2:$A$495,0))=D39),INDEX('Dashboard Items'!$C$2:$C$495,MATCH(E39,'Dashboard Items'!$A$2:$A$495,0)),"Level does not match ID")),"ID not found")) | G39: ks7 | H39: =IF(G39="","",IF(ISNUMBER(SEARCH(",",G39)),"Several items (the script lists them)",IFERROR(INDEX('Dashboard Items'!$B$2:$B$495,MATCH(G39,'Dashboard Items'!$A$2:$A$495,0))&": "&INDEX('Dashboard Items'!$C$2:$C$495,MATCH(G39,'Dashboard Items'!$A$2:$A$495,0)),"ID not found"))) | I39: percent | J39: 1 | K39: Yes | L39: Target | M39: 5 | N39: 15 | O39: Yes | P39: Every year | Q39: IT Director | R39: SysAid | U39: =IF(B39="","",IF(IF(D39<>"",D39,IFERROR(INDEX('Dashboard Items'!$B$2:$B$495,MATCH(E39,'Dashboard Items'!$A$2:$A$495,0)),""))="Key Service",IF(O39="No","Key Service: shown, not counted","Counts in Key Service gauge"),IF(IF(D39<>"",D39,IFERROR(INDEX('Dashboard Items'!$B$2:$B$495,MATCH(E39,'Dashboard Items'!$A$2:$A$495,0)),""))="Program",IF(ISNUMBER(SEARCH("ks",G39)),IF(O39="No","Program, also at Key Service: not counted","Counts in Key Service gauge + sets Program chip"),IF(O39="No","Program: shown, no status chip","Sets Program status chip")),IF(IF(D39<>"",D39,IFERROR(INDEX('Dashboard Items'!$B$2:$B$495,MATCH(E39,'Dashboard Items'!$A$2:$A$495,0)),""))="Work System","Work System: shown, not counted","Check Level"))))
A40: =LEFT(B40, FIND("-", B40) - 1) | B40: IT-TIXSLA | C40: Help desk ticket SLA compliance | D40: Program | E40: p34 | F40: =IF(E40="","",IFERROR(IF(INDEX('Dashboard Items'!$B$2:$B$495,MATCH(E40,'Dashboard Items'!$A$2:$A$495,0))="Objective","Objectives go in the next column",IF(OR(D40="",INDEX('Dashboard Items'!$B$2:$B$495,MATCH(E40,'Dashboard Items'!$A$2:$A$495,0))=D40),INDEX('Dashboard Items'!$C$2:$C$495,MATCH(E40,'Dashboard Items'!$A$2:$A$495,0)),"Level does not match ID")),"ID not found")) | G40: ks7 | H40: =IF(G40="","",IF(ISNUMBER(SEARCH(",",G40)),"Several items (the script lists them)",IFERROR(INDEX('Dashboard Items'!$B$2:$B$495,MATCH(G40,'Dashboard Items'!$A$2:$A$495,0))&": "&INDEX('Dashboard Items'!$C$2:$C$495,MATCH(G40,'Dashboard Items'!$A$2:$A$495,0)),"ID not found"))) | I40: percent | J40: 2 | K40: Yes | L40: Target | M40: 5 | N40: 15 | O40: Yes | P40: Every year | Q40: IT Director | R40: SysAid | U40: =IF(B40="","",IF(IF(D40<>"",D40,IFERROR(INDEX('Dashboard Items'!$B$2:$B$495,MATCH(E40,'Dashboard Items'!$A$2:$A$495,0)),""))="Key Service",IF(O40="No","Key Service: shown, not counted","Counts in Key Service gauge"),IF(IF(D40<>"",D40,IFERROR(INDEX('Dashboard Items'!$B$2:$B$495,MATCH(E40,'Dashboard Items'!$A$2:$A$495,0)),""))="Program",IF(ISNUMBER(SEARCH("ks",G40)),IF(O40="No","Program, also at Key Service: not counted","Counts in Key Service gauge + sets Program chip"),IF(O40="No","Program: shown, no status chip","Sets Program status chip")),IF(IF(D40<>"",D40,IFERROR(INDEX('Dashboard Items'!$B$2:$B$495,MATCH(E40,'Dashboard Items'!$A$2:$A$495,0)),""))="Work System","Work System: shown, not counted","Check Level"))))
A41: =LEFT(B41, FIND("-", B41) - 1) | B41: IT-UPTIME | C41: Network uptime | D41: Program | E41: p30 | F41: =IF(E41="","",IFERROR(IF(INDEX('Dashboard Items'!$B$2:$B$495,MATCH(E41,'Dashboard Items'!$A$2:$A$495,0))="Objective","Objectives go in the next column",IF(OR(D41="",INDEX('Dashboard Items'!$B$2:$B$495,MATCH(E41,'Dashboard Items'!$A$2:$A$495,0))=D41),INDEX('Dashboard Items'!$C$2:$C$495,MATCH(E41,'Dashboard Items'!$A$2:$A$495,0)),"Level does not match ID")),"ID not found")) | G41: ks7, ob14 | H41: =IF(G41="","",IF(ISNUMBER(SEARCH(",",G41)),"Several items (the script lists them)",IFERROR(INDEX('Dashboard Items'!$B$2:$B$495,MATCH(G41,'Dashboard Items'!$A$2:$A$495,0))&": "&INDEX('Dashboard Items'!$C$2:$C$495,MATCH(G41,'Dashboard Items'!$A$2:$A$495,0)),"ID not found"))) | I41: percent | J41: 2 | K41: Yes | L41: Target | M41: 5 | N41: 15 | O41: Yes | P41: Every year | Q41: IT Director | R41: Solar Winds | U41: =IF(B41="","",IF(IF(D41<>"",D41,IFERROR(INDEX('Dashboard Items'!$B$2:$B$495,MATCH(E41,'Dashboard Items'!$A$2:$A$495,0)),""))="Key Service",IF(O41="No","Key Service: shown, not counted","Counts in Key Service gauge"),IF(IF(D41<>"",D41,IFERROR(INDEX('Dashboard Items'!$B$2:$B$495,MATCH(E41,'Dashboard Items'!$A$2:$A$495,0)),""))="Program",IF(ISNUMBER(SEARCH("ks",G41)),IF(O41="No","Program, also at Key Service: not counted","Counts in Key Service gauge + sets Program chip"),IF(O41="No","Program: shown, no status chip","Sets Program status chip")),IF(IF(D41<>"",D41,IFERROR(INDEX('Dashboard Items'!$B$2:$B$495,MATCH(E41,'Dashboard Items'!$A$2:$A$495,0)),""))="Work System","Work System: shown, not counted","Check Level"))))
A42: =LEFT(B42, FIND("-", B42) - 1) | B42: LIB-CIRCULATION | C42: Total circulation (physical and digital) | D42: Program | E42: p82 | F42: =IF(E42="","",IFERROR(IF(INDEX('Dashboard Items'!$B$2:$B$495,MATCH(E42,'Dashboard Items'!$A$2:$A$495,0))="Objective","Objectives go in the next column",IF(OR(D42="",INDEX('Dashboard Items'!$B$2:$B$495,MATCH(E42,'Dashboard Items'!$A$2:$A$495,0))=D42),INDEX('Dashboard Items'!$C$2:$C$495,MATCH(E42,'Dashboard Items'!$A$2:$A$495,0)),"Level does not match ID")),"ID not found")) | G42: ks17 | H42: =IF(G42="","",IF(ISNUMBER(SEARCH(",",G42)),"Several items (the script lists them)",IFERROR(INDEX('Dashboard Items'!$B$2:$B$495,MATCH(G42,'Dashboard Items'!$A$2:$A$495,0))&": "&INDEX('Dashboard Items'!$C$2:$C$495,MATCH(G42,'Dashboard Items'!$A$2:$A$495,0)),"ID not found"))) | I42: number | J42: 0 | K42: Yes | L42: Target | M42: 0 | N42: 0 | O42: Yes | P42: Every Year | Q42: Library Director | U42: =IF(B42="","",IF(IF(D42<>"",D42,IFERROR(INDEX('Dashboard Items'!$B$2:$B$495,MATCH(E42,'Dashboard Items'!$A$2:$A$495,0)),""))="Key Service",IF(O42="No","Key Service: shown, not counted","Counts in Key Service gauge"),IF(IF(D42<>"",D42,IFERROR(INDEX('Dashboard Items'!$B$2:$B$495,MATCH(E42,'Dashboard Items'!$A$2:$A$495,0)),""))="Program",IF(ISNUMBER(SEARCH("ks",G42)),IF(O42="No","Program, also at Key Service: not counted","Counts in Key Service gauge + sets Program chip"),IF(O42="No","Program: shown, no status chip","Sets Program status chip")),IF(IF(D42<>"",D42,IFERROR(INDEX('Dashboard Items'!$B$2:$B$495,MATCH(E42,'Dashboard Items'!$A$2:$A$495,0)),""))="Work System","Work System: shown, not counted","Check Level"))))
A43: =LEFT(B43, FIND("-", B43) - 1) | B43: LIB-COMPANDWIFI | C43: Unique wireless use and Total Computer Use | D43: Program | E43: p83 | F43: =IF(E43="","",IFERROR(IF(INDEX('Dashboard Items'!$B$2:$B$495,MATCH(E43,'Dashboard Items'!$A$2:$A$495,0))="Objective","Objectives go in the next column",IF(OR(D43="",INDEX('Dashboard Items'!$B$2:$B$495,MATCH(E43,'Dashboard Items'!$A$2:$A$495,0))=D43),INDEX('Dashboard Items'!$C$2:$C$495,MATCH(E43,'Dashboard Items'!$A$2:$A$495,0)),"Level does not match ID")),"ID not found")) | H43: =IF(G43="","",IF(ISNUMBER(SEARCH(",",G43)),"Several items (the script lists them)",IFERROR(INDEX('Dashboard Items'!$B$2:$B$495,MATCH(G43,'Dashboard Items'!$A$2:$A$495,0))&": "&INDEX('Dashboard Items'!$C$2:$C$495,MATCH(G43,'Dashboard Items'!$A$2:$A$495,0)),"ID not found"))) | I43: number | J43: 2 | K43: Yes | L43: Target | M43: 0 | N43: 0 | O43: Yes | P43: Every Year | Q43: Library Director | U43: =IF(B43="","",IF(IF(D43<>"",D43,IFERROR(INDEX('Dashboard Items'!$B$2:$B$495,MATCH(E43,'Dashboard Items'!$A$2:$A$495,0)),""))="Key Service",IF(O43="No","Key Service: shown, not counted","Counts in Key Service gauge"),IF(IF(D43<>"",D43,IFERROR(INDEX('Dashboard Items'!$B$2:$B$495,MATCH(E43,'Dashboard Items'!$A$2:$A$495,0)),""))="Program",IF(ISNUMBER(SEARCH("ks",G43)),IF(O43="No","Program, also at Key Service: not counted","Counts in Key Service gauge + sets Program chip"),IF(O43="No","Program: shown, no status chip","Sets Program status chip")),IF(IF(D43<>"",D43,IFERROR(INDEX('Dashboard Items'!$B$2:$B$495,MATCH(E43,'Dashboard Items'!$A$2:$A$495,0)),""))="Work System","Work System: shown, not counted","Check Level"))))
A44: =LEFT(B44, FIND("-", B44) - 1) | B44: LIB-OUTREACHCON | C44: Total outreach contacts | D44: Program | E44: p85 | F44: =IF(E44="","",IFERROR(IF(INDEX('Dashboard Items'!$B$2:$B$495,MATCH(E44,'Dashboard Items'!$A$2:$A$495,0))="Objective","Objectives go in the next column",IF(OR(D44="",INDEX('Dashboard Items'!$B$2:$B$495,MATCH(E44,'Dashboard Items'!$A$2:$A$495,0))=D44),INDEX('Dashboard Items'!$C$2:$C$495,MATCH(E44,'Dashboard Items'!$A$2:$A$495,0)),"Level does not match ID")),"ID not found")) | H44: =IF(G44="","",IF(ISNUMBER(SEARCH(",",G44)),"Several items (the script lists them)",IFERROR(INDEX('Dashboard Items'!$B$2:$B$495,MATCH(G44,'Dashboard Items'!$A$2:$A$495,0))&": "&INDEX('Dashboard Items'!$C$2:$C$495,MATCH(G44,'Dashboard Items'!$A$2:$A$495,0)),"ID not found"))) | I44: number | J44: 2 | K44: Yes | L44: Target | M44: 0 | N44: 0 | O44: Yes | P44: Every Year | Q44: Library Director | U44: =IF(B44="","",IF(IF(D44<>"",D44,IFERROR(INDEX('Dashboard Items'!$B$2:$B$495,MATCH(E44,'Dashboard Items'!$A$2:$A$495,0)),""))="Key Service",IF(O44="No","Key Service: shown, not counted","Counts in Key Service gauge"),IF(IF(D44<>"",D44,IFERROR(INDEX('Dashboard Items'!$B$2:$B$495,MATCH(E44,'Dashboard Items'!$A$2:$A$495,0)),""))="Program",IF(ISNUMBER(SEARCH("ks",G44)),IF(O44="No","Program, also at Key Service: not counted","Counts in Key Service gauge + sets Program chip"),IF(O44="No","Program: shown, no status chip","Sets Program status chip")),IF(IF(D44<>"",D44,IFERROR(INDEX('Dashboard Items'!$B$2:$B$495,MATCH(E44,'Dashboard Items'!$A$2:$A$495,0)),""))="Work System","Work System: shown, not counted","Check Level"))))
A45: =LEFT(B45, FIND("-", B45) - 1) | B45: LIB-PATRONPPROG | C45: Patron per program | D45: Program | E45: p85 | F45: =IF(E45="","",IFERROR(IF(INDEX('Dashboard Items'!$B$2:$B$495,MATCH(E45,'Dashboard Items'!$A$2:$A$495,0))="Objective","Objectives go in the next column",IF(OR(D45="",INDEX('Dashboard Items'!$B$2:$B$495,MATCH(E45,'Dashboard Items'!$A$2:$A$495,0))=D45),INDEX('Dashboard Items'!$C$2:$C$495,MATCH(E45,'Dashboard Items'!$A$2:$A$495,0)),"Level does not match ID")),"ID not found")) | H45: =IF(G45="","",IF(ISNUMBER(SEARCH(",",G45)),"Several items (the script lists them)",IFERROR(INDEX('Dashboard Items'!$B$2:$B$495,MATCH(G45,'Dashboard Items'!$A$2:$A$495,0))&": "&INDEX('Dashboard Items'!$C$2:$C$495,MATCH(G45,'Dashboard Items'!$A$2:$A$495,0)),"ID not found"))) | I45: number | J45: 2 | K45: Yes | L45: Target | M45: 0 | N45: 0 | O45: Yes | P45: Every Year | Q45: Library Director | U45: =IF(B45="","",IF(IF(D45<>"",D45,IFERROR(INDEX('Dashboard Items'!$B$2:$B$495,MATCH(E45,'Dashboard Items'!$A$2:$A$495,0)),""))="Key Service",IF(O45="No","Key Service: shown, not counted","Counts in Key Service gauge"),IF(IF(D45<>"",D45,IFERROR(INDEX('Dashboard Items'!$B$2:$B$495,MATCH(E45,'Dashboard Items'!$A$2:$A$495,0)),""))="Program",IF(ISNUMBER(SEARCH("ks",G45)),IF(O45="No","Program, also at Key Service: not counted","Counts in Key Service gauge + sets Program chip"),IF(O45="No","Program: shown, no status chip","Sets Program status chip")),IF(IF(D45<>"",D45,IFERROR(INDEX('Dashboard Items'!$B$2:$B$495,MATCH(E45,'Dashboard Items'!$A$2:$A$495,0)),""))="Work System","Work System: shown, not counted","Check Level"))))
A46: =LEFT(B46, FIND("-", B46) - 1) | B46: LIB-PROGATTEND | C46: Total program attendance | D46: Program | E46: p85 | F46: =IF(E46="","",IFERROR(IF(INDEX('Dashboard Items'!$B$2:$B$495,MATCH(E46,'Dashboard Items'!$A$2:$A$495,0))="Objective","Objectives go in the next column",IF(OR(D46="",INDEX('Dashboard Items'!$B$2:$B$495,MATCH(E46,'Dashboard Items'!$A$2:$A$495,0))=D46),INDEX('Dashboard Items'!$C$2:$C$495,MATCH(E46,'Dashboard Items'!$A$2:$A$495,0)),"Level does not match ID")),"ID not found")) | H46: =IF(G46="","",IF(ISNUMBER(SEARCH(",",G46)),"Several items (the script lists them)",IFERROR(INDEX('Dashboard Items'!$B$2:$B$495,MATCH(G46,'Dashboard Items'!$A$2:$A$495,0))&": "&INDEX('Dashboard Items'!$C$2:$C$495,MATCH(G46,'Dashboard Items'!$A$2:$A$495,0)),"ID not found"))) | I46: number | J46: 2 | K46: Yes | L46: Target | M46: 0 | N46: 0 | O46: Yes | P46: Every Year | Q46: Library Director | U46: =IF(B46="","",IF(IF(D46<>"",D46,IFERROR(INDEX('Dashboard Items'!$B$2:$B$495,MATCH(E46,'Dashboard Items'!$A$2:$A$495,0)),""))="Key Service",IF(O46="No","Key Service: shown, not counted","Counts in Key Service gauge"),IF(IF(D46<>"",D46,IFERROR(INDEX('Dashboard Items'!$B$2:$B$495,MATCH(E46,'Dashboard Items'!$A$2:$A$495,0)),""))="Program",IF(ISNUMBER(SEARCH("ks",G46)),IF(O46="No","Program, also at Key Service: not counted","Counts in Key Service gauge + sets Program chip"),IF(O46="No","Program: shown, no status chip","Sets Program status chip")),IF(IF(D46<>"",D46,IFERROR(INDEX('Dashboard Items'!$B$2:$B$495,MATCH(E46,'Dashboard Items'!$A$2:$A$495,0)),""))="Work System","Work System: shown, not counted","Check Level"))))
A47: =LEFT(B47, FIND("-", B47) - 1) | B47: LIB-REFQUEST | C47: Reference Questions - 5 segments (avg. per month, manually counted one day per mo) | D47: Program | E47: p84 | F47: =IF(E47="","",IFERROR(IF(INDEX('Dashboard Items'!$B$2:$B$495,MATCH(E47,'Dashboard Items'!$A$2:$A$495,0))="Objective","Objectives go in the next column",IF(OR(D47="",INDEX('Dashboard Items'!$B$2:$B$495,MATCH(E47,'Dashboard Items'!$A$2:$A$495,0))=D47),INDEX('Dashboard Items'!$C$2:$C$495,MATCH(E47,'Dashboard Items'!$A$2:$A$495,0)),"Level does not match ID")),"ID not found")) | H47: =IF(G47="","",IF(ISNUMBER(SEARCH(",",G47)),"Several items (the script lists them)",IFERROR(INDEX('Dashboard Items'!$B$2:$B$495,MATCH(G47,'Dashboard Items'!$A$2:$A$495,0))&": "&INDEX('Dashboard Items'!$C$2:$C$495,MATCH(G47,'Dashboard Items'!$A$2:$A$495,0)),"ID not found"))) | I47: number | J47: 2 | K47: Yes | L47: Target | M47: 0 | N47: 0 | O47: Yes | P47: Every Year | Q47: Library Director | U47: =IF(B47="","",IF(IF(D47<>"",D47,IFERROR(INDEX('Dashboard Items'!$B$2:$B$495,MATCH(E47,'Dashboard Items'!$A$2:$A$495,0)),""))="Key Service",IF(O47="No","Key Service: shown, not counted","Counts in Key Service gauge"),IF(IF(D47<>"",D47,IFERROR(INDEX('Dashboard Items'!$B$2:$B$495,MATCH(E47,'Dashboard Items'!$A$2:$A$495,0)),""))="Program",IF(ISNUMBER(SEARCH("ks",G47)),IF(O47="No","Program, also at Key Service: not counted","Counts in Key Service gauge + sets Program chip"),IF(O47="No","Program: shown, no status chip","Sets Program status chip")),IF(IF(D47<>"",D47,IFERROR(INDEX('Dashboard Items'!$B$2:$B$495,MATCH(E47,'Dashboard Items'!$A$2:$A$495,0)),""))="Work System","Work System: shown, not counted","Check Level"))))
A48: =LEFT(B48, FIND("-", B48) - 1) | B48: LIB-ROOMRENTALS | C48: Program room rentals | D48: Program | E48: p83 | F48: =IF(E48="","",IFERROR(IF(INDEX('Dashboard Items'!$B$2:$B$495,MATCH(E48,'Dashboard Items'!$A$2:$A$495,0))="Objective","Objectives go in the next column",IF(OR(D48="",INDEX('Dashboard Items'!$B$2:$B$495,MATCH(E48,'Dashboard Items'!$A$2:$A$495,0))=D48),INDEX('Dashboard Items'!$C$2:$C$495,MATCH(E48,'Dashboard Items'!$A$2:$A$495,0)),"Level does not match ID")),"ID not found")) | H48: =IF(G48="","",IF(ISNUMBER(SEARCH(",",G48)),"Several items (the script lists them)",IFERROR(INDEX('Dashboard Items'!$B$2:$B$495,MATCH(G48,'Dashboard Items'!$A$2:$A$495,0))&": "&INDEX('Dashboard Items'!$C$2:$C$495,MATCH(G48,'Dashboard Items'!$A$2:$A$495,0)),"ID not found"))) | I48: number | J48: 2 | K48: Yes | L48: Target | M48: 0 | N48: 0 | O48: Yes | P48: Every Year | Q48: Library Director | U48: =IF(B48="","",IF(IF(D48<>"",D48,IFERROR(INDEX('Dashboard Items'!$B$2:$B$495,MATCH(E48,'Dashboard Items'!$A$2:$A$495,0)),""))="Key Service",IF(O48="No","Key Service: shown, not counted","Counts in Key Service gauge"),IF(IF(D48<>"",D48,IFERROR(INDEX('Dashboard Items'!$B$2:$B$495,MATCH(E48,'Dashboard Items'!$A$2:$A$495,0)),""))="Program",IF(ISNUMBER(SEARCH("ks",G48)),IF(O48="No","Program, also at Key Service: not counted","Counts in Key Service gauge + sets Program chip"),IF(O48="No","Program: shown, no status chip","Sets Program status chip")),IF(IF(D48<>"",D48,IFERROR(INDEX('Dashboard Items'!$B$2:$B$495,MATCH(E48,'Dashboard Items'!$A$2:$A$495,0)),""))="Work System","Work System: shown, not counted","Check Level"))))
A49: =LEFT(B49, FIND("-", B49) - 1) | B49: LIB-SOCIALENG | C49: Total social media user engagement | D49: Program | E49: p85 | F49: =IF(E49="","",IFERROR(IF(INDEX('Dashboard Items'!$B$2:$B$495,MATCH(E49,'Dashboard Items'!$A$2:$A$495,0))="Objective","Objectives go in the next column",IF(OR(D49="",INDEX('Dashboard Items'!$B$2:$B$495,MATCH(E49,'Dashboard Items'!$A$2:$A$495,0))=D49),INDEX('Dashboard Items'!$C$2:$C$495,MATCH(E49,'Dashboard Items'!$A$2:$A$495,0)),"Level does not match ID")),"ID not found")) | H49: =IF(G49="","",IF(ISNUMBER(SEARCH(",",G49)),"Several items (the script lists them)",IFERROR(INDEX('Dashboard Items'!$B$2:$B$495,MATCH(G49,'Dashboard Items'!$A$2:$A$495,0))&": "&INDEX('Dashboard Items'!$C$2:$C$495,MATCH(G49,'Dashboard Items'!$A$2:$A$495,0)),"ID not found"))) | I49: number | J49: 2 | K49: Yes | L49: Target | M49: 0 | N49: 0 | O49: Yes | P49: Every Year | Q49: Library Director | U49: =IF(B49="","",IF(IF(D49<>"",D49,IFERROR(INDEX('Dashboard Items'!$B$2:$B$495,MATCH(E49,'Dashboard Items'!$A$2:$A$495,0)),""))="Key Service",IF(O49="No","Key Service: shown, not counted","Counts in Key Service gauge"),IF(IF(D49<>"",D49,IFERROR(INDEX('Dashboard Items'!$B$2:$B$495,MATCH(E49,'Dashboard Items'!$A$2:$A$495,0)),""))="Program",IF(ISNUMBER(SEARCH("ks",G49)),IF(O49="No","Program, also at Key Service: not counted","Counts in Key Service gauge + sets Program chip"),IF(O49="No","Program: shown, no status chip","Sets Program status chip")),IF(IF(D49<>"",D49,IFERROR(INDEX('Dashboard Items'!$B$2:$B$495,MATCH(E49,'Dashboard Items'!$A$2:$A$495,0)),""))="Work System","Work System: shown, not counted","Check Level"))))
A50: =LEFT(B50, FIND("-", B50) - 1) | B50: LIB-VISITS | C50: Visitation | D50: Program | E50: p83 | F50: =IF(E50="","",IFERROR(IF(INDEX('Dashboard Items'!$B$2:$B$495,MATCH(E50,'Dashboard Items'!$A$2:$A$495,0))="Objective","Objectives go in the next column",IF(OR(D50="",INDEX('Dashboard Items'!$B$2:$B$495,MATCH(E50,'Dashboard Items'!$A$2:$A$495,0))=D50),INDEX('Dashboard Items'!$C$2:$C$495,MATCH(E50,'Dashboard Items'!$A$2:$A$495,0)),"Level does not match ID")),"ID not found")) | G50: ks17 | H50: =IF(G50="","",IF(ISNUMBER(SEARCH(",",G50)),"Several items (the script lists them)",IFERROR(INDEX('Dashboard Items'!$B$2:$B$495,MATCH(G50,'Dashboard Items'!$A$2:$A$495,0))&": "&INDEX('Dashboard Items'!$C$2:$C$495,MATCH(G50,'Dashboard Items'!$A$2:$A$495,0)),"ID not found"))) | I50: number | J50: 0 | K50: Yes | L50: Target | M50: 0 | N50: 0 | O50: Yes | P50: Every Year | Q50: Library Director | U50: =IF(B50="","",IF(IF(D50<>"",D50,IFERROR(INDEX('Dashboard Items'!$B$2:$B$495,MATCH(E50,'Dashboard Items'!$A$2:$A$495,0)),""))="Key Service",IF(O50="No","Key Service: shown, not counted","Counts in Key Service gauge"),IF(IF(D50<>"",D50,IFERROR(INDEX('Dashboard Items'!$B$2:$B$495,MATCH(E50,'Dashboard Items'!$A$2:$A$495,0)),""))="Program",IF(ISNUMBER(SEARCH("ks",G50)),IF(O50="No","Program, also at Key Service: not counted","Counts in Key Service gauge + sets Program chip"),IF(O50="No","Program: shown, no status chip","Sets Program status chip")),IF(IF(D50<>"",D50,IFERROR(INDEX('Dashboard Items'!$B$2:$B$495,MATCH(E50,'Dashboard Items'!$A$2:$A$495,0)),""))="Work System","Work System: shown, not counted","Check Level"))))
A51: =LEFT(B51, FIND("-", B51) - 1) | B51: PD-BGROUNDSVHIRED | C51: Backgrounds Completed vs people hired | D51: Program | E51: p102 | F51: =IF(E51="","",IFERROR(IF(INDEX('Dashboard Items'!$B$2:$B$495,MATCH(E51,'Dashboard Items'!$A$2:$A$495,0))="Objective","Objectives go in the next column",IF(OR(D51="",INDEX('Dashboard Items'!$B$2:$B$495,MATCH(E51,'Dashboard Items'!$A$2:$A$495,0))=D51),INDEX('Dashboard Items'!$C$2:$C$495,MATCH(E51,'Dashboard Items'!$A$2:$A$495,0)),"Level does not match ID")),"ID not found")) | H51: =IF(G51="","",IF(ISNUMBER(SEARCH(",",G51)),"Several items (the script lists them)",IFERROR(INDEX('Dashboard Items'!$B$2:$B$495,MATCH(G51,'Dashboard Items'!$A$2:$A$495,0))&": "&INDEX('Dashboard Items'!$C$2:$C$495,MATCH(G51,'Dashboard Items'!$A$2:$A$495,0)),"ID not found"))) | I51: number | J51: 2 | K51: Yes | L51: Target | M51: 0 | N51: 0 | O51: Yes | P51: Every year | Q51: Chief of Police | U51: =IF(B51="","",IF(IF(D51<>"",D51,IFERROR(INDEX('Dashboard Items'!$B$2:$B$495,MATCH(E51,'Dashboard Items'!$A$2:$A$495,0)),""))="Key Service",IF(O51="No","Key Service: shown, not counted","Counts in Key Service gauge"),IF(IF(D51<>"",D51,IFERROR(INDEX('Dashboard Items'!$B$2:$B$495,MATCH(E51,'Dashboard Items'!$A$2:$A$495,0)),""))="Program",IF(ISNUMBER(SEARCH("ks",G51)),IF(O51="No","Program, also at Key Service: not counted","Counts in Key Service gauge + sets Program chip"),IF(O51="No","Program: shown, no status chip","Sets Program status chip")),IF(IF(D51<>"",D51,IFERROR(INDEX('Dashboard Items'!$B$2:$B$495,MATCH(E51,'Dashboard Items'!$A$2:$A$495,0)),""))="Work System","Work System: shown, not counted","Check Level"))))
A52: =LEFT(B52, FIND("-", B52) - 1) | B52: PD-CALLVOLUME | C52: Call volume - officer initiated vs citizen initiated | D52: Key Service | E52: ks11 | F52: =IF(E52="","",IFERROR(IF(INDEX('Dashboard Items'!$B$2:$B$495,MATCH(E52,'Dashboard Items'!$A$2:$A$495,0))="Objective","Objectives go in the next column",IF(OR(D52="",INDEX('Dashboard Items'!$B$2:$B$495,MATCH(E52,'Dashboard Items'!$A$2:$A$495,0))=D52),INDEX('Dashboard Items'!$C$2:$C$495,MATCH(E52,'Dashboard Items'!$A$2:$A$495,0)),"Level does not match ID")),"ID not found")) | H52: =IF(G52="","",IF(ISNUMBER(SEARCH(",",G52)),"Several items (the script lists them)",IFERROR(INDEX('Dashboard Items'!$B$2:$B$495,MATCH(G52,'Dashboard Items'!$A$2:$A$495,0))&": "&INDEX('Dashboard Items'!$C$2:$C$495,MATCH(G52,'Dashboard Items'!$A$2:$A$495,0)),"ID not found"))) | I52: number | J52: 2 | K52: Yes | L52: Target | M52: 0 | N52: 0 | O52: Yes | P52: Every year | Q52: Chief of Police | U52: =IF(B52="","",IF(IF(D52<>"",D52,IFERROR(INDEX('Dashboard Items'!$B$2:$B$495,MATCH(E52,'Dashboard Items'!$A$2:$A$495,0)),""))="Key Service",IF(O52="No","Key Service: shown, not counted","Counts in Key Service gauge"),IF(IF(D52<>"",D52,IFERROR(INDEX('Dashboard Items'!$B$2:$B$495,MATCH(E52,'Dashboard Items'!$A$2:$A$495,0)),""))="Program",IF(ISNUMBER(SEARCH("ks",G52)),IF(O52="No","Program, also at Key Service: not counted","Counts in Key Service gauge + sets Program chip"),IF(O52="No","Program: shown, no status chip","Sets Program status chip")),IF(IF(D52<>"",D52,IFERROR(INDEX('Dashboard Items'!$B$2:$B$495,MATCH(E52,'Dashboard Items'!$A$2:$A$495,0)),""))="Work System","Work System: shown, not counted","Check Level"))))
A53: =LEFT(B53, FIND("-", B53) - 1) | B53: PD-CASECLOSURERATE | C53: Case Closure Rate by clearance code (cleared by arrest, inactive, etc.) - solvability percent - amount that ended in arrest vs the rest | D53: Program | E53: p102 | F53: =IF(E53="","",IFERROR(IF(INDEX('Dashboard Items'!$B$2:$B$495,MATCH(E53,'Dashboard Items'!$A$2:$A$495,0))="Objective","Objectives go in the next column",IF(OR(D53="",INDEX('Dashboard Items'!$B$2:$B$495,MATCH(E53,'Dashboard Items'!$A$2:$A$495,0))=D53),INDEX('Dashboard Items'!$C$2:$C$495,MATCH(E53,'Dashboard Items'!$A$2:$A$495,0)),"Level does not match ID")),"ID not found")) | G53: p50 | H53: =IF(G53="","",IF(ISNUMBER(SEARCH(",",G53)),"Several items (the script lists them)",IFERROR(INDEX('Dashboard Items'!$B$2:$B$495,MATCH(G53,'Dashboard Items'!$A$2:$A$495,0))&": "&INDEX('Dashboard Items'!$C$2:$C$495,MATCH(G53,'Dashboard Items'!$A$2:$A$495,0)),"ID not found"))) | I53: number | J53: 2 | K53: Yes | L53: Target | M53: 0 | N53: 0 | O53: Yes | P53: Every year | Q53: Chief of Police | U53: =IF(B53="","",IF(IF(D53<>"",D53,IFERROR(INDEX('Dashboard Items'!$B$2:$B$495,MATCH(E53,'Dashboard Items'!$A$2:$A$495,0)),""))="Key Service",IF(O53="No","Key Service: shown, not counted","Counts in Key Service gauge"),IF(IF(D53<>"",D53,IFERROR(INDEX('Dashboard Items'!$B$2:$B$495,MATCH(E53,'Dashboard Items'!$A$2:$A$495,0)),""))="Program",IF(ISNUMBER(SEARCH("ks",G53)),IF(O53="No","Program, also at Key Service: not counted","Counts in Key Service gauge + sets Program chip"),IF(O53="No","Program: shown, no status chip","Sets Program status chip")),IF(IF(D53<>"",D53,IFERROR(INDEX('Dashboard Items'!$B$2:$B$495,MATCH(E53,'Dashboard Items'!$A$2:$A$495,0)),""))="Work System","Work System: shown, not counted","Check Level"))))
A54: =LEFT(B54, FIND("-", B54) - 1) | B54: PD-CASESPROCESSED | C54: Cases/Records Processed trending (can compare to calls for service) | D54: Program | E54: p102 | F54: =IF(E54="","",IFERROR(IF(INDEX('Dashboard Items'!$B$2:$B$495,MATCH(E54,'Dashboard Items'!$A$2:$A$495,0))="Objective","Objectives go in the next column",IF(OR(D54="",INDEX('Dashboard Items'!$B$2:$B$495,MATCH(E54,'Dashboard Items'!$A$2:$A$495,0))=D54),INDEX('Dashboard Items'!$C$2:$C$495,MATCH(E54,'Dashboard Items'!$A$2:$A$495,0)),"Level does not match ID")),"ID not found")) | H54: =IF(G54="","",IF(ISNUMBER(SEARCH(",",G54)),"Several items (the script lists them)",IFERROR(INDEX('Dashboard Items'!$B$2:$B$495,MATCH(G54,'Dashboard Items'!$A$2:$A$495,0))&": "&INDEX('Dashboard Items'!$C$2:$C$495,MATCH(G54,'Dashboard Items'!$A$2:$A$495,0)),"ID not found"))) | I54: number | J54: 2 | K54: Yes | L54: Target | M54: 0 | N54: 0 | O54: Yes | P54: Every year | Q54: Chief of Police | U54: =IF(B54="","",IF(IF(D54<>"",D54,IFERROR(INDEX('Dashboard Items'!$B$2:$B$495,MATCH(E54,'Dashboard Items'!$A$2:$A$495,0)),""))="Key Service",IF(O54="No","Key Service: shown, not counted","Counts in Key Service gauge"),IF(IF(D54<>"",D54,IFERROR(INDEX('Dashboard Items'!$B$2:$B$495,MATCH(E54,'Dashboard Items'!$A$2:$A$495,0)),""))="Program",IF(ISNUMBER(SEARCH("ks",G54)),IF(O54="No","Program, also at Key Service: not counted","Counts in Key Service gauge + sets Program chip"),IF(O54="No","Program: shown, no status chip","Sets Program status chip")),IF(IF(D54<>"",D54,IFERROR(INDEX('Dashboard Items'!$B$2:$B$495,MATCH(E54,'Dashboard Items'!$A$2:$A$495,0)),""))="Work System","Work System: shown, not counted","Check Level"))))
A55: =LEFT(B55, FIND("-", B55) - 1) | B55: PD-CITATIONS | C55: Citations Issued by kind (brings down number of incidents, traffic accidents, etc.) | D55: Program | E55: p51 | F55: =IF(E55="","",IFERROR(IF(INDEX('Dashboard Items'!$B$2:$B$495,MATCH(E55,'Dashboard Items'!$A$2:$A$495,0))="Objective","Objectives go in the next column",IF(OR(D55="",INDEX('Dashboard Items'!$B$2:$B$495,MATCH(E55,'Dashboard Items'!$A$2:$A$495,0))=D55),INDEX('Dashboard Items'!$C$2:$C$495,MATCH(E55,'Dashboard Items'!$A$2:$A$495,0)),"Level does not match ID")),"ID not found")) | H55: =IF(G55="","",IF(ISNUMBER(SEARCH(",",G55)),"Several items (the script lists them)",IFERROR(INDEX('Dashboard Items'!$B$2:$B$495,MATCH(G55,'Dashboard Items'!$A$2:$A$495,0))&": "&INDEX('Dashboard Items'!$C$2:$C$495,MATCH(G55,'Dashboard Items'!$A$2:$A$495,0)),"ID not found"))) | I55: number | J55: 2 | K55: Yes | L55: Target | M55: 0 | N55: 0 | O55: Yes | P55: Every year | Q55: Chief of Police | U55: =IF(B55="","",IF(IF(D55<>"",D55,IFERROR(INDEX('Dashboard Items'!$B$2:$B$495,MATCH(E55,'Dashboard Items'!$A$2:$A$495,0)),""))="Key Service",IF(O55="No","Key Service: shown, not counted","Counts in Key Service gauge"),IF(IF(D55<>"",D55,IFERROR(INDEX('Dashboard Items'!$B$2:$B$495,MATCH(E55,'Dashboard Items'!$A$2:$A$495,0)),""))="Program",IF(ISNUMBER(SEARCH("ks",G55)),IF(O55="No","Program, also at Key Service: not counted","Counts in Key Service gauge + sets Program chip"),IF(O55="No","Program: shown, no status chip","Sets Program status chip")),IF(IF(D55<>"",D55,IFERROR(INDEX('Dashboard Items'!$B$2:$B$495,MATCH(E55,'Dashboard Items'!$A$2:$A$495,0)),""))="Work System","Work System: shown, not counted","Check Level"))))
A56: =LEFT(B56, FIND("-", B56) - 1) | B56: PD-COMPLAINTS | C56: Complaints (dog off leash in certain parks, ART, e-bikes, etc.) | D56: Program | E56: p51 | F56: =IF(E56="","",IFERROR(IF(INDEX('Dashboard Items'!$B$2:$B$495,MATCH(E56,'Dashboard Items'!$A$2:$A$495,0))="Objective","Objectives go in the next column",IF(OR(D56="",INDEX('Dashboard Items'!$B$2:$B$495,MATCH(E56,'Dashboard Items'!$A$2:$A$495,0))=D56),INDEX('Dashboard Items'!$C$2:$C$495,MATCH(E56,'Dashboard Items'!$A$2:$A$495,0)),"Level does not match ID")),"ID not found")) | H56: =IF(G56="","",IF(ISNUMBER(SEARCH(",",G56)),"Several items (the script lists them)",IFERROR(INDEX('Dashboard Items'!$B$2:$B$495,MATCH(G56,'Dashboard Items'!$A$2:$A$495,0))&": "&INDEX('Dashboard Items'!$C$2:$C$495,MATCH(G56,'Dashboard Items'!$A$2:$A$495,0)),"ID not found"))) | I56: number | J56: 2 | K56: Yes | L56: Target | M56: 0 | N56: 0 | O56: Yes | P56: Every year | Q56: Chief of Police | U56: =IF(B56="","",IF(IF(D56<>"",D56,IFERROR(INDEX('Dashboard Items'!$B$2:$B$495,MATCH(E56,'Dashboard Items'!$A$2:$A$495,0)),""))="Key Service",IF(O56="No","Key Service: shown, not counted","Counts in Key Service gauge"),IF(IF(D56<>"",D56,IFERROR(INDEX('Dashboard Items'!$B$2:$B$495,MATCH(E56,'Dashboard Items'!$A$2:$A$495,0)),""))="Program",IF(ISNUMBER(SEARCH("ks",G56)),IF(O56="No","Program, also at Key Service: not counted","Counts in Key Service gauge + sets Program chip"),IF(O56="No","Program: shown, no status chip","Sets Program status chip")),IF(IF(D56<>"",D56,IFERROR(INDEX('Dashboard Items'!$B$2:$B$495,MATCH(E56,'Dashboard Items'!$A$2:$A$495,0)),""))="Work System","Work System: shown, not counted","Check Level"))))
A57: =LEFT(B57, FIND("-", B57) - 1) | B57: PD-CORAREQEUESTS | C57: CORA Requests Processed within specified time frame - PD specific | D57: Program | E57: p102 | F57: =IF(E57="","",IFERROR(IF(INDEX('Dashboard Items'!$B$2:$B$495,MATCH(E57,'Dashboard Items'!$A$2:$A$495,0))="Objective","Objectives go in the next column",IF(OR(D57="",INDEX('Dashboard Items'!$B$2:$B$495,MATCH(E57,'Dashboard Items'!$A$2:$A$495,0))=D57),INDEX('Dashboard Items'!$C$2:$C$495,MATCH(E57,'Dashboard Items'!$A$2:$A$495,0)),"Level does not match ID")),"ID not found")) | H57: =IF(G57="","",IF(ISNUMBER(SEARCH(",",G57)),"Several items (the script lists them)",IFERROR(INDEX('Dashboard Items'!$B$2:$B$495,MATCH(G57,'Dashboard Items'!$A$2:$A$495,0))&": "&INDEX('Dashboard Items'!$C$2:$C$495,MATCH(G57,'Dashboard Items'!$A$2:$A$495,0)),"ID not found"))) | I57: number | J57: 2 | K57: Yes | L57: Target | M57: 0 | N57: 0 | O57: Yes | P57: Every year | Q57: Chief of Police | U57: =IF(B57="","",IF(IF(D57<>"",D57,IFERROR(INDEX('Dashboard Items'!$B$2:$B$495,MATCH(E57,'Dashboard Items'!$A$2:$A$495,0)),""))="Key Service",IF(O57="No","Key Service: shown, not counted","Counts in Key Service gauge"),IF(IF(D57<>"",D57,IFERROR(INDEX('Dashboard Items'!$B$2:$B$495,MATCH(E57,'Dashboard Items'!$A$2:$A$495,0)),""))="Program",IF(ISNUMBER(SEARCH("ks",G57)),IF(O57="No","Program, also at Key Service: not counted","Counts in Key Service gauge + sets Program chip"),IF(O57="No","Program: shown, no status chip","Sets Program status chip")),IF(IF(D57<>"",D57,IFERROR(INDEX('Dashboard Items'!$B$2:$B$495,MATCH(E57,'Dashboard Items'!$A$2:$A$495,0)),""))="Work System","Work System: shown, not counted","Check Level"))))
A58: =LEFT(B58, FIND("-", B58) - 1) | B58: PD-CORECASES | C58: Total cases (CORE) | D58: Program | E58: p51 | F58: =IF(E58="","",IFERROR(IF(INDEX('Dashboard Items'!$B$2:$B$495,MATCH(E58,'Dashboard Items'!$A$2:$A$495,0))="Objective","Objectives go in the next column",IF(OR(D58="",INDEX('Dashboard Items'!$B$2:$B$495,MATCH(E58,'Dashboard Items'!$A$2:$A$495,0))=D58),INDEX('Dashboard Items'!$C$2:$C$495,MATCH(E58,'Dashboard Items'!$A$2:$A$495,0)),"Level does not match ID")),"ID not found")) | H58: =IF(G58="","",IF(ISNUMBER(SEARCH(",",G58)),"Several items (the script lists them)",IFERROR(INDEX('Dashboard Items'!$B$2:$B$495,MATCH(G58,'Dashboard Items'!$A$2:$A$495,0))&": "&INDEX('Dashboard Items'!$C$2:$C$495,MATCH(G58,'Dashboard Items'!$A$2:$A$495,0)),"ID not found"))) | I58: number | J58: 2 | K58: Yes | L58: Target | M58: 0 | N58: 0 | O58: Yes | P58: Every year | Q58: Chief of Police | U58: =IF(B58="","",IF(IF(D58<>"",D58,IFERROR(INDEX('Dashboard Items'!$B$2:$B$495,MATCH(E58,'Dashboard Items'!$A$2:$A$495,0)),""))="Key Service",IF(O58="No","Key Service: shown, not counted","Counts in Key Service gauge"),IF(IF(D58<>"",D58,IFERROR(INDEX('Dashboard Items'!$B$2:$B$495,MATCH(E58,'Dashboard Items'!$A$2:$A$495,0)),""))="Program",IF(ISNUMBER(SEARCH("ks",G58)),IF(O58="No","Program, also at Key Service: not counted","Counts in Key Service gauge + sets Program chip"),IF(O58="No","Program: shown, no status chip","Sets Program status chip")),IF(IF(D58<>"",D58,IFERROR(INDEX('Dashboard Items'!$B$2:$B$495,MATCH(E58,'Dashboard Items'!$A$2:$A$495,0)),""))="Work System","Work System: shown, not counted","Check Level"))))
A59: =LEFT(B59, FIND("-", B59) - 1) | B59: PD-CRIMECLEARANCE | C59: Crime clearance rate - solvability by type. ticket, arrest, transfer out, etc. | D59: Key Service | E59: ks11 | F59: =IF(E59="","",IFERROR(IF(INDEX('Dashboard Items'!$B$2:$B$495,MATCH(E59,'Dashboard Items'!$A$2:$A$495,0))="Objective","Objectives go in the next column",IF(OR(D59="",INDEX('Dashboard Items'!$B$2:$B$495,MATCH(E59,'Dashboard Items'!$A$2:$A$495,0))=D59),INDEX('Dashboard Items'!$C$2:$C$495,MATCH(E59,'Dashboard Items'!$A$2:$A$495,0)),"Level does not match ID")),"ID not found")) | H59: =IF(G59="","",IF(ISNUMBER(SEARCH(",",G59)),"Several items (the script lists them)",IFERROR(INDEX('Dashboard Items'!$B$2:$B$495,MATCH(G59,'Dashboard Items'!$A$2:$A$495,0))&": "&INDEX('Dashboard Items'!$C$2:$C$495,MATCH(G59,'Dashboard Items'!$A$2:$A$495,0)),"ID not found"))) | I59: number | J59: 2 | K59: Yes | L59: Target | M59: 0 | N59: 0 | O59: Yes | P59: Every year | Q59: Chief of Police | U59: =IF(B59="","",IF(IF(D59<>"",D59,IFERROR(INDEX('Dashboard Items'!$B$2:$B$495,MATCH(E59,'Dashboard Items'!$A$2:$A$495,0)),""))="Key Service",IF(O59="No","Key Service: shown, not counted","Counts in Key Service gauge"),IF(IF(D59<>"",D59,IFERROR(INDEX('Dashboard Items'!$B$2:$B$495,MATCH(E59,'Dashboard Items'!$A$2:$A$495,0)),""))="Program",IF(ISNUMBER(SEARCH("ks",G59)),IF(O59="No","Program, also at Key Service: not counted","Counts in Key Service gauge + sets Program chip"),IF(O59="No","Program: shown, no status chip","Sets Program status chip")),IF(IF(D59<>"",D59,IFERROR(INDEX('Dashboard Items'!$B$2:$B$495,MATCH(E59,'Dashboard Items'!$A$2:$A$495,0)),""))="Work System","Work System: shown, not counted","Check Level"))))
A60: =LEFT(B60, FIND("-", B60) - 1) | B60: PD-DIGITALFORENSICS | C60: Digital forensics processing (internal and external) - includes devices for other agencies | D60: Program | E60: p102 | F60: =IF(E60="","",IFERROR(IF(INDEX('Dashboard Items'!$B$2:$B$495,MATCH(E60,'Dashboard Items'!$A$2:$A$495,0))="Objective","Objectives go in the next column",IF(OR(D60="",INDEX('Dashboard Items'!$B$2:$B$495,MATCH(E60,'Dashboard Items'!$A$2:$A$495,0))=D60),INDEX('Dashboard Items'!$C$2:$C$495,MATCH(E60,'Dashboard Items'!$A$2:$A$495,0)),"Level does not match ID")),"ID not found")) | G60: p50 | H60: =IF(G60="","",IF(ISNUMBER(SEARCH(",",G60)),"Several items (the script lists them)",IFERROR(INDEX('Dashboard Items'!$B$2:$B$495,MATCH(G60,'Dashboard Items'!$A$2:$A$495,0))&": "&INDEX('Dashboard Items'!$C$2:$C$495,MATCH(G60,'Dashboard Items'!$A$2:$A$495,0)),"ID not found"))) | I60: number | J60: 2 | K60: Yes | L60: Target | M60: 0 | N60: 0 | O60: Yes | P60: Every year | Q60: Chief of Police | U60: =IF(B60="","",IF(IF(D60<>"",D60,IFERROR(INDEX('Dashboard Items'!$B$2:$B$495,MATCH(E60,'Dashboard Items'!$A$2:$A$495,0)),""))="Key Service",IF(O60="No","Key Service: shown, not counted","Counts in Key Service gauge"),IF(IF(D60<>"",D60,IFERROR(INDEX('Dashboard Items'!$B$2:$B$495,MATCH(E60,'Dashboard Items'!$A$2:$A$495,0)),""))="Program",IF(ISNUMBER(SEARCH("ks",G60)),IF(O60="No","Program, also at Key Service: not counted","Counts in Key Service gauge + sets Program chip"),IF(O60="No","Program: shown, no status chip","Sets Program status chip")),IF(IF(D60<>"",D60,IFERROR(INDEX('Dashboard Items'!$B$2:$B$495,MATCH(E60,'Dashboard Items'!$A$2:$A$495,0)),""))="Work System","Work System: shown, not counted","Check Level"))))
A61: =LEFT(B61, FIND("-", B61) - 1) | B61: PD-DRONEASAFR | C61: Drone as first responder | D61: Program | E61: p104 | F61: =IF(E61="","",IFERROR(IF(INDEX('Dashboard Items'!$B$2:$B$495,MATCH(E61,'Dashboard Items'!$A$2:$A$495,0))="Objective","Objectives go in the next column",IF(OR(D61="",INDEX('Dashboard Items'!$B$2:$B$495,MATCH(E61,'Dashboard Items'!$A$2:$A$495,0))=D61),INDEX('Dashboard Items'!$C$2:$C$495,MATCH(E61,'Dashboard Items'!$A$2:$A$495,0)),"Level does not match ID")),"ID not found")) | H61: =IF(G61="","",IF(ISNUMBER(SEARCH(",",G61)),"Several items (the script lists them)",IFERROR(INDEX('Dashboard Items'!$B$2:$B$495,MATCH(G61,'Dashboard Items'!$A$2:$A$495,0))&": "&INDEX('Dashboard Items'!$C$2:$C$495,MATCH(G61,'Dashboard Items'!$A$2:$A$495,0)),"ID not found"))) | I61: number | J61: 2 | K61: Yes | L61: Target | M61: 0 | N61: 0 | O61: Yes | P61: Every year | Q61: Chief of Police | U61: =IF(B61="","",IF(IF(D61<>"",D61,IFERROR(INDEX('Dashboard Items'!$B$2:$B$495,MATCH(E61,'Dashboard Items'!$A$2:$A$495,0)),""))="Key Service",IF(O61="No","Key Service: shown, not counted","Counts in Key Service gauge"),IF(IF(D61<>"",D61,IFERROR(INDEX('Dashboard Items'!$B$2:$B$495,MATCH(E61,'Dashboard Items'!$A$2:$A$495,0)),""))="Program",IF(ISNUMBER(SEARCH("ks",G61)),IF(O61="No","Program, also at Key Service: not counted","Counts in Key Service gauge + sets Program chip"),IF(O61="No","Program: shown, no status chip","Sets Program status chip")),IF(IF(D61<>"",D61,IFERROR(INDEX('Dashboard Items'!$B$2:$B$495,MATCH(E61,'Dashboard Items'!$A$2:$A$495,0)),""))="Work System","Work System: shown, not counted","Check Level"))))
A62: =LEFT(B62, FIND("-", B62) - 1) | B62: PD-DUIARRESTS | C62: DUI Arrests | D62: Program | E62: p49 | F62: =IF(E62="","",IFERROR(IF(INDEX('Dashboard Items'!$B$2:$B$495,MATCH(E62,'Dashboard Items'!$A$2:$A$495,0))="Objective","Objectives go in the next column",IF(OR(D62="",INDEX('Dashboard Items'!$B$2:$B$495,MATCH(E62,'Dashboard Items'!$A$2:$A$495,0))=D62),INDEX('Dashboard Items'!$C$2:$C$495,MATCH(E62,'Dashboard Items'!$A$2:$A$495,0)),"Level does not match ID")),"ID not found")) | H62: =IF(G62="","",IF(ISNUMBER(SEARCH(",",G62)),"Several items (the script lists them)",IFERROR(INDEX('Dashboard Items'!$B$2:$B$495,MATCH(G62,'Dashboard Items'!$A$2:$A$495,0))&": "&INDEX('Dashboard Items'!$C$2:$C$495,MATCH(G62,'Dashboard Items'!$A$2:$A$495,0)),"ID not found"))) | I62: number | J62: 2 | K62: Yes | L62: Target | M62: 0 | N62: 0 | O62: Yes | P62: Every year | Q62: Chief of Police | U62: =IF(B62="","",IF(IF(D62<>"",D62,IFERROR(INDEX('Dashboard Items'!$B$2:$B$495,MATCH(E62,'Dashboard Items'!$A$2:$A$495,0)),""))="Key Service",IF(O62="No","Key Service: shown, not counted","Counts in Key Service gauge"),IF(IF(D62<>"",D62,IFERROR(INDEX('Dashboard Items'!$B$2:$B$495,MATCH(E62,'Dashboard Items'!$A$2:$A$495,0)),""))="Program",IF(ISNUMBER(SEARCH("ks",G62)),IF(O62="No","Program, also at Key Service: not counted","Counts in Key Service gauge + sets Program chip"),IF(O62="No","Program: shown, no status chip","Sets Program status chip")),IF(IF(D62<>"",D62,IFERROR(INDEX('Dashboard Items'!$B$2:$B$495,MATCH(E62,'Dashboard Items'!$A$2:$A$495,0)),""))="Work System","Work System: shown, not counted","Check Level"))))
A63: =LEFT(B63, FIND("-", B63) - 1) | B63: PD-EVIDENCEFORDA | C63: Evidence Processed vs Discovery for DA (ratio) | D63: Program | E63: p102 | F63: =IF(E63="","",IFERROR(IF(INDEX('Dashboard Items'!$B$2:$B$495,MATCH(E63,'Dashboard Items'!$A$2:$A$495,0))="Objective","Objectives go in the next column",IF(OR(D63="",INDEX('Dashboard Items'!$B$2:$B$495,MATCH(E63,'Dashboard Items'!$A$2:$A$495,0))=D63),INDEX('Dashboard Items'!$C$2:$C$495,MATCH(E63,'Dashboard Items'!$A$2:$A$495,0)),"Level does not match ID")),"ID not found")) | H63: =IF(G63="","",IF(ISNUMBER(SEARCH(",",G63)),"Several items (the script lists them)",IFERROR(INDEX('Dashboard Items'!$B$2:$B$495,MATCH(G63,'Dashboard Items'!$A$2:$A$495,0))&": "&INDEX('Dashboard Items'!$C$2:$C$495,MATCH(G63,'Dashboard Items'!$A$2:$A$495,0)),"ID not found"))) | I63: number | J63: 2 | K63: Yes | L63: Target | M63: 0 | N63: 0 | O63: Yes | P63: Every year | Q63: Chief of Police | U63: =IF(B63="","",IF(IF(D63<>"",D63,IFERROR(INDEX('Dashboard Items'!$B$2:$B$495,MATCH(E63,'Dashboard Items'!$A$2:$A$495,0)),""))="Key Service",IF(O63="No","Key Service: shown, not counted","Counts in Key Service gauge"),IF(IF(D63<>"",D63,IFERROR(INDEX('Dashboard Items'!$B$2:$B$495,MATCH(E63,'Dashboard Items'!$A$2:$A$495,0)),""))="Program",IF(ISNUMBER(SEARCH("ks",G63)),IF(O63="No","Program, also at Key Service: not counted","Counts in Key Service gauge + sets Program chip"),IF(O63="No","Program: shown, no status chip","Sets Program status chip")),IF(IF(D63<>"",D63,IFERROR(INDEX('Dashboard Items'!$B$2:$B$495,MATCH(E63,'Dashboard Items'!$A$2:$A$495,0)),""))="Work System","Work System: shown, not counted","Check Level"))))
A64: =LEFT(B64, FIND("-", B64) - 1) | B64: PD-FATALCRASH | C64: Fatal crash trend | D64: Key Service | E64: ks11 | F64: =IF(E64="","",IFERROR(IF(INDEX('Dashboard Items'!$B$2:$B$495,MATCH(E64,'Dashboard Items'!$A$2:$A$495,0))="Objective","Objectives go in the next column",IF(OR(D64="",INDEX('Dashboard Items'!$B$2:$B$495,MATCH(E64,'Dashboard Items'!$A$2:$A$495,0))=D64),INDEX('Dashboard Items'!$C$2:$C$495,MATCH(E64,'Dashboard Items'!$A$2:$A$495,0)),"Level does not match ID")),"ID not found")) | H64: =IF(G64="","",IF(ISNUMBER(SEARCH(",",G64)),"Several items (the script lists them)",IFERROR(INDEX('Dashboard Items'!$B$2:$B$495,MATCH(G64,'Dashboard Items'!$A$2:$A$495,0))&": "&INDEX('Dashboard Items'!$C$2:$C$495,MATCH(G64,'Dashboard Items'!$A$2:$A$495,0)),"ID not found"))) | I64: number | J64: 2 | K64: Yes | L64: Target | M64: 0 | N64: 0 | O64: Yes | P64: Every year | Q64: Chief of Police | U64: =IF(B64="","",IF(IF(D64<>"",D64,IFERROR(INDEX('Dashboard Items'!$B$2:$B$495,MATCH(E64,'Dashboard Items'!$A$2:$A$495,0)),""))="Key Service",IF(O64="No","Key Service: shown, not counted","Counts in Key Service gauge"),IF(IF(D64<>"",D64,IFERROR(INDEX('Dashboard Items'!$B$2:$B$495,MATCH(E64,'Dashboard Items'!$A$2:$A$495,0)),""))="Program",IF(ISNUMBER(SEARCH("ks",G64)),IF(O64="No","Program, also at Key Service: not counted","Counts in Key Service gauge + sets Program chip"),IF(O64="No","Program: shown, no status chip","Sets Program status chip")),IF(IF(D64<>"",D64,IFERROR(INDEX('Dashboard Items'!$B$2:$B$495,MATCH(E64,'Dashboard Items'!$A$2:$A$495,0)),""))="Work System","Work System: shown, not counted","Check Level"))))
A65: =LEFT(B65, FIND("-", B65) - 1) | B65: PD-FELONYREVIEWS | C65: In custody felony reviews - increase in felony arrests by patrol | D65: Program | E65: p102 | F65: =IF(E65="","",IFERROR(IF(INDEX('Dashboard Items'!$B$2:$B$495,MATCH(E65,'Dashboard Items'!$A$2:$A$495,0))="Objective","Objectives go in the next column",IF(OR(D65="",INDEX('Dashboard Items'!$B$2:$B$495,MATCH(E65,'Dashboard Items'!$A$2:$A$495,0))=D65),INDEX('Dashboard Items'!$C$2:$C$495,MATCH(E65,'Dashboard Items'!$A$2:$A$495,0)),"Level does not match ID")),"ID not found")) | G65: p50 | H65: =IF(G65="","",IF(ISNUMBER(SEARCH(",",G65)),"Several items (the script lists them)",IFERROR(INDEX('Dashboard Items'!$B$2:$B$495,MATCH(G65,'Dashboard Items'!$A$2:$A$495,0))&": "&INDEX('Dashboard Items'!$C$2:$C$495,MATCH(G65,'Dashboard Items'!$A$2:$A$495,0)),"ID not found"))) | I65: number | J65: 2 | K65: Yes | L65: Target | M65: 0 | N65: 0 | O65: Yes | P65: Every year | Q65: Chief of Police | U65: =IF(B65="","",IF(IF(D65<>"",D65,IFERROR(INDEX('Dashboard Items'!$B$2:$B$495,MATCH(E65,'Dashboard Items'!$A$2:$A$495,0)),""))="Key Service",IF(O65="No","Key Service: shown, not counted","Counts in Key Service gauge"),IF(IF(D65<>"",D65,IFERROR(INDEX('Dashboard Items'!$B$2:$B$495,MATCH(E65,'Dashboard Items'!$A$2:$A$495,0)),""))="Program",IF(ISNUMBER(SEARCH("ks",G65)),IF(O65="No","Program, also at Key Service: not counted","Counts in Key Service gauge + sets Program chip"),IF(O65="No","Program: shown, no status chip","Sets Program status chip")),IF(IF(D65<>"",D65,IFERROR(INDEX('Dashboard Items'!$B$2:$B$495,MATCH(E65,'Dashboard Items'!$A$2:$A$495,0)),""))="Work System","Work System: shown, not counted","Check Level"))))
A66: =LEFT(B66, FIND("-", B66) - 1) | B66: PD-INCIDENTS | C66: Total incidents - officer initiatied/proactivity vs dispatch call for service by incident type? - outcome would be more proactivity. | D66: Program | E66: p49 | F66: =IF(E66="","",IFERROR(IF(INDEX('Dashboard Items'!$B$2:$B$495,MATCH(E66,'Dashboard Items'!$A$2:$A$495,0))="Objective","Objectives go in the next column",IF(OR(D66="",INDEX('Dashboard Items'!$B$2:$B$495,MATCH(E66,'Dashboard Items'!$A$2:$A$495,0))=D66),INDEX('Dashboard Items'!$C$2:$C$495,MATCH(E66,'Dashboard Items'!$A$2:$A$495,0)),"Level does not match ID")),"ID not found")) | H66: =IF(G66="","",IF(ISNUMBER(SEARCH(",",G66)),"Several items (the script lists them)",IFERROR(INDEX('Dashboard Items'!$B$2:$B$495,MATCH(G66,'Dashboard Items'!$A$2:$A$495,0))&": "&INDEX('Dashboard Items'!$C$2:$C$495,MATCH(G66,'Dashboard Items'!$A$2:$A$495,0)),"ID not found"))) | I66: number | J66: 2 | K66: Yes | L66: Target | M66: 0 | N66: 0 | O66: Yes | P66: Every year | Q66: Chief of Police | U66: =IF(B66="","",IF(IF(D66<>"",D66,IFERROR(INDEX('Dashboard Items'!$B$2:$B$495,MATCH(E66,'Dashboard Items'!$A$2:$A$495,0)),""))="Key Service",IF(O66="No","Key Service: shown, not counted","Counts in Key Service gauge"),IF(IF(D66<>"",D66,IFERROR(INDEX('Dashboard Items'!$B$2:$B$495,MATCH(E66,'Dashboard Items'!$A$2:$A$495,0)),""))="Program",IF(ISNUMBER(SEARCH("ks",G66)),IF(O66="No","Program, also at Key Service: not counted","Counts in Key Service gauge + sets Program chip"),IF(O66="No","Program: shown, no status chip","Sets Program status chip")),IF(IF(D66<>"",D66,IFERROR(INDEX('Dashboard Items'!$B$2:$B$495,MATCH(E66,'Dashboard Items'!$A$2:$A$495,0)),""))="Work System","Work System: shown, not counted","Check Level"))))
A67: =LEFT(B67, FIND("-", B67) - 1) | B67: PD-OFFICERINITIATED | C67: Officer initiated activity | D67: Program | E67: p49 | F67: =IF(E67="","",IFERROR(IF(INDEX('Dashboard Items'!$B$2:$B$495,MATCH(E67,'Dashboard Items'!$A$2:$A$495,0))="Objective","Objectives go in the next column",IF(OR(D67="",INDEX('Dashboard Items'!$B$2:$B$495,MATCH(E67,'Dashboard Items'!$A$2:$A$495,0))=D67),INDEX('Dashboard Items'!$C$2:$C$495,MATCH(E67,'Dashboard Items'!$A$2:$A$495,0)),"Level does not match ID")),"ID not found")) | H67: =IF(G67="","",IF(ISNUMBER(SEARCH(",",G67)),"Several items (the script lists them)",IFERROR(INDEX('Dashboard Items'!$B$2:$B$495,MATCH(G67,'Dashboard Items'!$A$2:$A$495,0))&": "&INDEX('Dashboard Items'!$C$2:$C$495,MATCH(G67,'Dashboard Items'!$A$2:$A$495,0)),"ID not found"))) | I67: number | J67: 2 | K67: Yes | L67: Target | M67: 0 | N67: 0 | O67: Yes | P67: Every year | Q67: Chief of Police | U67: =IF(B67="","",IF(IF(D67<>"",D67,IFERROR(INDEX('Dashboard Items'!$B$2:$B$495,MATCH(E67,'Dashboard Items'!$A$2:$A$495,0)),""))="Key Service",IF(O67="No","Key Service: shown, not counted","Counts in Key Service gauge"),IF(IF(D67<>"",D67,IFERROR(INDEX('Dashboard Items'!$B$2:$B$495,MATCH(E67,'Dashboard Items'!$A$2:$A$495,0)),""))="Program",IF(ISNUMBER(SEARCH("ks",G67)),IF(O67="No","Program, also at Key Service: not counted","Counts in Key Service gauge + sets Program chip"),IF(O67="No","Program: shown, no status chip","Sets Program status chip")),IF(IF(D67<>"",D67,IFERROR(INDEX('Dashboard Items'!$B$2:$B$495,MATCH(E67,'Dashboard Items'!$A$2:$A$495,0)),""))="Work System","Work System: shown, not counted","Check Level"))))
A68: =LEFT(B68, FIND("-", B68) - 1) | B68: PD-PROACTIVETIME | C68: Proactive vs reactive time | D68: Program | E68: p49 | F68: =IF(E68="","",IFERROR(IF(INDEX('Dashboard Items'!$B$2:$B$495,MATCH(E68,'Dashboard Items'!$A$2:$A$495,0))="Objective","Objectives go in the next column",IF(OR(D68="",INDEX('Dashboard Items'!$B$2:$B$495,MATCH(E68,'Dashboard Items'!$A$2:$A$495,0))=D68),INDEX('Dashboard Items'!$C$2:$C$495,MATCH(E68,'Dashboard Items'!$A$2:$A$495,0)),"Level does not match ID")),"ID not found")) | H68: =IF(G68="","",IF(ISNUMBER(SEARCH(",",G68)),"Several items (the script lists them)",IFERROR(INDEX('Dashboard Items'!$B$2:$B$495,MATCH(G68,'Dashboard Items'!$A$2:$A$495,0))&": "&INDEX('Dashboard Items'!$C$2:$C$495,MATCH(G68,'Dashboard Items'!$A$2:$A$495,0)),"ID not found"))) | I68: number | J68: 2 | K68: Yes | L68: Target | M68: 0 | N68: 0 | O68: Yes | P68: Every year | Q68: Chief of Police | U68: =IF(B68="","",IF(IF(D68<>"",D68,IFERROR(INDEX('Dashboard Items'!$B$2:$B$495,MATCH(E68,'Dashboard Items'!$A$2:$A$495,0)),""))="Key Service",IF(O68="No","Key Service: shown, not counted","Counts in Key Service gauge"),IF(IF(D68<>"",D68,IFERROR(INDEX('Dashboard Items'!$B$2:$B$495,MATCH(E68,'Dashboard Items'!$A$2:$A$495,0)),""))="Program",IF(ISNUMBER(SEARCH("ks",G68)),IF(O68="No","Program, also at Key Service: not counted","Counts in Key Service gauge + sets Program chip"),IF(O68="No","Program: shown, no status chip","Sets Program status chip")),IF(IF(D68<>"",D68,IFERROR(INDEX('Dashboard Items'!$B$2:$B$495,MATCH(E68,'Dashboard Items'!$A$2:$A$495,0)),""))="Work System","Work System: shown, not counted","Check Level"))))
A69: =LEFT(B69, FIND("-", B69) - 1) | B69: PD-PROPERTYRECTIME | C69: Total Hours each property/records employee was spending per officer | D69: Program | E69: p102 | F69: =IF(E69="","",IFERROR(IF(INDEX('Dashboard Items'!$B$2:$B$495,MATCH(E69,'Dashboard Items'!$A$2:$A$495,0))="Objective","Objectives go in the next column",IF(OR(D69="",INDEX('Dashboard Items'!$B$2:$B$495,MATCH(E69,'Dashboard Items'!$A$2:$A$495,0))=D69),INDEX('Dashboard Items'!$C$2:$C$495,MATCH(E69,'Dashboard Items'!$A$2:$A$495,0)),"Level does not match ID")),"ID not found")) | H69: =IF(G69="","",IF(ISNUMBER(SEARCH(",",G69)),"Several items (the script lists them)",IFERROR(INDEX('Dashboard Items'!$B$2:$B$495,MATCH(G69,'Dashboard Items'!$A$2:$A$495,0))&": "&INDEX('Dashboard Items'!$C$2:$C$495,MATCH(G69,'Dashboard Items'!$A$2:$A$495,0)),"ID not found"))) | I69: number | J69: 2 | K69: Yes | L69: Target | M69: 0 | N69: 0 | O69: Yes | P69: Every year | Q69: Chief of Police | U69: =IF(B69="","",IF(IF(D69<>"",D69,IFERROR(INDEX('Dashboard Items'!$B$2:$B$495,MATCH(E69,'Dashboard Items'!$A$2:$A$495,0)),""))="Key Service",IF(O69="No","Key Service: shown, not counted","Counts in Key Service gauge"),IF(IF(D69<>"",D69,IFERROR(INDEX('Dashboard Items'!$B$2:$B$495,MATCH(E69,'Dashboard Items'!$A$2:$A$495,0)),""))="Program",IF(ISNUMBER(SEARCH("ks",G69)),IF(O69="No","Program, also at Key Service: not counted","Counts in Key Service gauge + sets Program chip"),IF(O69="No","Program: shown, no status chip","Sets Program status chip")),IF(IF(D69<>"",D69,IFERROR(INDEX('Dashboard Items'!$B$2:$B$495,MATCH(E69,'Dashboard Items'!$A$2:$A$495,0)),""))="Work System","Work System: shown, not counted","Check Level"))))
A70: =LEFT(B70, FIND("-", B70) - 1) | B70: PD-RESPONSETIME | C70: Response time - segmented into 911 and non emergent response | D70: Key Service | E70: ks11 | F70: =IF(E70="","",IFERROR(IF(INDEX('Dashboard Items'!$B$2:$B$495,MATCH(E70,'Dashboard Items'!$A$2:$A$495,0))="Objective","Objectives go in the next column",IF(OR(D70="",INDEX('Dashboard Items'!$B$2:$B$495,MATCH(E70,'Dashboard Items'!$A$2:$A$495,0))=D70),INDEX('Dashboard Items'!$C$2:$C$495,MATCH(E70,'Dashboard Items'!$A$2:$A$495,0)),"Level does not match ID")),"ID not found")) | G70: p49,p104 | H70: =IF(G70="","",IF(ISNUMBER(SEARCH(",",G70)),"Several items (the script lists them)",IFERROR(INDEX('Dashboard Items'!$B$2:$B$495,MATCH(G70,'Dashboard Items'!$A$2:$A$495,0))&": "&INDEX('Dashboard Items'!$C$2:$C$495,MATCH(G70,'Dashboard Items'!$A$2:$A$495,0)),"ID not found"))) | I70: number | J70: 2 | K70: Yes | L70: Target | M70: 0 | N70: 0 | O70: Yes | P70: Every year | Q70: Chief of Police | U70: =IF(B70="","",IF(IF(D70<>"",D70,IFERROR(INDEX('Dashboard Items'!$B$2:$B$495,MATCH(E70,'Dashboard Items'!$A$2:$A$495,0)),""))="Key Service",IF(O70="No","Key Service: shown, not counted","Counts in Key Service gauge"),IF(IF(D70<>"",D70,IFERROR(INDEX('Dashboard Items'!$B$2:$B$495,MATCH(E70,'Dashboard Items'!$A$2:$A$495,0)),""))="Program",IF(ISNUMBER(SEARCH("ks",G70)),IF(O70="No","Program, also at Key Service: not counted","Counts in Key Service gauge + sets Program chip"),IF(O70="No","Program: shown, no status chip","Sets Program status chip")),IF(IF(D70<>"",D70,IFERROR(INDEX('Dashboard Items'!$B$2:$B$495,MATCH(E70,'Dashboard Items'!$A$2:$A$495,0)),""))="Work System","Work System: shown, not counted","Check Level"))))
A71: =LEFT(B71, FIND("-", B71) - 1) | B71: PD-SAFETOTELL | C71: Time to view case for Safe to Tell (could segment by type or solvability) - criminal vs school administrative issue | D71: Program | E71: p51 | F71: =IF(E71="","",IFERROR(IF(INDEX('Dashboard Items'!$B$2:$B$495,MATCH(E71,'Dashboard Items'!$A$2:$A$495,0))="Objective","Objectives go in the next column",IF(OR(D71="",INDEX('Dashboard Items'!$B$2:$B$495,MATCH(E71,'Dashboard Items'!$A$2:$A$495,0))=D71),INDEX('Dashboard Items'!$C$2:$C$495,MATCH(E71,'Dashboard Items'!$A$2:$A$495,0)),"Level does not match ID")),"ID not found")) | H71: =IF(G71="","",IF(ISNUMBER(SEARCH(",",G71)),"Several items (the script lists them)",IFERROR(INDEX('Dashboard Items'!$B$2:$B$495,MATCH(G71,'Dashboard Items'!$A$2:$A$495,0))&": "&INDEX('Dashboard Items'!$C$2:$C$495,MATCH(G71,'Dashboard Items'!$A$2:$A$495,0)),"ID not found"))) | I71: number | J71: 2 | K71: Yes | L71: Target | M71: 0 | N71: 0 | O71: Yes | P71: Every year | Q71: Chief of Police | U71: =IF(B71="","",IF(IF(D71<>"",D71,IFERROR(INDEX('Dashboard Items'!$B$2:$B$495,MATCH(E71,'Dashboard Items'!$A$2:$A$495,0)),""))="Key Service",IF(O71="No","Key Service: shown, not counted","Counts in Key Service gauge"),IF(IF(D71<>"",D71,IFERROR(INDEX('Dashboard Items'!$B$2:$B$495,MATCH(E71,'Dashboard Items'!$A$2:$A$495,0)),""))="Program",IF(ISNUMBER(SEARCH("ks",G71)),IF(O71="No","Program, also at Key Service: not counted","Counts in Key Service gauge + sets Program chip"),IF(O71="No","Program: shown, no status chip","Sets Program status chip")),IF(IF(D71<>"",D71,IFERROR(INDEX('Dashboard Items'!$B$2:$B$495,MATCH(E71,'Dashboard Items'!$A$2:$A$495,0)),""))="Work System","Work System: shown, not counted","Check Level"))))
A72: =LEFT(B72, FIND("-", B72) - 1) | B72: PD-TRAFFICINJURY | C72: Traffic injury trend | D72: Key Service | E72: ks11 | F72: =IF(E72="","",IFERROR(IF(INDEX('Dashboard Items'!$B$2:$B$495,MATCH(E72,'Dashboard Items'!$A$2:$A$495,0))="Objective","Objectives go in the next column",IF(OR(D72="",INDEX('Dashboard Items'!$B$2:$B$495,MATCH(E72,'Dashboard Items'!$A$2:$A$495,0))=D72),INDEX('Dashboard Items'!$C$2:$C$495,MATCH(E72,'Dashboard Items'!$A$2:$A$495,0)),"Level does not match ID")),"ID not found")) | H72: =IF(G72="","",IF(ISNUMBER(SEARCH(",",G72)),"Several items (the script lists them)",IFERROR(INDEX('Dashboard Items'!$B$2:$B$495,MATCH(G72,'Dashboard Items'!$A$2:$A$495,0))&": "&INDEX('Dashboard Items'!$C$2:$C$495,MATCH(G72,'Dashboard Items'!$A$2:$A$495,0)),"ID not found"))) | I72: number | J72: 2 | K72: Yes | L72: Target | M72: 0 | N72: 0 | O72: Yes | P72: Every year | Q72: Chief of Police | U72: =IF(B72="","",IF(IF(D72<>"",D72,IFERROR(INDEX('Dashboard Items'!$B$2:$B$495,MATCH(E72,'Dashboard Items'!$A$2:$A$495,0)),""))="Key Service",IF(O72="No","Key Service: shown, not counted","Counts in Key Service gauge"),IF(IF(D72<>"",D72,IFERROR(INDEX('Dashboard Items'!$B$2:$B$495,MATCH(E72,'Dashboard Items'!$A$2:$A$495,0)),""))="Program",IF(ISNUMBER(SEARCH("ks",G72)),IF(O72="No","Program, also at Key Service: not counted","Counts in Key Service gauge + sets Program chip"),IF(O72="No","Program: shown, no status chip","Sets Program status chip")),IF(IF(D72<>"",D72,IFERROR(INDEX('Dashboard Items'!$B$2:$B$495,MATCH(E72,'Dashboard Items'!$A$2:$A$495,0)),""))="Work System","Work System: shown, not counted","Check Level"))))
A73: =LEFT(B73, FIND("-", B73) - 1) | B73: PD-VIOLENTPROPCRIME | C73: Violent/property crime trend | D73: Key Service | E73: ks11 | F73: =IF(E73="","",IFERROR(IF(INDEX('Dashboard Items'!$B$2:$B$495,MATCH(E73,'Dashboard Items'!$A$2:$A$495,0))="Objective","Objectives go in the next column",IF(OR(D73="",INDEX('Dashboard Items'!$B$2:$B$495,MATCH(E73,'Dashboard Items'!$A$2:$A$495,0))=D73),INDEX('Dashboard Items'!$C$2:$C$495,MATCH(E73,'Dashboard Items'!$A$2:$A$495,0)),"Level does not match ID")),"ID not found")) | H73: =IF(G73="","",IF(ISNUMBER(SEARCH(",",G73)),"Several items (the script lists them)",IFERROR(INDEX('Dashboard Items'!$B$2:$B$495,MATCH(G73,'Dashboard Items'!$A$2:$A$495,0))&": "&INDEX('Dashboard Items'!$C$2:$C$495,MATCH(G73,'Dashboard Items'!$A$2:$A$495,0)),"ID not found"))) | I73: per 1,000 residents | J73: 0 | K73: No | L73: Target | M73: 0 | N73: 0 | O73: Yes | P73: Every year | Q73: Chief of Police | S73: Part 1 crimes (violent and property crimes) in Durango per 1,000 residents each fiscal year. | T73: Target: at least 10% below the Colorado average. Benchmark: Colorado's Part 1 crime rate, 36.4 per 1,000. Rates use Durango's resident population of about 19,000; they do not include the more than 30,000 tourists, workers and other visitors in Durango each day. | U73: =IF(B73="","",IF(IF(D73<>"",D73,IFERROR(INDEX('Dashboard Items'!$B$2:$B$495,MATCH(E73,'Dashboard Items'!$A$2:$A$495,0)),""))="Key Service",IF(O73="No","Key Service: shown, not counted","Counts in Key Service gauge"),IF(IF(D73<>"",D73,IFERROR(INDEX('Dashboard Items'!$B$2:$B$495,MATCH(E73,'Dashboard Items'!$A$2:$A$495,0)),""))="Program",IF(ISNUMBER(SEARCH("ks",G73)),IF(O73="No","Program, also at Key Service: not counted","Counts in Key Service gauge + sets Program chip"),IF(O73="No","Program: shown, no status chip","Sets Program status chip")),IF(IF(D73<>"",D73,IFERROR(INDEX('Dashboard Items'!$B$2:$B$495,MATCH(E73,'Dashboard Items'!$A$2:$A$495,0)),""))="Work System","Work System: shown, not counted","Check Level"))))
A74: =LEFT(B74, FIND("-", B74) - 1) | B74: PD-WILDLIFETRENDS | C74: Wildlife trends by type | D74: Program | E74: p51 | F74: =IF(E74="","",IFERROR(IF(INDEX('Dashboard Items'!$B$2:$B$495,MATCH(E74,'Dashboard Items'!$A$2:$A$495,0))="Objective","Objectives go in the next column",IF(OR(D74="",INDEX('Dashboard Items'!$B$2:$B$495,MATCH(E74,'Dashboard Items'!$A$2:$A$495,0))=D74),INDEX('Dashboard Items'!$C$2:$C$495,MATCH(E74,'Dashboard Items'!$A$2:$A$495,0)),"Level does not match ID")),"ID not found")) | H74: =IF(G74="","",IF(ISNUMBER(SEARCH(",",G74)),"Several items (the script lists them)",IFERROR(INDEX('Dashboard Items'!$B$2:$B$495,MATCH(G74,'Dashboard Items'!$A$2:$A$495,0))&": "&INDEX('Dashboard Items'!$C$2:$C$495,MATCH(G74,'Dashboard Items'!$A$2:$A$495,0)),"ID not found"))) | I74: number | J74: 2 | K74: Yes | L74: Target | M74: 0 | N74: 0 | O74: Yes | P74: Every year | Q74: Chief of Police | U74: =IF(B74="","",IF(IF(D74<>"",D74,IFERROR(INDEX('Dashboard Items'!$B$2:$B$495,MATCH(E74,'Dashboard Items'!$A$2:$A$495,0)),""))="Key Service",IF(O74="No","Key Service: shown, not counted","Counts in Key Service gauge"),IF(IF(D74<>"",D74,IFERROR(INDEX('Dashboard Items'!$B$2:$B$495,MATCH(E74,'Dashboard Items'!$A$2:$A$495,0)),""))="Program",IF(ISNUMBER(SEARCH("ks",G74)),IF(O74="No","Program, also at Key Service: not counted","Counts in Key Service gauge + sets Program chip"),IF(O74="No","Program: shown, no status chip","Sets Program status chip")),IF(IF(D74<>"",D74,IFERROR(INDEX('Dashboard Items'!$B$2:$B$495,MATCH(E74,'Dashboard Items'!$A$2:$A$495,0)),""))="Work System","Work System: shown, not counted","Check Level"))))
A75: =LEFT(B75, FIND("-", B75) - 1) | B75: PIO-AUDIENCEGROWTH | C75: Social media audience growth (FB, IG, TT) | D75: Program | E75: p12 | F75: =IF(E75="","",IFERROR(IF(INDEX('Dashboard Items'!$B$2:$B$495,MATCH(E75,'Dashboard Items'!$A$2:$A$495,0))="Objective","Objectives go in the next column",IF(OR(D75="",INDEX('Dashboard Items'!$B$2:$B$495,MATCH(E75,'Dashboard Items'!$A$2:$A$495,0))=D75),INDEX('Dashboard Items'!$C$2:$C$495,MATCH(E75,'Dashboard Items'!$A$2:$A$495,0)),"Level does not match ID")),"ID not found")) | O75: Yes | P75: Every year | U75: =IF(B75="","",IF(IF(D75<>"",D75,IFERROR(INDEX('Dashboard Items'!$B$2:$B$495,MATCH(E75,'Dashboard Items'!$A$2:$A$495,0)),""))="Key Service",IF(O75="No","Key Service: shown, not counted","Counts in Key Service gauge"),IF(IF(D75<>"",D75,IFERROR(INDEX('Dashboard Items'!$B$2:$B$495,MATCH(E75,'Dashboard Items'!$A$2:$A$495,0)),""))="Program",IF(ISNUMBER(SEARCH("ks",G75)),IF(O75="No","Program, also at Key Service: not counted","Counts in Key Service gauge + sets Program chip"),IF(O75="No","Program: shown, no status chip","Sets Program status chip")),IF(IF(D75<>"",D75,IFERROR(INDEX('Dashboard Items'!$B$2:$B$495,MATCH(E75,'Dashboard Items'!$A$2:$A$495,0)),""))="Work System","Work System: shown, not counted","Check Level"))))
A76: =LEFT(B76, FIND("-", B76) - 1) | B76: PIO-ENGRATE | C76: Social media engagement rate (FB, IG, TT) | D76: Program | E76: p12 | F76: =IF(E76="","",IFERROR(IF(INDEX('Dashboard Items'!$B$2:$B$495,MATCH(E76,'Dashboard Items'!$A$2:$A$495,0))="Objective","Objectives go in the next column",IF(OR(D76="",INDEX('Dashboard Items'!$B$2:$B$495,MATCH(E76,'Dashboard Items'!$A$2:$A$495,0))=D76),INDEX('Dashboard Items'!$C$2:$C$495,MATCH(E76,'Dashboard Items'!$A$2:$A$495,0)),"Level does not match ID")),"ID not found")) | G76: ks3 | H76: =IF(G76="","",IF(ISNUMBER(SEARCH(",",G76)),"Several items (the script lists them)",IFERROR(INDEX('Dashboard Items'!$B$2:$B$495,MATCH(G76,'Dashboard Items'!$A$2:$A$495,0))&": "&INDEX('Dashboard Items'!$C$2:$C$495,MATCH(G76,'Dashboard Items'!$A$2:$A$495,0)),"ID not found"))) | J76: 2 | K76: Yes | L76: Target | M76: 0 | N76: 0 | O76: Yes | P76: Every year | Q76: Public Information Officer | R76: Instagram, Facebook, LinkedIn, TikTok | U76: =IF(B76="","",IF(IF(D76<>"",D76,IFERROR(INDEX('Dashboard Items'!$B$2:$B$495,MATCH(E76,'Dashboard Items'!$A$2:$A$495,0)),""))="Key Service",IF(O76="No","Key Service: shown, not counted","Counts in Key Service gauge"),IF(IF(D76<>"",D76,IFERROR(INDEX('Dashboard Items'!$B$2:$B$495,MATCH(E76,'Dashboard Items'!$A$2:$A$495,0)),""))="Program",IF(ISNUMBER(SEARCH("ks",G76)),IF(O76="No","Program, also at Key Service: not counted","Counts in Key Service gauge + sets Program chip"),IF(O76="No","Program: shown, no status chip","Sets Program status chip")),IF(IF(D76<>"",D76,IFERROR(INDEX('Dashboard Items'!$B$2:$B$495,MATCH(E76,'Dashboard Items'!$A$2:$A$495,0)),""))="Work System","Work System: shown, not counted","Check Level"))))
A77: =LEFT(B77, FIND("-", B77) - 1) | B77: PIO-SEECLICKFIX | C77: SeeClickFix requests | D77: Program | E77: p11 | F77: =IF(E77="","",IFERROR(IF(INDEX('Dashboard Items'!$B$2:$B$495,MATCH(E77,'Dashboard Items'!$A$2:$A$495,0))="Objective","Objectives go in the next column",IF(OR(D77="",INDEX('Dashboard Items'!$B$2:$B$495,MATCH(E77,'Dashboard Items'!$A$2:$A$495,0))=D77),INDEX('Dashboard Items'!$C$2:$C$495,MATCH(E77,'Dashboard Items'!$A$2:$A$495,0)),"Level does not match ID")),"ID not found")) | G77: ks3 | H77: =IF(G77="","",IF(ISNUMBER(SEARCH(",",G77)),"Several items (the script lists them)",IFERROR(INDEX('Dashboard Items'!$B$2:$B$495,MATCH(G77,'Dashboard Items'!$A$2:$A$495,0))&": "&INDEX('Dashboard Items'!$C$2:$C$495,MATCH(G77,'Dashboard Items'!$A$2:$A$495,0)),"ID not found"))) | O77: Yes | P77: Every year | U77: =IF(B77="","",IF(IF(D77<>"",D77,IFERROR(INDEX('Dashboard Items'!$B$2:$B$495,MATCH(E77,'Dashboard Items'!$A$2:$A$495,0)),""))="Key Service",IF(O77="No","Key Service: shown, not counted","Counts in Key Service gauge"),IF(IF(D77<>"",D77,IFERROR(INDEX('Dashboard Items'!$B$2:$B$495,MATCH(E77,'Dashboard Items'!$A$2:$A$495,0)),""))="Program",IF(ISNUMBER(SEARCH("ks",G77)),IF(O77="No","Program, also at Key Service: not counted","Counts in Key Service gauge + sets Program chip"),IF(O77="No","Program: shown, no status chip","Sets Program status chip")),IF(IF(D77<>"",D77,IFERROR(INDEX('Dashboard Items'!$B$2:$B$495,MATCH(E77,'Dashboard Items'!$A$2:$A$495,0)),""))="Work System","Work System: shown, not counted","Check Level"))))
A78: =LEFT(B78, FIND("-", B78) - 1) | B78: PIO-VIEWERSHIP | C78: Website views + social media post link clicks + news letter open rate | D78: Program | E78: p11 | F78: =IF(E78="","",IFERROR(IF(INDEX('Dashboard Items'!$B$2:$B$495,MATCH(E78,'Dashboard Items'!$A$2:$A$495,0))="Objective","Objectives go in the next column",IF(OR(D78="",INDEX('Dashboard Items'!$B$2:$B$495,MATCH(E78,'Dashboard Items'!$A$2:$A$495,0))=D78),INDEX('Dashboard Items'!$C$2:$C$495,MATCH(E78,'Dashboard Items'!$A$2:$A$495,0)),"Level does not match ID")),"ID not found")) | G78: ks3 | H78: =IF(G78="","",IF(ISNUMBER(SEARCH(",",G78)),"Several items (the script lists them)",IFERROR(INDEX('Dashboard Items'!$B$2:$B$495,MATCH(G78,'Dashboard Items'!$A$2:$A$495,0))&": "&INDEX('Dashboard Items'!$C$2:$C$495,MATCH(G78,'Dashboard Items'!$A$2:$A$495,0)),"ID not found"))) | O78: Yes | P78: Every year | U78: =IF(B78="","",IF(IF(D78<>"",D78,IFERROR(INDEX('Dashboard Items'!$B$2:$B$495,MATCH(E78,'Dashboard Items'!$A$2:$A$495,0)),""))="Key Service",IF(O78="No","Key Service: shown, not counted","Counts in Key Service gauge"),IF(IF(D78<>"",D78,IFERROR(INDEX('Dashboard Items'!$B$2:$B$495,MATCH(E78,'Dashboard Items'!$A$2:$A$495,0)),""))="Program",IF(ISNUMBER(SEARCH("ks",G78)),IF(O78="No","Program, also at Key Service: not counted","Counts in Key Service gauge + sets Program chip"),IF(O78="No","Program: shown, no status chip","Sets Program status chip")),IF(IF(D78<>"",D78,IFERROR(INDEX('Dashboard Items'!$B$2:$B$495,MATCH(E78,'Dashboard Items'!$A$2:$A$495,0)),""))="Work System","Work System: shown, not counted","Check Level"))))
A79: =LEFT(B79, FIND("-", B79) - 1) | B79: PROS-ALLCOMMEVENTS | C79: All community events - segmented by total, produced and serviced. | D79: Key Service | E79: ks20 | F79: =IF(E79="","",IFERROR(IF(INDEX('Dashboard Items'!$B$2:$B$495,MATCH(E79,'Dashboard Items'!$A$2:$A$495,0))="Objective","Objectives go in the next column",IF(OR(D79="",INDEX('Dashboard Items'!$B$2:$B$495,MATCH(E79,'Dashboard Items'!$A$2:$A$495,0))=D79),INDEX('Dashboard Items'!$C$2:$C$495,MATCH(E79,'Dashboard Items'!$A$2:$A$495,0)),"Level does not match ID")),"ID not found")) | G79: p95 | H79: =IF(G79="","",IF(ISNUMBER(SEARCH(",",G79)),"Several items (the script lists them)",IFERROR(INDEX('Dashboard Items'!$B$2:$B$495,MATCH(G79,'Dashboard Items'!$A$2:$A$495,0))&": "&INDEX('Dashboard Items'!$C$2:$C$495,MATCH(G79,'Dashboard Items'!$A$2:$A$495,0)),"ID not found"))) | I79: number | J79: 0 | K79: Yes | L79: Target | M79: 0 | N79: 0 | O79: Yes | P79: Every year | Q79: Prosperity Officer | S79: Community events supported with City services such as production, facilities and equipment, each fiscal year. | T79: Target: 250 events, set from Customer Service portal and self-service capacity. Growth is limited by the calendar and the number of facilities available. | U79: =IF(B79="","",IF(IF(D79<>"",D79,IFERROR(INDEX('Dashboard Items'!$B$2:$B$495,MATCH(E79,'Dashboard Items'!$A$2:$A$495,0)),""))="Key Service",IF(O79="No","Key Service: shown, not counted","Counts in Key Service gauge"),IF(IF(D79<>"",D79,IFERROR(INDEX('Dashboard Items'!$B$2:$B$495,MATCH(E79,'Dashboard Items'!$A$2:$A$495,0)),""))="Program",IF(ISNUMBER(SEARCH("ks",G79)),IF(O79="No","Program, also at Key Service: not counted","Counts in Key Service gauge + sets Program chip"),IF(O79="No","Program: shown, no status chip","Sets Program status chip")),IF(IF(D79<>"",D79,IFERROR(INDEX('Dashboard Items'!$B$2:$B$495,MATCH(E79,'Dashboard Items'!$A$2:$A$495,0)),""))="Work System","Work System: shown, not counted","Check Level"))))
A80: =LEFT(B80, FIND("-", B80) - 1) | B80: PROS-COMMSURVEY | C80: Comm survey- have you attended an event? | D80: Program | E80: p95 | F80: =IF(E80="","",IFERROR(IF(INDEX('Dashboard Items'!$B$2:$B$495,MATCH(E80,'Dashboard Items'!$A$2:$A$495,0))="Objective","Objectives go in the next column",IF(OR(D80="",INDEX('Dashboard Items'!$B$2:$B$495,MATCH(E80,'Dashboard Items'!$A$2:$A$495,0))=D80),INDEX('Dashboard Items'!$C$2:$C$495,MATCH(E80,'Dashboard Items'!$A$2:$A$495,0)),"Level does not match ID")),"ID not found")) | H80: =IF(G80="","",IF(ISNUMBER(SEARCH(",",G80)),"Several items (the script lists them)",IFERROR(INDEX('Dashboard Items'!$B$2:$B$495,MATCH(G80,'Dashboard Items'!$A$2:$A$495,0))&": "&INDEX('Dashboard Items'!$C$2:$C$495,MATCH(G80,'Dashboard Items'!$A$2:$A$495,0)),"ID not found"))) | I80: number | J80: 2 | K80: Yes | L80: Target | M80: 0 | N80: 0 | O80: Yes | P80: Every year | Q80: Prosperity Officer | U80: =IF(B80="","",IF(IF(D80<>"",D80,IFERROR(INDEX('Dashboard Items'!$B$2:$B$495,MATCH(E80,'Dashboard Items'!$A$2:$A$495,0)),""))="Key Service",IF(O80="No","Key Service: shown, not counted","Counts in Key Service gauge"),IF(IF(D80<>"",D80,IFERROR(INDEX('Dashboard Items'!$B$2:$B$495,MATCH(E80,'Dashboard Items'!$A$2:$A$495,0)),""))="Program",IF(ISNUMBER(SEARCH("ks",G80)),IF(O80="No","Program, also at Key Service: not counted","Counts in Key Service gauge + sets Program chip"),IF(O80="No","Program: shown, no status chip","Sets Program status chip")),IF(IF(D80<>"",D80,IFERROR(INDEX('Dashboard Items'!$B$2:$B$495,MATCH(E80,'Dashboard Items'!$A$2:$A$495,0)),""))="Work System","Work System: shown, not counted","Check Level"))))
A81: =LEFT(B81, FIND("-", B81) - 1) | B81: PROS-GRANTAWARDED | C81: Number of grants awarded Annually | D81: Program | E81: p100 | F81: =IF(E81="","",IFERROR(IF(INDEX('Dashboard Items'!$B$2:$B$495,MATCH(E81,'Dashboard Items'!$A$2:$A$495,0))="Objective","Objectives go in the next column",IF(OR(D81="",INDEX('Dashboard Items'!$B$2:$B$495,MATCH(E81,'Dashboard Items'!$A$2:$A$495,0))=D81),INDEX('Dashboard Items'!$C$2:$C$495,MATCH(E81,'Dashboard Items'!$A$2:$A$495,0)),"Level does not match ID")),"ID not found")) | H81: =IF(G81="","",IF(ISNUMBER(SEARCH(",",G81)),"Several items (the script lists them)",IFERROR(INDEX('Dashboard Items'!$B$2:$B$495,MATCH(G81,'Dashboard Items'!$A$2:$A$495,0))&": "&INDEX('Dashboard Items'!$C$2:$C$495,MATCH(G81,'Dashboard Items'!$A$2:$A$495,0)),"ID not found"))) | I81: number | J81: 2 | K81: Yes | L81: Target | M81: 0 | N81: 0 | O81: Yes | P81: Every year | Q81: Prosperity Officer | U81: =IF(B81="","",IF(IF(D81<>"",D81,IFERROR(INDEX('Dashboard Items'!$B$2:$B$495,MATCH(E81,'Dashboard Items'!$A$2:$A$495,0)),""))="Key Service",IF(O81="No","Key Service: shown, not counted","Counts in Key Service gauge"),IF(IF(D81<>"",D81,IFERROR(INDEX('Dashboard Items'!$B$2:$B$495,MATCH(E81,'Dashboard Items'!$A$2:$A$495,0)),""))="Program",IF(ISNUMBER(SEARCH("ks",G81)),IF(O81="No","Program, also at Key Service: not counted","Counts in Key Service gauge + sets Program chip"),IF(O81="No","Program: shown, no status chip","Sets Program status chip")),IF(IF(D81<>"",D81,IFERROR(INDEX('Dashboard Items'!$B$2:$B$495,MATCH(E81,'Dashboard Items'!$A$2:$A$495,0)),""))="Work System","Work System: shown, not counted","Check Level"))))
A82: =LEFT(B82, FIND("-", B82) - 1) | B82: PROS-LOCALSPEND | C82: Local Spend from grants awarded Annually | D82: Program | E82: p100 | F82: =IF(E82="","",IFERROR(IF(INDEX('Dashboard Items'!$B$2:$B$495,MATCH(E82,'Dashboard Items'!$A$2:$A$495,0))="Objective","Objectives go in the next column",IF(OR(D82="",INDEX('Dashboard Items'!$B$2:$B$495,MATCH(E82,'Dashboard Items'!$A$2:$A$495,0))=D82),INDEX('Dashboard Items'!$C$2:$C$495,MATCH(E82,'Dashboard Items'!$A$2:$A$495,0)),"Level does not match ID")),"ID not found")) | H82: =IF(G82="","",IF(ISNUMBER(SEARCH(",",G82)),"Several items (the script lists them)",IFERROR(INDEX('Dashboard Items'!$B$2:$B$495,MATCH(G82,'Dashboard Items'!$A$2:$A$495,0))&": "&INDEX('Dashboard Items'!$C$2:$C$495,MATCH(G82,'Dashboard Items'!$A$2:$A$495,0)),"ID not found"))) | I82: currency | J82: 0 | K82: Yes | L82: Target | M82: 0 | N82: 0 | O82: Yes | P82: Every year | Q82: Prosperity Officer | R82: Submittable grant reimbursement forms (local spend reported), with some manual adjustments | S82: Money spent locally by grant recipients, as reported on their reimbursement forms, for Lodgers' Tax Arts and Culture, Local Event Marketing, Re:New and Durango Creates! grants. Counted by the year of the grant round. | U82: =IF(B82="","",IF(IF(D82<>"",D82,IFERROR(INDEX('Dashboard Items'!$B$2:$B$495,MATCH(E82,'Dashboard Items'!$A$2:$A$495,0)),""))="Key Service",IF(O82="No","Key Service: shown, not counted","Counts in Key Service gauge"),IF(IF(D82<>"",D82,IFERROR(INDEX('Dashboard Items'!$B$2:$B$495,MATCH(E82,'Dashboard Items'!$A$2:$A$495,0)),""))="Program",IF(ISNUMBER(SEARCH("ks",G82)),IF(O82="No","Program, also at Key Service: not counted","Counts in Key Service gauge + sets Program chip"),IF(O82="No","Program: shown, no status chip","Sets Program status chip")),IF(IF(D82<>"",D82,IFERROR(INDEX('Dashboard Items'!$B$2:$B$495,MATCH(E82,'Dashboard Items'!$A$2:$A$495,0)),""))="Work System","Work System: shown, not counted","Check Level"))))
A83: =LEFT(B83, FIND("-", B83) - 1) | B83: PROS-NIGHTONTOUR | C83: Total Nights on Tour Sales (annual) | D83: Program | E83: p40 | F83: =IF(E83="","",IFERROR(IF(INDEX('Dashboard Items'!$B$2:$B$495,MATCH(E83,'Dashboard Items'!$A$2:$A$495,0))="Objective","Objectives go in the next column",IF(OR(D83="",INDEX('Dashboard Items'!$B$2:$B$495,MATCH(E83,'Dashboard Items'!$A$2:$A$495,0))=D83),INDEX('Dashboard Items'!$C$2:$C$495,MATCH(E83,'Dashboard Items'!$A$2:$A$495,0)),"Level does not match ID")),"ID not found")) | G83: p43 | H83: =IF(G83="","",IF(ISNUMBER(SEARCH(",",G83)),"Several items (the script lists them)",IFERROR(INDEX('Dashboard Items'!$B$2:$B$495,MATCH(G83,'Dashboard Items'!$A$2:$A$495,0))&": "&INDEX('Dashboard Items'!$C$2:$C$495,MATCH(G83,'Dashboard Items'!$A$2:$A$495,0)),"ID not found"))) | I83: number | J83: 0 | K83: Yes | L83: Target | M83: 0 | N83: 0 | O83: Yes | P83: Every year | Q83: Prosperity Officer | S83: Room nights sold during the year to new tour companies, meeting planners and FIT (independent traveler) contracts, including nights booked now for stays in later years. | T83: Counts new organizations only. Ongoing accounts are not included; for example, the two Tauck Tours series sold in 2024 bring about 400 room nights a year but are not in the 2026 count. | U83: =IF(B83="","",IF(IF(D83<>"",D83,IFERROR(INDEX('Dashboard Items'!$B$2:$B$495,MATCH(E83,'Dashboard Items'!$A$2:$A$495,0)),""))="Key Service",IF(O83="No","Key Service: shown, not counted","Counts in Key Service gauge"),IF(IF(D83<>"",D83,IFERROR(INDEX('Dashboard Items'!$B$2:$B$495,MATCH(E83,'Dashboard Items'!$A$2:$A$495,0)),""))="Program",IF(ISNUMBER(SEARCH("ks",G83)),IF(O83="No","Program, also at Key Service: not counted","Counts in Key Service gauge + sets Program chip"),IF(O83="No","Program: shown, no status chip","Sets Program status chip")),IF(IF(D83<>"",D83,IFERROR(INDEX('Dashboard Items'!$B$2:$B$495,MATCH(E83,'Dashboard Items'!$A$2:$A$495,0)),""))="Work System","Work System: shown, not counted","Check Level"))))
A84: =LEFT(B84, FIND("-", B84) - 1) | B84: PROS-OCCRATE | C84: Occupancy Rate (Year over Year Quarterly) | D84: Key Service | E84: ks9 | F84: =IF(E84="","",IFERROR(IF(INDEX('Dashboard Items'!$B$2:$B$495,MATCH(E84,'Dashboard Items'!$A$2:$A$495,0))="Objective","Objectives go in the next column",IF(OR(D84="",INDEX('Dashboard Items'!$B$2:$B$495,MATCH(E84,'Dashboard Items'!$A$2:$A$495,0))=D84),INDEX('Dashboard Items'!$C$2:$C$495,MATCH(E84,'Dashboard Items'!$A$2:$A$495,0)),"Level does not match ID")),"ID not found")) | G84: p100, p43 | H84: =IF(G84="","",IF(ISNUMBER(SEARCH(",",G84)),"Several items (the script lists them)",IFERROR(INDEX('Dashboard Items'!$B$2:$B$495,MATCH(G84,'Dashboard Items'!$A$2:$A$495,0))&": "&INDEX('Dashboard Items'!$C$2:$C$495,MATCH(G84,'Dashboard Items'!$A$2:$A$495,0)),"ID not found"))) | I84: percent | J84: 2 | K84: Yes | L84: Target | M84: 0 | N84: 0 | O84: Yes | P84: Every year | Q84: Prosperity Officer | U84: =IF(B84="","",IF(IF(D84<>"",D84,IFERROR(INDEX('Dashboard Items'!$B$2:$B$495,MATCH(E84,'Dashboard Items'!$A$2:$A$495,0)),""))="Key Service",IF(O84="No","Key Service: shown, not counted","Counts in Key Service gauge"),IF(IF(D84<>"",D84,IFERROR(INDEX('Dashboard Items'!$B$2:$B$495,MATCH(E84,'Dashboard Items'!$A$2:$A$495,0)),""))="Program",IF(ISNUMBER(SEARCH("ks",G84)),IF(O84="No","Program, also at Key Service: not counted","Counts in Key Service gauge + sets Program chip"),IF(O84="No","Program: shown, no status chip","Sets Program status chip")),IF(IF(D84<>"",D84,IFERROR(INDEX('Dashboard Items'!$B$2:$B$495,MATCH(E84,'Dashboard Items'!$A$2:$A$495,0)),""))="Work System","Work System: shown, not counted","Check Level"))))
A85: =LEFT(B85, FIND("-", B85) - 1) | B85: PROS-PERMITNUM | C85: Number of Permits Issued (Activity, Parks, Banners) | D85: Program | E85: p95 | F85: =IF(E85="","",IFERROR(IF(INDEX('Dashboard Items'!$B$2:$B$495,MATCH(E85,'Dashboard Items'!$A$2:$A$495,0))="Objective","Objectives go in the next column",IF(OR(D85="",INDEX('Dashboard Items'!$B$2:$B$495,MATCH(E85,'Dashboard Items'!$A$2:$A$495,0))=D85),INDEX('Dashboard Items'!$C$2:$C$495,MATCH(E85,'Dashboard Items'!$A$2:$A$495,0)),"Level does not match ID")),"ID not found")) | H85: =IF(G85="","",IF(ISNUMBER(SEARCH(",",G85)),"Several items (the script lists them)",IFERROR(INDEX('Dashboard Items'!$B$2:$B$495,MATCH(G85,'Dashboard Items'!$A$2:$A$495,0))&": "&INDEX('Dashboard Items'!$C$2:$C$495,MATCH(G85,'Dashboard Items'!$A$2:$A$495,0)),"ID not found"))) | I85: number | J85: 0 | K85: Yes | L85: Target | M85: 0 | N85: 0 | O85: Yes | P85: Every year | Q85: Prosperity Officer | S85: Community event permits issued each fiscal year. | T85: Target: 240 permits, set from Customer Service portal and self-service capacity. Growth is limited by the calendar and the number of facilities available. Counts community event permits only; activity, park and banner permits are not included yet. | U85: =IF(B85="","",IF(IF(D85<>"",D85,IFERROR(INDEX('Dashboard Items'!$B$2:$B$495,MATCH(E85,'Dashboard Items'!$A$2:$A$495,0)),""))="Key Service",IF(O85="No","Key Service: shown, not counted","Counts in Key Service gauge"),IF(IF(D85<>"",D85,IFERROR(INDEX('Dashboard Items'!$B$2:$B$495,MATCH(E85,'Dashboard Items'!$A$2:$A$495,0)),""))="Program",IF(ISNUMBER(SEARCH("ks",G85)),IF(O85="No","Program, also at Key Service: not counted","Counts in Key Service gauge + sets Program chip"),IF(O85="No","Program: shown, no status chip","Sets Program status chip")),IF(IF(D85<>"",D85,IFERROR(INDEX('Dashboard Items'!$B$2:$B$495,MATCH(E85,'Dashboard Items'!$A$2:$A$495,0)),""))="Work System","Work System: shown, not counted","Check Level"))))
A86: =LEFT(B86, FIND("-", B86) - 1) | B86: PROS-PROP123 | C86: Building Permits Issued Under Prop 123 | D86: Program | E86: p37 | F86: =IF(E86="","",IFERROR(IF(INDEX('Dashboard Items'!$B$2:$B$495,MATCH(E86,'Dashboard Items'!$A$2:$A$495,0))="Objective","Objectives go in the next column",IF(OR(D86="",INDEX('Dashboard Items'!$B$2:$B$495,MATCH(E86,'Dashboard Items'!$A$2:$A$495,0))=D86),INDEX('Dashboard Items'!$C$2:$C$495,MATCH(E86,'Dashboard Items'!$A$2:$A$495,0)),"Level does not match ID")),"ID not found")) | H86: =IF(G86="","",IF(ISNUMBER(SEARCH(",",G86)),"Several items (the script lists them)",IFERROR(INDEX('Dashboard Items'!$B$2:$B$495,MATCH(G86,'Dashboard Items'!$A$2:$A$495,0))&": "&INDEX('Dashboard Items'!$C$2:$C$495,MATCH(G86,'Dashboard Items'!$A$2:$A$495,0)),"ID not found"))) | I86: number | J86: 2 | K86: Yes | L86: Target | M86: 0 | N86: 0 | O86: Yes | P86: Every year | Q86: Prosperity Officer | T86: Benchmark is the goal of 99 by 2029 | U86: =IF(B86="","",IF(IF(D86<>"",D86,IFERROR(INDEX('Dashboard Items'!$B$2:$B$495,MATCH(E86,'Dashboard Items'!$A$2:$A$495,0)),""))="Key Service",IF(O86="No","Key Service: shown, not counted","Counts in Key Service gauge"),IF(IF(D86<>"",D86,IFERROR(INDEX('Dashboard Items'!$B$2:$B$495,MATCH(E86,'Dashboard Items'!$A$2:$A$495,0)),""))="Program",IF(ISNUMBER(SEARCH("ks",G86)),IF(O86="No","Program, also at Key Service: not counted","Counts in Key Service gauge + sets Program chip"),IF(O86="No","Program: shown, no status chip","Sets Program status chip")),IF(IF(D86<>"",D86,IFERROR(INDEX('Dashboard Items'!$B$2:$B$495,MATCH(E86,'Dashboard Items'!$A$2:$A$495,0)),""))="Work System","Work System: shown, not counted","Check Level"))))
A87: =LEFT(B87, FIND("-", B87) - 1) | B87: PROS-REGULATEDUNITS | C87: Total Regulated Affordable Housing Units | D87: Key Service | E87: ks8 | F87: =IF(E87="","",IFERROR(IF(INDEX('Dashboard Items'!$B$2:$B$495,MATCH(E87,'Dashboard Items'!$A$2:$A$495,0))="Objective","Objectives go in the next column",IF(OR(D87="",INDEX('Dashboard Items'!$B$2:$B$495,MATCH(E87,'Dashboard Items'!$A$2:$A$495,0))=D87),INDEX('Dashboard Items'!$C$2:$C$495,MATCH(E87,'Dashboard Items'!$A$2:$A$495,0)),"Level does not match ID")),"ID not found")) | G87: p37 | H87: =IF(G87="","",IF(ISNUMBER(SEARCH(",",G87)),"Several items (the script lists them)",IFERROR(INDEX('Dashboard Items'!$B$2:$B$495,MATCH(G87,'Dashboard Items'!$A$2:$A$495,0))&": "&INDEX('Dashboard Items'!$C$2:$C$495,MATCH(G87,'Dashboard Items'!$A$2:$A$495,0)),"ID not found"))) | I87: number | J87: 0 | K87: Yes | L87: Target | M87: 0 | N87: 0 | O87: Yes | P87: Every year | Q87: Prosperity Officer | T87: Counts homes with a formal affordability agreement on record with the City, by the year each property was completed. Mixed-income developments count only their income-restricted units. Another 114+ units are planned through City partnerships but not yet built. | U87: =IF(B87="","",IF(IF(D87<>"",D87,IFERROR(INDEX('Dashboard Items'!$B$2:$B$495,MATCH(E87,'Dashboard Items'!$A$2:$A$495,0)),""))="Key Service",IF(O87="No","Key Service: shown, not counted","Counts in Key Service gauge"),IF(IF(D87<>"",D87,IFERROR(INDEX('Dashboard Items'!$B$2:$B$495,MATCH(E87,'Dashboard Items'!$A$2:$A$495,0)),""))="Program",IF(ISNUMBER(SEARCH("ks",G87)),IF(O87="No","Program, also at Key Service: not counted","Counts in Key Service gauge + sets Program chip"),IF(O87="No","Program: shown, no status chip","Sets Program status chip")),IF(IF(D87<>"",D87,IFERROR(INDEX('Dashboard Items'!$B$2:$B$495,MATCH(E87,'Dashboard Items'!$A$2:$A$495,0)),""))="Work System","Work System: shown, not counted","Check Level"))))
A88: =LEFT(B88, FIND("-", B88) - 1) | B88: PROS-RESBUILPERMIT | C88: Total Residential Budilding Permits | D88: Program | E88: p37 | F88: =IF(E88="","",IFERROR(IF(INDEX('Dashboard Items'!$B$2:$B$495,MATCH(E88,'Dashboard Items'!$A$2:$A$495,0))="Objective","Objectives go in the next column",IF(OR(D88="",INDEX('Dashboard Items'!$B$2:$B$495,MATCH(E88,'Dashboard Items'!$A$2:$A$495,0))=D88),INDEX('Dashboard Items'!$C$2:$C$495,MATCH(E88,'Dashboard Items'!$A$2:$A$495,0)),"Level does not match ID")),"ID not found")) | H88: =IF(G88="","",IF(ISNUMBER(SEARCH(",",G88)),"Several items (the script lists them)",IFERROR(INDEX('Dashboard Items'!$B$2:$B$495,MATCH(G88,'Dashboard Items'!$A$2:$A$495,0))&": "&INDEX('Dashboard Items'!$C$2:$C$495,MATCH(G88,'Dashboard Items'!$A$2:$A$495,0)),"ID not found"))) | I88: number | J88: 2 | K88: Yes | L88: Target | M88: 0 | N88: 0 | O88: Yes | P88: Every year | Q88: Prosperity Officer | U88: =IF(B88="","",IF(IF(D88<>"",D88,IFERROR(INDEX('Dashboard Items'!$B$2:$B$495,MATCH(E88,'Dashboard Items'!$A$2:$A$495,0)),""))="Key Service",IF(O88="No","Key Service: shown, not counted","Counts in Key Service gauge"),IF(IF(D88<>"",D88,IFERROR(INDEX('Dashboard Items'!$B$2:$B$495,MATCH(E88,'Dashboard Items'!$A$2:$A$495,0)),""))="Program",IF(ISNUMBER(SEARCH("ks",G88)),IF(O88="No","Program, also at Key Service: not counted","Counts in Key Service gauge + sets Program chip"),IF(O88="No","Program: shown, no status chip","Sets Program status chip")),IF(IF(D88<>"",D88,IFERROR(INDEX('Dashboard Items'!$B$2:$B$495,MATCH(E88,'Dashboard Items'!$A$2:$A$495,0)),""))="Work System","Work System: shown, not counted","Check Level"))))
A89: =LEFT(B89, FIND("-", B89) - 1) | B89: PROS-URAINCOME | C89: Annual URA Income as a rate of growth - broken out individually by URA and total | D89: Key Service | E89: ks9 | F89: =IF(E89="","",IFERROR(IF(INDEX('Dashboard Items'!$B$2:$B$495,MATCH(E89,'Dashboard Items'!$A$2:$A$495,0))="Objective","Objectives go in the next column",IF(OR(D89="",INDEX('Dashboard Items'!$B$2:$B$495,MATCH(E89,'Dashboard Items'!$A$2:$A$495,0))=D89),INDEX('Dashboard Items'!$C$2:$C$495,MATCH(E89,'Dashboard Items'!$A$2:$A$495,0)),"Level does not match ID")),"ID not found")) | G89: p100, p40 | H89: =IF(G89="","",IF(ISNUMBER(SEARCH(",",G89)),"Several items (the script lists them)",IFERROR(INDEX('Dashboard Items'!$B$2:$B$495,MATCH(G89,'Dashboard Items'!$A$2:$A$495,0))&": "&INDEX('Dashboard Items'!$C$2:$C$495,MATCH(G89,'Dashboard Items'!$A$2:$A$495,0)),"ID not found"))) | I89: percent | J89: 2 | K89: Yes | L89: Target | M89: 0 | N89: 0 | O89: Yes | P89: Every year | Q89: Prosperity Officer | U89: =IF(B89="","",IF(IF(D89<>"",D89,IFERROR(INDEX('Dashboard Items'!$B$2:$B$495,MATCH(E89,'Dashboard Items'!$A$2:$A$495,0)),""))="Key Service",IF(O89="No","Key Service: shown, not counted","Counts in Key Service gauge"),IF(IF(D89<>"",D89,IFERROR(INDEX('Dashboard Items'!$B$2:$B$495,MATCH(E89,'Dashboard Items'!$A$2:$A$495,0)),""))="Program",IF(ISNUMBER(SEARCH("ks",G89)),IF(O89="No","Program, also at Key Service: not counted","Counts in Key Service gauge + sets Program chip"),IF(O89="No","Program: shown, no status chip","Sets Program status chip")),IF(IF(D89<>"",D89,IFERROR(INDEX('Dashboard Items'!$B$2:$B$495,MATCH(E89,'Dashboard Items'!$A$2:$A$495,0)),""))="Work System","Work System: shown, not counted","Check Level"))))
A90: =LEFT(B90, FIND("-", B90) - 1) | B90: PROS-VISITORSPEND | C90: Visitor Spend (Annual Year over Year) | D90: Program | E90: p40 | F90: =IF(E90="","",IFERROR(IF(INDEX('Dashboard Items'!$B$2:$B$495,MATCH(E90,'Dashboard Items'!$A$2:$A$495,0))="Objective","Objectives go in the next column",IF(OR(D90="",INDEX('Dashboard Items'!$B$2:$B$495,MATCH(E90,'Dashboard Items'!$A$2:$A$495,0))=D90),INDEX('Dashboard Items'!$C$2:$C$495,MATCH(E90,'Dashboard Items'!$A$2:$A$495,0)),"Level does not match ID")),"ID not found")) | G90: p43, ks9 | H90: =IF(G90="","",IF(ISNUMBER(SEARCH(",",G90)),"Several items (the script lists them)",IFERROR(INDEX('Dashboard Items'!$B$2:$B$495,MATCH(G90,'Dashboard Items'!$A$2:$A$495,0))&": "&INDEX('Dashboard Items'!$C$2:$C$495,MATCH(G90,'Dashboard Items'!$A$2:$A$495,0)),"ID not found"))) | I90: number | J90: 2 | K90: Yes | L90: Target | M90: 0 | N90: 0 | O90: Yes | P90: Every year | Q90: Prosperity Officer | U90: =IF(B90="","",IF(IF(D90<>"",D90,IFERROR(INDEX('Dashboard Items'!$B$2:$B$495,MATCH(E90,'Dashboard Items'!$A$2:$A$495,0)),""))="Key Service",IF(O90="No","Key Service: shown, not counted","Counts in Key Service gauge"),IF(IF(D90<>"",D90,IFERROR(INDEX('Dashboard Items'!$B$2:$B$495,MATCH(E90,'Dashboard Items'!$A$2:$A$495,0)),""))="Program",IF(ISNUMBER(SEARCH("ks",G90)),IF(O90="No","Program, also at Key Service: not counted","Counts in Key Service gauge + sets Program chip"),IF(O90="No","Program: shown, no status chip","Sets Program status chip")),IF(IF(D90<>"",D90,IFERROR(INDEX('Dashboard Items'!$B$2:$B$495,MATCH(E90,'Dashboard Items'!$A$2:$A$495,0)),""))="Work System","Work System: shown, not counted","Check Level"))))
A91: =LEFT(B91, FIND("-", B91) - 1) | B91: PROS-WELCOMECENT | C91: Welcome Center Door Count | D91: Program | E91: p40 | F91: =IF(E91="","",IFERROR(IF(INDEX('Dashboard Items'!$B$2:$B$495,MATCH(E91,'Dashboard Items'!$A$2:$A$495,0))="Objective","Objectives go in the next column",IF(OR(D91="",INDEX('Dashboard Items'!$B$2:$B$495,MATCH(E91,'Dashboard Items'!$A$2:$A$495,0))=D91),INDEX('Dashboard Items'!$C$2:$C$495,MATCH(E91,'Dashboard Items'!$A$2:$A$495,0)),"Level does not match ID")),"ID not found")) | G91: p43 | H91: =IF(G91="","",IF(ISNUMBER(SEARCH(",",G91)),"Several items (the script lists them)",IFERROR(INDEX('Dashboard Items'!$B$2:$B$495,MATCH(G91,'Dashboard Items'!$A$2:$A$495,0))&": "&INDEX('Dashboard Items'!$C$2:$C$495,MATCH(G91,'Dashboard Items'!$A$2:$A$495,0)),"ID not found"))) | I91: number | J91: 2 | K91: Yes | L91: Target | M91: 0 | N91: 0 | O91: Yes | P91: Every year | Q91: Prosperity Officer | U91: =IF(B91="","",IF(IF(D91<>"",D91,IFERROR(INDEX('Dashboard Items'!$B$2:$B$495,MATCH(E91,'Dashboard Items'!$A$2:$A$495,0)),""))="Key Service",IF(O91="No","Key Service: shown, not counted","Counts in Key Service gauge"),IF(IF(D91<>"",D91,IFERROR(INDEX('Dashboard Items'!$B$2:$B$495,MATCH(E91,'Dashboard Items'!$A$2:$A$495,0)),""))="Program",IF(ISNUMBER(SEARCH("ks",G91)),IF(O91="No","Program, also at Key Service: not counted","Counts in Key Service gauge + sets Program chip"),IF(O91="No","Program: shown, no status chip","Sets Program status chip")),IF(IF(D91<>"",D91,IFERROR(INDEX('Dashboard Items'!$B$2:$B$495,MATCH(E91,'Dashboard Items'!$A$2:$A$495,0)),""))="Work System","Work System: shown, not counted","Check Level"))))
A92: =LEFT(B92, FIND("-", B92) - 1) | B92: TRAN-BIKEANDSWLINFT | C92: Linear feet/miles of bike lanes and sidewalks by road classification | D92: Program | E92: p71 | F92: =IF(E92="","",IFERROR(IF(INDEX('Dashboard Items'!$B$2:$B$495,MATCH(E92,'Dashboard Items'!$A$2:$A$495,0))="Objective","Objectives go in the next column",IF(OR(D92="",INDEX('Dashboard Items'!$B$2:$B$495,MATCH(E92,'Dashboard Items'!$A$2:$A$495,0))=D92),INDEX('Dashboard Items'!$C$2:$C$495,MATCH(E92,'Dashboard Items'!$A$2:$A$495,0)),"Level does not match ID")),"ID not found")) | G92: ks14 | H92: =IF(G92="","",IF(ISNUMBER(SEARCH(",",G92)),"Several items (the script lists them)",IFERROR(INDEX('Dashboard Items'!$B$2:$B$495,MATCH(G92,'Dashboard Items'!$A$2:$A$495,0))&": "&INDEX('Dashboard Items'!$C$2:$C$495,MATCH(G92,'Dashboard Items'!$A$2:$A$495,0)),"ID not found"))) | I92: number | J92: 2 | K92: Yes | L92: Target | M92: 0 | N92: 0 | O92: Yes | P92: Every year | Q92: Multimodal Manager | U92: =IF(B92="","",IF(IF(D92<>"",D92,IFERROR(INDEX('Dashboard Items'!$B$2:$B$495,MATCH(E92,'Dashboard Items'!$A$2:$A$495,0)),""))="Key Service",IF(O92="No","Key Service: shown, not counted","Counts in Key Service gauge"),IF(IF(D92<>"",D92,IFERROR(INDEX('Dashboard Items'!$B$2:$B$495,MATCH(E92,'Dashboard Items'!$A$2:$A$495,0)),""))="Program",IF(ISNUMBER(SEARCH("ks",G92)),IF(O92="No","Program, also at Key Service: not counted","Counts in Key Service gauge + sets Program chip"),IF(O92="No","Program: shown, no status chip","Sets Program status chip")),IF(IF(D92<>"",D92,IFERROR(INDEX('Dashboard Items'!$B$2:$B$495,MATCH(E92,'Dashboard Items'!$A$2:$A$495,0)),""))="Work System","Work System: shown, not counted","Check Level"))))
A93: =LEFT(B93, FIND("-", B93) - 1) | B93: TRAN-BIKEPEDCOUNT | C93: Bi-annual bike and pedestrian counts | D93: Program | E93: p71 | F93: =IF(E93="","",IFERROR(IF(INDEX('Dashboard Items'!$B$2:$B$495,MATCH(E93,'Dashboard Items'!$A$2:$A$495,0))="Objective","Objectives go in the next column",IF(OR(D93="",INDEX('Dashboard Items'!$B$2:$B$495,MATCH(E93,'Dashboard Items'!$A$2:$A$495,0))=D93),INDEX('Dashboard Items'!$C$2:$C$495,MATCH(E93,'Dashboard Items'!$A$2:$A$495,0)),"Level does not match ID")),"ID not found")) | H93: =IF(G93="","",IF(ISNUMBER(SEARCH(",",G93)),"Several items (the script lists them)",IFERROR(INDEX('Dashboard Items'!$B$2:$B$495,MATCH(G93,'Dashboard Items'!$A$2:$A$495,0))&": "&INDEX('Dashboard Items'!$C$2:$C$495,MATCH(G93,'Dashboard Items'!$A$2:$A$495,0)),"ID not found"))) | I93: number | J93: 0 | K93: Yes | P93: Every 2 years | Q93: Multimodal Manager | R93: City bike and pedestrian counts (Consolidated Count Data, 2009–2025) | S93: Average number of people walking and biking at each count location during the morning (7–9 am) and afternoon (4–6 pm) peak counts, added up across all locations. Higher numbers mean more people are walking and biking. | T93: Total of average bike and pedestrian counts at 11 intersections, counted every two years. Shown from 2015, the first year all 11 locations were counted. | U93: =IF(B93="","",IF(IF(D93<>"",D93,IFERROR(INDEX('Dashboard Items'!$B$2:$B$495,MATCH(E93,'Dashboard Items'!$A$2:$A$495,0)),""))="Key Service",IF(O93="No","Key Service: shown, not counted","Counts in Key Service gauge"),IF(IF(D93<>"",D93,IFERROR(INDEX('Dashboard Items'!$B$2:$B$495,MATCH(E93,'Dashboard Items'!$A$2:$A$495,0)),""))="Program",IF(ISNUMBER(SEARCH("ks",G93)),IF(O93="No","Program, also at Key Service: not counted","Counts in Key Service gauge + sets Program chip"),IF(O93="No","Program: shown, no status chip","Sets Program status chip")),IF(IF(D93<>"",D93,IFERROR(INDEX('Dashboard Items'!$B$2:$B$495,MATCH(E93,'Dashboard Items'!$A$2:$A$495,0)),""))="Work System","Work System: shown, not counted","Check Level"))))
A94: =LEFT(B94, FIND("-", B94) - 1) | B94: TRAN-CITATIONCLOSE | C94: Reasons for citations closure | D94: Program | E94: p75 | F94: =IF(E94="","",IFERROR(IF(INDEX('Dashboard Items'!$B$2:$B$495,MATCH(E94,'Dashboard Items'!$A$2:$A$495,0))="Objective","Objectives go in the next column",IF(OR(D94="",INDEX('Dashboard Items'!$B$2:$B$495,MATCH(E94,'Dashboard Items'!$A$2:$A$495,0))=D94),INDEX('Dashboard Items'!$C$2:$C$495,MATCH(E94,'Dashboard Items'!$A$2:$A$495,0)),"Level does not match ID")),"ID not found")) | H94: =IF(G94="","",IF(ISNUMBER(SEARCH(",",G94)),"Several items (the script lists them)",IFERROR(INDEX('Dashboard Items'!$B$2:$B$495,MATCH(G94,'Dashboard Items'!$A$2:$A$495,0))&": "&INDEX('Dashboard Items'!$C$2:$C$495,MATCH(G94,'Dashboard Items'!$A$2:$A$495,0)),"ID not found"))) | I94: number | J94: 0 | K94: Yes | L94: Target | M94: 0 | N94: 0 | O94: Yes | P94: Every year | Q94: Parking Manager | R94: Parking citation closed reasons, yearly (Citation_Metrics_and_Data_.xlsx, 2018–2025) | S94: Parking citations closed without payment each year, by the reason they were closed (for example a warning, a registration issue or a meter malfunction). | T94: "Paid Wrong Plate (Mobile)" was first tracked in 2025. 2026 is not yet entered. No target has been set. | U94: =IF(B94="","",IF(IF(D94<>"",D94,IFERROR(INDEX('Dashboard Items'!$B$2:$B$495,MATCH(E94,'Dashboard Items'!$A$2:$A$495,0)),""))="Key Service",IF(O94="No","Key Service: shown, not counted","Counts in Key Service gauge"),IF(IF(D94<>"",D94,IFERROR(INDEX('Dashboard Items'!$B$2:$B$495,MATCH(E94,'Dashboard Items'!$A$2:$A$495,0)),""))="Program",IF(ISNUMBER(SEARCH("ks",G94)),IF(O94="No","Program, also at Key Service: not counted","Counts in Key Service gauge + sets Program chip"),IF(O94="No","Program: shown, no status chip","Sets Program status chip")),IF(IF(D94<>"",D94,IFERROR(INDEX('Dashboard Items'!$B$2:$B$495,MATCH(E94,'Dashboard Items'!$A$2:$A$495,0)),""))="Work System","Work System: shown, not counted","Check Level"))))
A95: =LEFT(B95, FIND("-", B95) - 1) | B95: TRAN-COMPSCORE | C95: Parking compliance count for the central business district | D95: Program | E95: p75 | F95: =IF(E95="","",IFERROR(IF(INDEX('Dashboard Items'!$B$2:$B$495,MATCH(E95,'Dashboard Items'!$A$2:$A$495,0))="Objective","Objectives go in the next column",IF(OR(D95="",INDEX('Dashboard Items'!$B$2:$B$495,MATCH(E95,'Dashboard Items'!$A$2:$A$495,0))=D95),INDEX('Dashboard Items'!$C$2:$C$495,MATCH(E95,'Dashboard Items'!$A$2:$A$495,0)),"Level does not match ID")),"ID not found")) | H95: =IF(G95="","",IF(ISNUMBER(SEARCH(",",G95)),"Several items (the script lists them)",IFERROR(INDEX('Dashboard Items'!$B$2:$B$495,MATCH(G95,'Dashboard Items'!$A$2:$A$495,0))&": "&INDEX('Dashboard Items'!$C$2:$C$495,MATCH(G95,'Dashboard Items'!$A$2:$A$495,0)),"ID not found"))) | I95: percent | J95: 1 | K95: Yes | L95: Target | M95: 0 | N95: 0 | O95: Yes | P95: Every year | Q95: Parking Manager | R95: Downtown on-street meter compliance counts (Meter_Compliance_Count.xlsx, about five counts a month, 2021–Sep 2026) | S95: Share of cars parked at downtown meters that had paid or were exempt (accessible, government or free spaces) when counted. Higher is better. | T95: Target: 95% compliance; 100% is not realistic. Each year combines all counts taken that year, about 60 count days. 2026 covers January–September only (year to date). | U95: =IF(B95="","",IF(IF(D95<>"",D95,IFERROR(INDEX('Dashboard Items'!$B$2:$B$495,MATCH(E95,'Dashboard Items'!$A$2:$A$495,0)),""))="Key Service",IF(O95="No","Key Service: shown, not counted","Counts in Key Service gauge"),IF(IF(D95<>"",D95,IFERROR(INDEX('Dashboard Items'!$B$2:$B$495,MATCH(E95,'Dashboard Items'!$A$2:$A$495,0)),""))="Program",IF(ISNUMBER(SEARCH("ks",G95)),IF(O95="No","Program, also at Key Service: not counted","Counts in Key Service gauge + sets Program chip"),IF(O95="No","Program: shown, no status chip","Sets Program status chip")),IF(IF(D95<>"",D95,IFERROR(INDEX('Dashboard Items'!$B$2:$B$495,MATCH(E95,'Dashboard Items'!$A$2:$A$495,0)),""))="Work System","Work System: shown, not counted","Check Level"))))
A96: =LEFT(B96, FIND("-", B96) - 1) | B96: TRAN-CRASHDATA | C96: Crash data | D96: Program | E96: p71 | F96: =IF(E96="","",IFERROR(IF(INDEX('Dashboard Items'!$B$2:$B$495,MATCH(E96,'Dashboard Items'!$A$2:$A$495,0))="Objective","Objectives go in the next column",IF(OR(D96="",INDEX('Dashboard Items'!$B$2:$B$495,MATCH(E96,'Dashboard Items'!$A$2:$A$495,0))=D96),INDEX('Dashboard Items'!$C$2:$C$495,MATCH(E96,'Dashboard Items'!$A$2:$A$495,0)),"Level does not match ID")),"ID not found")) | G96: ks14 | H96: =IF(G96="","",IF(ISNUMBER(SEARCH(",",G96)),"Several items (the script lists them)",IFERROR(INDEX('Dashboard Items'!$B$2:$B$495,MATCH(G96,'Dashboard Items'!$A$2:$A$495,0))&": "&INDEX('Dashboard Items'!$C$2:$C$495,MATCH(G96,'Dashboard Items'!$A$2:$A$495,0)),"ID not found"))) | I96: number | J96: 0 | K96: No | L96: Target | M96: 0 | N96: 0 | O96: Yes | P96: Every year | Q96: Multimodal Manager | S96: Number of traffic crashes in which someone was injured or killed each fiscal year, including crashes involving pedestrians. | T96: Target: 10% fewer injury and fatal crashes than the previous year. Benchmark: 40.5 crashes, 10% below 2023. The approach follows Vision Zero principles: finding high-risk locations and underlying risk factors, and using proven fixes such as traffic calming, protected crossings and enforcement. | U96: =IF(B96="","",IF(IF(D96<>"",D96,IFERROR(INDEX('Dashboard Items'!$B$2:$B$495,MATCH(E96,'Dashboard Items'!$A$2:$A$495,0)),""))="Key Service",IF(O96="No","Key Service: shown, not counted","Counts in Key Service gauge"),IF(IF(D96<>"",D96,IFERROR(INDEX('Dashboard Items'!$B$2:$B$495,MATCH(E96,'Dashboard Items'!$A$2:$A$495,0)),""))="Program",IF(ISNUMBER(SEARCH("ks",G96)),IF(O96="No","Program, also at Key Service: not counted","Counts in Key Service gauge + sets Program chip"),IF(O96="No","Program: shown, no status chip","Sets Program status chip")),IF(IF(D96<>"",D96,IFERROR(INDEX('Dashboard Items'!$B$2:$B$495,MATCH(E96,'Dashboard Items'!$A$2:$A$495,0)),""))="Work System","Work System: shown, not counted","Check Level"))))
A97: =LEFT(B97, FIND("-", B97) - 1) | B97: TRAN-CUSTSAT | C97: Customer Satisfaction Ridership Survey | D97: Program | E97: p69 | F97: =IF(E97="","",IFERROR(IF(INDEX('Dashboard Items'!$B$2:$B$495,MATCH(E97,'Dashboard Items'!$A$2:$A$495,0))="Objective","Objectives go in the next column",IF(OR(D97="",INDEX('Dashboard Items'!$B$2:$B$495,MATCH(E97,'Dashboard Items'!$A$2:$A$495,0))=D97),INDEX('Dashboard Items'!$C$2:$C$495,MATCH(E97,'Dashboard Items'!$A$2:$A$495,0)),"Level does not match ID")),"ID not found"))
A98: =LEFT(B98, FIND("-", B98) - 1) | B98: TRAN-DEPENDENCY | C98: Transit Dependency | D98: Program | E98: p73 | F98: =IF(E98="","",IFERROR(IF(INDEX('Dashboard Items'!$B$2:$B$495,MATCH(E98,'Dashboard Items'!$A$2:$A$495,0))="Objective","Objectives go in the next column",IF(OR(D98="",INDEX('Dashboard Items'!$B$2:$B$495,MATCH(E98,'Dashboard Items'!$A$2:$A$495,0))=D98),INDEX('Dashboard Items'!$C$2:$C$495,MATCH(E98,'Dashboard Items'!$A$2:$A$495,0)),"Level does not match ID")),"ID not found")) | G98: ks14
A99: =LEFT(B99, FIND("-", B99) - 1) | B99: TRAN-DESTANDORIGIN | C99: Destination and Origin | D99: Program | E99: p72 | F99: =IF(E99="","",IFERROR(IF(INDEX('Dashboard Items'!$B$2:$B$495,MATCH(E99,'Dashboard Items'!$A$2:$A$495,0))="Objective","Objectives go in the next column",IF(OR(D99="",INDEX('Dashboard Items'!$B$2:$B$495,MATCH(E99,'Dashboard Items'!$A$2:$A$495,0))=D99),INDEX('Dashboard Items'!$C$2:$C$495,MATCH(E99,'Dashboard Items'!$A$2:$A$495,0)),"Level does not match ID")),"ID not found"))
A100: =LEFT(B100, FIND("-", B100) - 1) | B100: TRAN-FAREBOX | C100: Farebox Revenue | D100: Program | E100: p74 | F100: =IF(E100="","",IFERROR(IF(INDEX('Dashboard Items'!$B$2:$B$495,MATCH(E100,'Dashboard Items'!$A$2:$A$495,0))="Objective","Objectives go in the next column",IF(OR(D100="",INDEX('Dashboard Items'!$B$2:$B$495,MATCH(E100,'Dashboard Items'!$A$2:$A$495,0))=D100),INDEX('Dashboard Items'!$C$2:$C$495,MATCH(E100,'Dashboard Items'!$A$2:$A$495,0)),"Level does not match ID")),"ID not found")) | I100: currency | J100: 0 | K100: Yes | L100: Target | M100: 0 | N100: 0 | O100: Yes | P100: Every year | R100: Durango Transit monthly ridership report (Ridership_Demographics.xlsx, Jan 2019–Sep 2026) | S100: Fare dollars collected on the fixed routes (Loop and Trolley) each year. | T100: Target: higher than the previous year. At or above last year shows On Track; below it shows Off Track. Fixed routes only; Dial-A-Ride fares were not reported. August 2022 was fare-free, so no fares were collected that month. 2026 is January–September and is compared with the same months of 2025. | U100: =IF(B100="","",IF(IF(D100<>"",D100,IFERROR(INDEX('Dashboard Items'!$B$2:$B$495,MATCH(E100,'Dashboard Items'!$A$2:$A$495,0)),""))="Key Service",IF(O100="No","Key Service: shown, not counted","Counts in Key Service gauge"),IF(IF(D100<>"",D100,IFERROR(INDEX('Dashboard Items'!$B$2:$B$495,MATCH(E100,'Dashboard Items'!$A$2:$A$495,0)),""))="Program",IF(ISNUMBER(SEARCH("ks",G100)),IF(O100="No","Program, also at Key Service: not counted","Counts in Key Service gauge + sets Program chip"),IF(O100="No","Program: shown, no status chip","Sets Program status chip")),IF(IF(D100<>"",D100,IFERROR(INDEX('Dashboard Items'!$B$2:$B$495,MATCH(E100,'Dashboard Items'!$A$2:$A$495,0)),""))="Work System","Work System: shown, not counted","Check Level"))))
...

Sheet KPI Data
A1: Dept | B1: KPI ID | C1: Period | D1: Segment | E1: Value | F1: Target | G1: Benchmark | H1: Note
A2: =LEFT(B2, FIND("-", B2) - 1) | B2: CLERK-CLICKTHRURATE | C2: X
A3: =LEFT(B3, FIND("-", B3) - 1) | B3: CLERK-QRESPRATE | C3: X
A4: =LEFT(B4, FIND("-", B4) - 1) | B4: CLERK-VOTERTURNOUT | C4: X
A5: =LEFT(B5, FIND("-", B5) - 1) | B5: CLERK-LOGICTEST | C5: X
A6: =LEFT(B6, FIND("-", B6) - 1) | B6: CLERK-CORARESPRATE | C6: 2024-Q4 | E6: 88 | F6: 90
A7: =LEFT(B7, FIND("-", B7) - 1) | B7: CLERK-AGENDAPOST | C7: 2024-Q4 | E7: 95 | F7: 90
A8: =LEFT(B8, FIND("-", B8) - 1) | B8: CLERK-LIQMARJLIC | C8: X
A9: =LEFT(B9, FIND("-", B9) - 1) | B9: CLERK-BIZLIC | C9: X
A10: =LEFT(B10, FIND("-", B10) - 1) | B10: HR-EMPENG | C10: 2022 | E10: 69 | G10: 76.6 | H10: Full-time employees only
A11: =LEFT(B11, FIND("-", B11) - 1) | B11: HR-EMPENG | C11: 2024 | E11: 81.3 | G11: 75.1 | H11: Full-time employees only
A12: =LEFT(B12, FIND("-", B12) - 1) | B12: HR-EMPENG | C12: 2026 | E12: 79.3 | G12: 76.6
A13: =LEFT(B13, FIND("-", B13) - 1) | B13: HR-EMPENG | C13: 2026 | D13: Full-time | E13: 79.9
A14: =LEFT(B14, FIND("-", B14) - 1) | B14: HR-EMPENG | C14: 2026 | D14: PT/Seasonal | E14: 78.2
A15: =LEFT(B15, FIND("-", B15) - 1) | B15: HR-EMPENG
A16: =LEFT(B16, FIND("-", B16) - 1) | B16: HR-TIMETOHIRE
A17: =LEFT(B17, FIND("-", B17) - 1) | B17: HR-TURNRATE | C17: 2021 | E17: 20.34 | F17: 20 | G17: 18
A18: =LEFT(B18, FIND("-", B18) - 1) | B18: HR-CFT
A19: =LEFT(B19, FIND("-", B19) - 1) | B19: HR-TUITIONREIMB
A20: =LEFT(B20, FIND("-", B20) - 1) | B20: HR-PROFDEV
A21: =LEFT(B21, FIND("-", B21) - 1) | B21: HR-JOBPOSTVIEW
A22: =LEFT(B22, FIND("-", B22) - 1) | B22: HR-APPPERREC
A23: =LEFT(B23, FIND("-", B23) - 1) | B23: HR-TRAFFICSOURCE
A24: =LEFT(B24, FIND("-", B24) - 1) | B24: HR-OFFICERACC
A25: =LEFT(B25, FIND("-", B25) - 1) | B25: HR-VACRATE
A26: =LEFT(B26, FIND("-", B26) - 1) | B26: HR-RETENTION
A27: =LEFT(B27, FIND("-", B27) - 1) | B27: HR-INTPROMO | C27: 2022 | E27: 49.3 | F27: 10 | G27: 6
A28: =LEFT(B28, FIND("-", B28) - 1) | B28: HR-COMPANDBEN
A29: =LEFT(B29, FIND("-", B29) - 1) | B29: HR-DOTCOMPSCORE
A30: =LEFT(B30, FIND("-", B30) - 1) | B30: HR-EMOD
A31: =LEFT(B31, FIND("-", B31) - 1) | B31: HR-LOSSRUNREPORT
A32: =LEFT(B32, FIND("-", B32) - 1) | B32: HR-PROPCASCLAIM
A33: =LEFT(B33, FIND("-", B33) - 1) | B33: HR-ACCREVBOARD
A34: =LEFT(B34, FIND("-", B34) - 1) | B34: HR-SAFETYTRAINING
A35: =LEFT(B35, FIND("-", B35) - 1) | B35: IT-UPTIME | C35: 2020 | E35: 99.89 | F35: 99.99 | G35: 99.999
A36: =LEFT(B36, FIND("-", B36) - 1) | B36: IT-UPTIME | C36: 2021 | E36: 99.98 | F36: 99.99 | G36: 99.999
A37: =LEFT(B37, FIND("-", B37) - 1) | B37: IT-UPTIME | C37: 2022 | E37: 99.92 | F37: 99.99 | G37: 99.999
A38: =LEFT(B38, FIND("-", B38) - 1) | B38: IT-UPTIME | C38: 2023 | E38: 99.91 | F38: 99.99 | G38: 99.999
A39: =LEFT(B39, FIND("-", B39) - 1) | B39: IT-UPTIME | C39: 2024 | E39: 99.79 | F39: 99.99 | G39: 99.999
A40: =LEFT(B40, FIND("-", B40) - 1) | B40: IT-UPTIME | C40: 2025 | E40: 99.85 | F40: 99.99 | G40: 99.999
A41: =LEFT(B41, FIND("-", B41) - 1) | B41: IT-PITSURV | C41: 2022 | E41: 80 | F41: 85
A42: =LEFT(B42, FIND("-", B42) - 1) | B42: IT-PITSURV | C42: 2023 | E42: 89.86 | F42: 85
A43: =LEFT(B43, FIND("-", B43) - 1) | B43: IT-PITSURV | C43: 2024 | E43: 85.71 | F43: 85
A44: =LEFT(B44, FIND("-", B44) - 1) | B44: IT-PITSURV | C44: 2025 | E44: 89.97 | F44: 85
A45: =LEFT(B45, FIND("-", B45) - 1) | B45: IT-TIXSLA | C45: 2022 | D45: Minor | F45: 95 | G45: 100
A46: =LEFT(B46, FIND("-", B46) - 1) | B46: IT-TIXSLA | C46: 2022 | D46: Normal | F46: 95 | G46: 100
A47: =LEFT(B47, FIND("-", B47) - 1) | B47: IT-TIXSLA | C47: 2022 | D47: Urgent | F47: 95 | G47: 100
A48: =LEFT(B48, FIND("-", B48) - 1) | B48: IT-TIXSLA | C48: 2022 | D48: Critical | F48: 95 | G48: 100
A49: =LEFT(B49, FIND("-", B49) - 1) | B49: IT-TIXSLA | C49: 2023 | D49: Minor | F49: 95 | G49: 100
A50: =LEFT(B50, FIND("-", B50) - 1) | B50: IT-TIXSLA | C50: 2023 | D50: Normal | F50: 95 | G50: 100
A51: =LEFT(B51, FIND("-", B51) - 1) | B51: IT-TIXSLA | C51: 2023 | D51: Urgent | F51: 95 | G51: 100
A52: =LEFT(B52, FIND("-", B52) - 1) | B52: IT-TIXSLA | C52: 2023 | D52: Critical | F52: 95 | G52: 100
A53: =LEFT(B53, FIND("-", B53) - 1) | B53: IT-TIXSLA | C53: 2024 | D53: Minor | F53: 95 | G53: 100
A54: =LEFT(B54, FIND("-", B54) - 1) | B54: IT-TIXSLA | C54: 2024 | D54: Normal | F54: 95 | G54: 100
A55: =LEFT(B55, FIND("-", B55) - 1) | B55: IT-TIXSLA | C55: 2024 | D55: Urgent | F55: 95 | G55: 100
A56: =LEFT(B56, FIND("-", B56) - 1) | B56: IT-TIXSLA | C56: 2024 | D56: Critical | F56: 95 | G56: 100
... A60: =LEFT(B60, FIND("-", B60) - 1) | B60: IT-TIXSLA | C60: 2025 | D60: Critical | F60: 95 | G60: 100
A61: =LEFT(B61, FIND("-", B61) - 1) | B61: IT-PHISHRATE | C61: 2020-Q1 | E61: 8.9 | F61: 3.9 | G61: 3.9
A62: =LEFT(B62, FIND("-", B62) - 1) | B62: IT-PHISHRATE | C62: 2020-Q2 | E62: 2.4 | F62: 3.9 | G62: 3.9
A63: =LEFT(B63, FIND("-", B63) - 1) | B63: IT-PHISHRATE | C63: 2022-Q2 | E63: 1.05 | F63: 3.9 | G63: 3.9
A64: =LEFT(B64, FIND("-", B64) - 1) | B64: IT-PHISHRATE | C64: 2022-Q3 | E64: 0.9 | F64: 3.9 | G64: 3.9
A65: =LEFT(B65, FIND("-", B65) - 1) | B65: IT-PHISHRATE | C65: 2022-Q4 | E65: 0.63333333 | F65: 3.9 | G65: 3.9
A66: =LEFT(B66, FIND("-", B66) - 1) | B66: IT-PHISHRATE | C66: 2023-Q1 | E66: 0.7 | F66: 3.9 | G66: 3.9
A67: =LEFT(B67, FIND("-", B67) - 1) | B67: IT-PHISHRATE | C67: 2023-Q2 | E67: 1.1333333 | F67: 3.9 | G67: 3.9
A68: =LEFT(B68, FIND("-", B68) - 1) | B68: IT-PHISHRATE | C68: 2023-Q3 | E68: 0.56666667 | F68: 3.9 | G68: 3.9
A69: =LEFT(B69, FIND("-", B69) - 1) | B69: IT-PHISHRATE | C69: 2023-Q4 | E69: 0.83333333 | F69: 3.9 | G69: 3.9
A70: =LEFT(B70, FIND("-", B70) - 1) | B70: IT-PHISHRATE | C70: 2024-Q1 | E70: 1.5333333 | F70: 3.9 | G70: 3.9
A71: =LEFT(B71, FIND("-", B71) - 1) | B71: IT-PHISHRATE | C71: 2024-Q2 | E71: 1.1 | F71: 3.9 | G71: 3.9
A72: =LEFT(B72, FIND("-", B72) - 1) | B72: IT-PHISHRATE | C72: 2024-Q3 | E72: 0.66666667 | F72: 3.9 | G72: 3.9
... A85: =LEFT(B85, FIND("-", B85) - 1) | B85: LIB-CIRCULATION | C85: 2025 | E85: 112 | F85: 150 | G85: 150
A86: =LEFT(B86, FIND("-", B86) - 1) | B86: LIB-CIRCULATION | C86: 2021 | D86: Digital | E86: 55 | F86: 50 | G86: 50
A87: =LEFT(B87, FIND("-", B87) - 1) | B87: LIB-CIRCULATION | C87: 2022 | D87: Digital | E87: 48 | F87: 50 | G87: 50
A88: =LEFT(B88, FIND("-", B88) - 1) | B88: LIB-CIRCULATION | C88: 2023 | D88: Digital | E88: 25 | F88: 50 | G88: 50
A89: =LEFT(B89, FIND("-", B89) - 1) | B89: LIB-CIRCULATION | C89: 2024 | D89: Digital | E89: 68 | F89: 50 | G89: 50
A90: =LEFT(B90, FIND("-", B90) - 1) | B90: LIB-CIRCULATION | C90: 2025 | D90: Digital | E90: 54 | F90: 50 | G90: 50
A91: =LEFT(B91, FIND("-", B91) - 1) | B91: LIB-CIRCULATION | C91: 2021 | D91: Physical | E91: 88 | F91: 50 | G91: 50
A92: =LEFT(B92, FIND("-", B92) - 1) | B92: LIB-CIRCULATION | C92: 2022 | D92: Physical | E92: 98 | F92: 50 | G92: 50
A93: =LEFT(B93, FIND("-", B93) - 1) | B93: LIB-CIRCULATION | C93: 2023 | D93: Physical | E93: 22 | F93: 50 | G93: 50
A94: =LEFT(B94, FIND("-", B94) - 1) | B94: LIB-CIRCULATION | C94: 2024 | D94: Physical | E94: 54 | F94: 50 | G94: 50
A95: =LEFT(B95, FIND("-", B95) - 1) | B95: LIB-CIRCULATION | C95: 2025 | D95: Physical | E95: 58 | F95: 50 | G95: 50
A96: =LEFT(B96, FIND("-", B96) - 1) | B96: LIB-ROOMRENTALS | C96: X
A97: =LEFT(B97, FIND("-", B97) - 1) | B97: LIB-COMPANDWIFI | C97: X
A98: =LEFT(B98, FIND("-", B98) - 1) | B98: LIB-REFQUEST | C98: X
A99: =LEFT(B99, FIND("-", B99) - 1) | B99: LIB-SOCIALENG | C99: X
A100: =LEFT(B100, FIND("-", B100) - 1) | B100: LIB-PATRONPPROG | C100: X
A101: =LEFT(B101, FIND("-", B101) - 1) | B101: LIB-PROGATTEND | C101: X
A102: =LEFT(B102, FIND("-", B102) - 1) | B102: LIB-OUTREACHCON | C102: X
A103: =LEFT(B103, FIND("-", B103) - 1) | B103: LIB-VISITS | C103: 2020 | E103: 65014 | F103: 71834 | G103: 62464
A104: =LEFT(B104, FIND("-", B104) - 1) | B104: LIB-VISITS | C104: 2021 | E104: 103774 | F104: 102033 | G104: 88724
A105: =LEFT(B105, FIND("-", B105) - 1) | B105: LIB-VISITS | C105: 2022 | E105: 211580 | F105: 150513 | G105: 130881
A106: =LEFT(B106, FIND("-", B106) - 1) | B106: LIB-VISITS | C106: 2023 | E106: 280116 | F106: 173234 | G106: 150638
A107: =LEFT(B107, FIND("-", B107) - 1) | B107: LIB-VISITS | C107: 2024 | E107: 287958 | F107: 197111 | G107: 171401
A108: =LEFT(B108, FIND("-", B108) - 1) | B108: LIB-VISITS | C108: 2025 | E108: 293189 | F108: 201250 | G108: 175000
A109: =LEFT(B109, FIND("-", B109) - 1) | B109: PIO-ENGRATE | C109: 2021 | D109: Instagram | E109: 4.11 | F109: 5.9 | G109: 2.6
A110: =LEFT(B110, FIND("-", B110) - 1) | B110: PIO-ENGRATE | C110: 2022 | D110: Instagram | E110: 4.2 | F110: 5.9 | G110: 2.6
A111: =LEFT(B111, FIND("-", B111) - 1) | B111: PIO-ENGRATE | C111: 2023 | D111: Instagram | E111: 5.1 | F111: 5.9 | G111: 2.6
A112: =LEFT(B112, FIND("-", B112) - 1) | B112: PIO-ENGRATE | C112: 2024 | D112: Instagram | E112: 5.7 | F112: 5.9 | G112: 2.6
A113: =LEFT(B113, FIND("-", B113) - 1) | B113: PIO-ENGRATE | C113: 2025 | D113: Instagram | E113: 3.5 | F113: 3.5 | G113: 3.5
A114: =LEFT(B114, FIND("-", B114) - 1) | B114: PIO-ENGRATE | C114: 2021 | D114: Facebook | E114: 8.4 | F114: 6.5 | G114: 2.5
A115: =LEFT(B115, FIND("-", B115) - 1) | B115: PIO-ENGRATE | C115: 2022 | D115: Facebook | E115: 6.9 | F115: 6.5 | G115: 2.5
...

Sheet Dashboard Items
A1: ID | B1: Level | C1: Name | D1: Key Service (for Programs) | E1: Work System | F1: Goal (for Objectives) | G1: Description
A2: ws1 | B2: Work System | C2: Leadership and Governance
A3: ws2 | B3: Work System | C3: Financial and Internal Services
A4: ws3 | B4: Work System | C4: Community Growth and Economic Vitality
A5: ws4 | B5: Work System | C5: Public Safety
A6: ws5 | B6: Work System | C6: Infrastructure
A7: ws6 | B7: Work System | C7: Parks, Recreation and Cultural Services
A8: ks1 | B8: Key Service | C8: Administrative Leadership & Governance | E8: Leadership and Governance
A9: ks2 | B9: Key Service | C9: City Clerk & Records Management | E9: Leadership and Governance
A10: ks3 | B10: Key Service | C10: Public Information & Community Engagement | E10: Leadership and Governance
A11: ks4 | B11: Key Service | C11: Financial Management & Accountability | E11: Financial and Internal Services
A12: ks5 | B12: Key Service | C12: Human Resources & Workforce Development | E12: Financial and Internal Services
A13: ks6 | B13: Key Service | C13: Legal Services | E13: Financial and Internal Services
A14: ks7 | B14: Key Service | C14: Information Technology Services | E14: Financial and Internal Services
A15: ks8 | B15: Key Service | C15: Community Development & Planning | E15: Community Growth and Economic Vitality
A16: ks9 | B16: Key Service | C16: Economic Prosperity & Business Support | E16: Community Growth and Economic Vitality
A17: ks10 | B17: Key Service | C17: Sustainability & Environmental Stewardship | E17: Community Growth and Economic Vitality
A18: ks11 | B18: Key Service | C18: Public Safety Services | E18: Public Safety
A19: ks12 | B19: Key Service | C19: Municipal Court | E19: Public Safety
... A26: ks20 | B26: Key Service | C26: Recreation & Community Programs | E26: Parks, Recreation and Cultural Services
A27: p2 | B27: Program | C27: Strategic Planning | D27: Administrative Leadership & Governance | E27: Leadership and Governance
A28: p3 | B28: Program | C28: Organizational Performance Management | D28: Administrative Leadership & Governance | E28: Leadership and Governance
A29: p4 | B29: Program | C29: Compliance Oversight | D29: Administrative Leadership & Governance | E29: Leadership and Governance
A30: p5 | B30: Program | C30: Customer Service | D30: Administrative Leadership & Governance | E30: Leadership and Governance
A31: p7 | B31: Program | C31: Records Management | D31: City Clerk & Records Management | E31: Leadership and Governance
A32: p8 | B32: Program | C32: Elections Administration | D32: City Clerk & Records Management | E32: Leadership and Governance
A33: p6 | B33: Program | C33: Council/Board Support | D33: City Clerk & Records Management | E33: Leadership and Governance
A34: p29 | B34: Program | C34: Licensing | D34: City Clerk & Records Management | E34: Leadership and Governance
A35: p11 | B35: Program | C35: Public Outreach | D35: Public Information & Community Engagement | E35: Leadership and Governance
A36: p12 | B36: Program | C36: Social Media | D36: Public Information & Community Engagement | E36: Leadership and Governance
A37: p13 | B37: Program | C37: Community Engagement Initiatives | D37: Public Information & Community Engagement | E37: Leadership and Governance
A38: p15 | B38: Program | C38: Budgeting & Forecasting | D38: Financial Management & Accountability | E38: Financial and Internal Services
... A126: p95 | B126: Program | C126: Community Events | D126: Recreation & Community Programs | E126: Parks, Recreation and Cultural Services
A127: g1 | B127: Goal | C127: Organizational Stewardship | G127: Organizational Stewardship addresses the key infrastructure and foundational processes in the organization that serve as a framework for success, ensuring the organization has the resources and approaches in place to support strategic and operational focus. This goal area ensures the integration of organizational efforts and critical factors for short-term success and long-term sustainability.
A128: g2 | B128: Goal | C128: Innovative Housing and Economic Development | G128: Innovative Housing & Economic Development (IHED) aims to advance the city’s housing and economic landscape through strategic partnerships and innovative solutions that bridge the affordability gap and support a multigenerational community. This goal area strives to propel economic progress by encouraging regional collaboration, entrepreneurship, and business growth, underpinned by city-supported initiatives. It also aims to enhance Durango’s unique charm and economic competitiveness by promoting community involvement, strategic infrastructure development, and robust public-private collaborations.
A129: g3 | B129: Goal | C129: Safety & Quality of Life | G129: Safety & Quality of Life (SQL) focuses on fostering a safe and vibrant community by ensuring the continuous enhancement of police, emergency response, and code enforcement services. This goal area emphasizes the importance of sustainable cultural, artistic, literary, and recreational programs that meet diverse community needs, and the ongoing stewardship of parks, trails, and natural lands to enhance the community’s quality of life.
